Workbook

Sheet CODIGOS
A1: CAJA | B1: ENVIO | C1: MONTO | D1: PESO | E1: ADUANA | F1: IMPUESTO | G1: CODIGO | H1: ESTADO | I1: FECHA ENVIO | J1: FECHA LLEGADA | K1: =TODAY() -> 46203 | L1: FECHA ESTIMADA | M1: IMPUESTO PAGADO
A2: 1 | B2: =LOOKUP(A2,ADQUISICIONES!O:O,ADQUISICIONES!P:P) -> 1 | C2: =LOOKUP(A2,ADQUISICIONES!$R$17:$R$63,ADQUISICIONES!$Y$17:$Y$63) -> 1437.8557 | D2: =LOOKUP(A2,ADQUISICIONES!$R$17:$R$63,ADQUISICIONES!$T$17:$T$63) -> 20148 | E2: TRUE | F2: =(C2*18%) -> 258.81402 | G2: CN110167833JP | H2: TRUE | I2: 45894 | J2: 45955 | K2: =J2-I2 -> 61 | L2: =I2+65 -> 45959 | M2: =SUMIF(E:E,TRUE,F:F) -> 2698.5715
A3: 2 | B3: =LOOKUP(A3,ADQUISICIONES!O:O,ADQUISICIONES!P:P) -> 2 | C3: =LOOKUP(A3,ADQUISICIONES!$R$17:$R$63,ADQUISICIONES!$Y$17:$Y$63) -> 1248.3276 | D3: =LOOKUP(A3,ADQUISICIONES!$R$17:$R$63,ADQUISICIONES!$T$17:$T$63) -> 17994 | E3: TRUE | F3: =(C3*18%) -> 224.69896 | G3: CN110110051JP | H3: TRUE | I3: 45894 | J3: 45955 | K3: =J3-I3 -> 61 | L3: =I3+65 -> 45959
A4: 3 | B4: =LOOKUP(A4,ADQUISICIONES!O:O,ADQUISICIONES!P:P) -> 2 | C4: =LOOKUP(A4,ADQUISICIONES!$R$17:$R$63,ADQUISICIONES!$Y$17:$Y$63) -> 1181.4643 | D4: =LOOKUP(A4,ADQUISICIONES!$R$17:$R$63,ADQUISICIONES!$T$17:$T$63) -> 15562 | E4: FALSE | F4: =(C4*18%) -> 212.66358 | G4: CN110593867JP | H4: TRUE | I4: 45899 | J4: 45965 | K4: =J4-I4 -> 66 | L4: =I4+65 -> 45964
A5: 4 | B5: =LOOKUP(A5,ADQUISICIONES!O:O,ADQUISICIONES!P:P) -> 5 | C5: =LOOKUP(A5,ADQUISICIONES!$R$17:$R$63,ADQUISICIONES!$Y$17:$Y$63) -> 1126.6503 | D5: =LOOKUP(A5,ADQUISICIONES!$R$17:$R$63,ADQUISICIONES!$T$17:$T$63) -> 19090 | E5: FALSE | F5: =(C5*18%) -> 202.79706 | G5: CN110868218JP | H5: TRUE | I5: 45899 | J5: 45965 | K5: =J5-I5 -> 66 | L5: =I5+65 -> 45964
A6: 5 | B6: =LOOKUP(A6,ADQUISICIONES!O:O,ADQUISICIONES!P:P) -> 6 | C6: =LOOKUP(A6,ADQUISICIONES!$R$17:$R$63,ADQUISICIONES!$Y$17:$Y$63) -> 1051.0959 | D6: =LOOKUP(A6,ADQUISICIONES!$R$17:$R$63,ADQUISICIONES!$T$17:$T$63) -> 14018 | E6: FALSE | F6: =(C6*18%) -> 189.19726 | G6: CN111297287JP | H6: TRUE | I6: 45915 | J6: 45981 | K6: =J6-I6 -> 66 | L6: =I6+65 -> 45980
A7: 6 | B7: =LOOKUP(A7,ADQUISICIONES!O:O,ADQUISICIONES!P:P) -> 7 | C7: =LOOKUP(A7,ADQUISICIONES!$R$17:$R$63,ADQUISICIONES!$Y$17:$Y$63) -> 1321.6399 | D7: =LOOKUP(A7,ADQUISICIONES!$R$17:$R$63,ADQUISICIONES!$T$17:$T$63) -> 22836 | E7: FALSE | F7: =(C7*18%) -> 237.89519 | G7: CN111293682JP | H7: TRUE | I7: 45915 | J7: 45982 | K7: =J7-I7 -> 67 | L7: =I7+65 -> 45980
A8: 7 | B8: =LOOKUP(A8,ADQUISICIONES!O:O,ADQUISICIONES!P:P) -> 8 | C8: =LOOKUP(A8,ADQUISICIONES!$R$17:$R$63,ADQUISICIONES!$Y$17:$Y$63) -> 348.1431 | D8: =LOOKUP(A8,ADQUISICIONES!$R$17:$R$63,ADQUISICIONES!$T$17:$T$63) -> 1002 | E8: FALSE | F8: =(C8*18%) -> 62.665758 | G8: RN096695531JP | H8: TRUE | I8: 45916 | J8: 45924 | K8: =J8-I8 -> 8 | L8: =I8+65 -> 45981
A9: 8 | B9: =LOOKUP(A9,ADQUISICIONES!O:O,ADQUISICIONES!P:P) -> 10 | C9: =LOOKUP(A9,ADQUISICIONES!$R$17:$R$63,ADQUISICIONES!$Y$17:$Y$63) -> 1438.1026 | D9: =LOOKUP(A9,ADQUISICIONES!$R$17:$R$63,ADQUISICIONES!$T$17:$T$63) -> 25918 | E9: FALSE | F9: =(C9*18%) -> 258.85847 | G9: CN111980519JP | H9: TRUE | I9: 45925 | J9: 45993 | K9: =J9-I9 -> 68 | L9: =I9+65 -> 45990
A10: 9 | B10: 14 | C10: =LOOKUP(A10,ADQUISICIONES!$R$17:$R$63,ADQUISICIONES!$Y$17:$Y$63) -> 1175.02 | D10: =LOOKUP(A10,ADQUISICIONES!$R$17:$R$63,ADQUISICIONES!$T$17:$T$63) -> 16178 | E10: TRUE | F10: =(C10*18%) -> 211.5036 | G10: CN112866696JP | H10: TRUE | I10: 45943 | J10: 46006 | K10: =J10-I10 -> 63 | L10: =I10+65 -> 46008
A11: 10 | B11: 11 | C11: =LOOKUP(A11,ADQUISICIONES!$R$17:$R$63,ADQUISICIONES!$Y$17:$Y$63) -> 1053.3428 | D11: =LOOKUP(A11,ADQUISICIONES!$R$17:$R$63,ADQUISICIONES!$T$17:$T$63) -> 10632 | E11: TRUE | F11: =(C11*18%) -> 189.6017 | G11: CN112692350JP | H11: TRUE | I11: 45941 | J11: 46006 | K11: =J11-I11 -> 65 | L11: =I11+65 -> 46006
A12: 11 | B12: 16 | C12: =LOOKUP(A12,ADQUISICIONES!$R$17:$R$63,ADQUISICIONES!$Y$17:$Y$63) -> 986.52891 | D12: =LOOKUP(A12,ADQUISICIONES!$R$17:$R$63,ADQUISICIONES!$T$17:$T$63) -> 10442 | E12: TRUE | F12: =(C12*18%) -> 177.5752 | G12: CN112966915JP | H12: TRUE | I12: 45941 | J12: 46006 | K12: =J12-I12 -> 65 | L12: =I12+65 -> 46006
A13: 12 | B13: 13 | C13: =LOOKUP(A13,ADQUISICIONES!$R$17:$R$63,ADQUISICIONES!$Y$17:$Y$63) -> 1080.0584 | D13: =LOOKUP(A13,ADQUISICIONES!$R$17:$R$63,ADQUISICIONES!$T$17:$T$63) -> 15170 | E13: TRUE | F13: =(C13*18%) -> 194.41051 | G13: CN113022594JP | H13: TRUE | I13: 45941 | J13: 46006 | K13: =J13-I13 -> 65 | L13: =I13+65 -> 46006
A14: 13 | B14: 17 | C14: =LOOKUP(A14,ADQUISICIONES!$R$17:$R$63,ADQUISICIONES!$Y$17:$Y$63) -> 1063.6142 | D14: =LOOKUP(A14,ADQUISICIONES!$R$17:$R$63,ADQUISICIONES!$T$17:$T$63) -> 14560 | E14: TRUE | F14: =(C14*18%) -> 191.45056 | G14: CN112745313JP | H14: TRUE | I14: 45941 | J14: 46006 | K14: =J14-I14 -> 65 | L14: =I14+65 -> 46006
A15: 14 | B15: 15 | C15: =LOOKUP(A15,ADQUISICIONES!$R$17:$R$63,ADQUISICIONES!$Y$17:$Y$63) -> 1041.9602 | D15: =LOOKUP(A15,ADQUISICIONES!$R$17:$R$63,ADQUISICIONES!$T$17:$T$63) -> 11042 | E15: TRUE | F15: =(C15*18%) -> 187.55284 | G15: CN113018056JP | H15: TRUE | I15: 45941 | J15: 46006 | K15: =J15-I15 -> 65 | L15: =I15+65 -> 46006
A16: 15 | B16: 12 | C16: =LOOKUP(A16,ADQUISICIONES!$R$17:$R$63,ADQUISICIONES!$Y$17:$Y$63) -> 1048.3552 | D16: =LOOKUP(A16,ADQUISICIONES!$R$17:$R$63,ADQUISICIONES!$T$17:$T$63) -> 9450 | E16: TRUE | F16: =(C16*18%) -> 188.70393 | G16: CN113076028JP | H16: TRUE | I16: 45941 | J16: 46006 | K16: =J16-I16 -> 65 | L16: =I16+65 -> 46006 | N16: CN116170521JP
A17: 16 | B17: 18 | C17: =LOOKUP(A17,ADQUISICIONES!$R$17:$R$63,ADQUISICIONES!$Y$17:$Y$63) -> 1225.8094 | D17: =LOOKUP(A17,ADQUISICIONES!$R$17:$R$63,ADQUISICIONES!$T$17:$T$63) -> 16574 | E17: FALSE | F17: =(C17*18%) -> 220.64569 | G17: CN112880698JP | H17: TRUE | I17: 45946 | J17: 46009 | K17: =J17-I17 -> 63 | L17: =I17+65 -> 46011
A18: 17 | B18: =LOOKUP(A18,ADQUISICIONES!O:O,ADQUISICIONES!P:P) -> 19 | C18: =LOOKUP(A18,ADQUISICIONES!$R$17:$R$63,ADQUISICIONES!$Y$17:$Y$63) -> 1294.0306 | D18: =LOOKUP(A18,ADQUISICIONES!$R$17:$R$63,ADQUISICIONES!$T$17:$T$63) -> 15602 | E18: FALSE | F18: =(C18*18%) -> 232.92551 | G18: CN115461531JP | H18: TRUE | I18: 45990 | J18: 46047 | K18: =J18-I18 -> 57 | L18: =I18+65 -> 46055 | M18: FABRIZIO
A19: 18 | B19: 20 | C19: =LOOKUP(A19,ADQUISICIONES!$R$17:$R$63,ADQUISICIONES!$Y$17:$Y$63) -> 1393.0074 | D19: =LOOKUP(A19,ADQUISICIONES!$R$17:$R$63,ADQUISICIONES!$T$17:$T$63) -> 22719 | E19: FALSE | F19: =(C19*18%) -> 250.74133 | G19: CN115298685JP | H19: TRUE | I19: 45990 | J19: 46048 | K19: =J19-I19 -> 58 | L19: =I19+65 -> 46055 | M19: JENNI
A20: 19 | B20: =LOOKUP(A20,ADQUISICIONES!O:O,ADQUISICIONES!P:P) -> 20 | C20: =LOOKUP(A20,ADQUISICIONES!$R$17:$R$63,ADQUISICIONES!$Y$17:$Y$63) -> 1159.2116 | D20: =LOOKUP(A20,ADQUISICIONES!$R$17:$R$63,ADQUISICIONES!$T$17:$T$63) -> 17138 | E20: TRUE | F20: =(C20*18%) -> 208.65808 | G20: CN115427708JP | H20: TRUE | I20: 45993 | J20: 46049 | K20: =J20-I20 -> 56 | L20: =I20+65 -> 46058 | M20: FABRIZIO
A21: 20 | B21: =LOOKUP(A21,ADQUISICIONES!O:O,ADQUISICIONES!P:P) -> 22 | C21: =LOOKUP(A21,ADQUISICIONES!$R$17:$R$63,ADQUISICIONES!$Y$17:$Y$63) -> 1491.8585 | D21: =LOOKUP(A21,ADQUISICIONES!$R$17:$R$63,ADQUISICIONES!$T$17:$T$63) -> 11890 | E21: FALSE | F21: =(C21*18%) -> 268.53453 | G21: CN115756315JP | H21: TRUE | I21: 45993 | J21: 46050 | K21: =J21-I21 -> 57 | L21: =I21+65 -> 46058 | M21: JENNI
A22: 21 | B22: =LOOKUP(A22,ADQUISICIONES!O:O,ADQUISICIONES!P:P) -> 23 | C22: =LOOKUP(A22,ADQUISICIONES!$R$17:$R$63,ADQUISICIONES!$Y$17:$Y$63) -> 1231.864 | D22: =LOOKUP(A22,ADQUISICIONES!$R$17:$R$63,ADQUISICIONES!$T$17:$T$63) -> 17597 | E22: TRUE | F22: =(C22*18%) -> 221.73553 | G22: CN116091585JP | H22: TRUE | I22: 45994 | J22: 46051 | K22: =J22-I22 -> 57 | L22: =I22+65 -> 46059 | M22: FABRIZIO
A23: 22 | B23: =LOOKUP(A23,ADQUISICIONES!O:O,ADQUISICIONES!P:P) -> 24 | C23: =LOOKUP(A23,ADQUISICIONES!$R$17:$R$63,ADQUISICIONES!$Y$17:$Y$63) -> 1146.1044 | D23: =LOOKUP(A23,ADQUISICIONES!$R$17:$R$63,ADQUISICIONES!$T$17:$T$63) -> 14436 | E23: FALSE | F23: =(C23*18%) -> 206.2988 | G23: CN116096826JP | H23: TRUE | I23: 45994 | J23: 46052 | K23: =J23-I23 -> 58 | L23: =I23+65 -> 46059 | M23: JENNI
A24: 23 | B24: 25 | C24: =LOOKUP(A24,ADQUISICIONES!$R$17:$R$63,ADQUISICIONES!$Y$17:$Y$63) -> 2390.4311 | D24: =LOOKUP(A24,ADQUISICIONES!$R$17:$R$63,ADQUISICIONES!$T$17:$T$63) -> 25978 | E24: FALSE | F24: =(C24*18%) -> 430.27761 | G24: CN116147531JP | H24: TRUE | I24: 45994 | J24: 46053 | K24: =J24-I24 -> 59 | L24: =I24+65 -> 46059 | M24: ALEX
B25: 26 | E25: TRUE | G25: CN116170521JP | H25: TRUE | I25: 45996 | J25: 46054 | K25: =J25-I25 -> 58 | L25: =I25+65 -> 46061
A26: 24 | B26: =LOOKUP(A26,ADQUISICIONES!O:O,ADQUISICIONES!P:P) -> 27 | C26: =LOOKUP(A26,ADQUISICIONES!$R$17:$R$63,ADQUISICIONES!$Y$17:$Y$63) -> 1329.8924 | D26: =LOOKUP(A26,ADQUISICIONES!$R$17:$R$63,ADQUISICIONES!$T$17:$T$63) -> 17922 | E26: FALSE | F26: =(C26*18%) -> 239.38062 | G26: CN116172995JP | H26: TRUE | I26: 45996 | J26: 46055 | K26: =J26-I26 -> 59 | L26: =I26+65 -> 46061 | M26: ALEX
A27: 25 | B27: =LOOKUP(A27,ADQUISICIONES!O:O,ADQUISICIONES!P:P) -> 28 | C27: =LOOKUP(A27,ADQUISICIONES!$R$17:$R$63,ADQUISICIONES!$Y$17:$Y$63) -> 1344.3365 | D27: =LOOKUP(A27,ADQUISICIONES!$R$17:$R$63,ADQUISICIONES!$T$17:$T$63) -> 20506 | E27: FALSE | F27: =(C27*18%) -> 241.98057 | G27: CN116006975JP | H27: TRUE | I27: 45996 | J27: 46056 | K27: =J27-I27 -> 60 | L27: =I27+65 -> 46061 | M27: JENNI
A28: 26 | B28: =LOOKUP(A28,ADQUISICIONES!O:O,ADQUISICIONES!P:P) -> 29 | C28: =LOOKUP(A28,ADQUISICIONES!$R$17:$R$63,ADQUISICIONES!$Y$17:$Y$63) -> 1251.126 | D28: =LOOKUP(A28,ADQUISICIONES!$R$17:$R$63,ADQUISICIONES!$T$17:$T$63) -> 17366 | E28: FALSE | F28: =(C28*18%) -> 225.20267 | G28: CN118380783JP | H28: TRUE | I28: 46041 | J28: 46111 | K28: =J28-I28 -> 70 | L28: =I28+65 -> 46106
A29: 27 | B29: 30 | C29: =LOOKUP(A29,ADQUISICIONES!R43:R89,ADQUISICIONES!Y43:Y89) -> 1304.2201 | D29: =LOOKUP(A29,ADQUISICIONES!$R$17:$R$63,ADQUISICIONES!$T$17:$T$63) -> 9802 | E29: FALSE | F29: =(C29*18%) -> 234.75962 | G29: CN118380633JP | H29: TRUE | I29: 46041 | J29: 46111 | K29: =J29-I29 -> 70 | L29: =I29+65 -> 46106
A30: 28 | B30: 31 | C30: =LOOKUP(A30,ADQUISICIONES!R44:R90,ADQUISICIONES!Y44:Y90) -> 1017.0248 | D30: =LOOKUP(A30,ADQUISICIONES!$R$17:$R$63,ADQUISICIONES!$T$17:$T$63) -> 12444 | E30: FALSE | F30: =(C30*18%) -> 183.06446 | G30: CN119371712JP | H30: TRUE | I30: 46055 | J30: 46120 | K30: =J30-I30 -> 65 | L30: =I30+65 -> 46120 | M30: ALEX
A31: 29 | B31: =LOOKUP(A31,ADQUISICIONES!O:O,ADQUISICIONES!P:P) -> 31 | C31: =LOOKUP(A31,ADQUISICIONES!R45:R91,ADQUISICIONES!Y45:Y91) -> 0 | D31: =LOOKUP(A31,ADQUISICIONES!$R$17:$R$63,ADQUISICIONES!$T$17:$T$63) -> 0 | E31: FALSE | F31: =(C31*18%) -> 0 | G31: CN120084696JP | H31: TRUE | I31: 46059 | J31: 46123 | K31: =J31-I31 -> 64 | L31: =I31+65 -> 46124
A32: 30 | B32: =LOOKUP(A32,ADQUISICIONES!O:O,ADQUISICIONES!P:P) -> 31 | C32: =LOOKUP(A32,ADQUISICIONES!R46:R92,ADQUISICIONES!Y46:Y92) -> 0 | D32: =LOOKUP(A32,ADQUISICIONES!$R$17:$R$63,ADQUISICIONES!$T$17:$T$63) -> 0 | E32: FALSE | F32: =(C32*18%) -> 0 | G32: CN119974797JP | H32: TRUE | I32: 46059 | J32: 46123 | K32: =J32-I32 -> 64 | L32: =I32+65 -> 46124
A33: 31 | B33: 34 | C33: =LOOKUP(A33,ADQUISICIONES!R47:R93,ADQUISICIONES!Y47:Y93) -> 855.80152 | D33: =LOOKUP(A33,ADQUISICIONES!$R$17:$R$63,ADQUISICIONES!$T$17:$T$63) -> 10616 | E33: FALSE | F33: =(C33*18%) -> 154.04427 | G33: CN119698666JP | H33: TRUE | I33: 46059 | J33: 46123 | K33: =J33-I33 -> 64 | L33: =I33+65 -> 46124
A34: 32 | B34: 35 | C34: =LOOKUP(A34,ADQUISICIONES!R48:R94,ADQUISICIONES!Y47:Y94) -> 855.80152 | D34: =LOOKUP(A34,ADQUISICIONES!$R$17:$R$63,ADQUISICIONES!$T$17:$T$63) -> 15454 | E34: FALSE | F34: =(C34*18%) -> 154.04427 | G34: CN119981135JP | H34: TRUE | I34: 46062 | J34: 46147 | K34: =J34-I34 -> 85 | L34: =I34+65 -> 46127
A35: 33 | B35: 36 | C35: =LOOKUP(A35,ADQUISICIONES!R49:R95,ADQUISICIONES!Y48:Y95) -> 1173.4819 | D35: =LOOKUP(A35,ADQUISICIONES!$R$17:$R$63,ADQUISICIONES!$T$17:$T$63) -> 1294 | E35: TRUE | F35: =(C35*18%) -> 211.22674 | G35: CN119922429JP | H35: TRUE | I35: 46062 | J35: 46148 | K35: =J35-I35 -> 86 | L35: =I35+65 -> 46127
A36: 34 | B36: 37 | C36: =LOOKUP(A36,ADQUISICIONES!R50:R96,ADQUISICIONES!Y49:Y96) -> 814.91443 | D36: =LOOKUP(A36,ADQUISICIONES!$R$17:$R$63,ADQUISICIONES!$T$17:$T$63) -> 16204 | E36: FALSE | F36: =(C36*18%) -> 146.6846 | G36: CN119869895JP | H36: TRUE | I36: 46062 | J36: 46147 | K36: =J36-I36 -> 85 | L36: =I36+65 -> 46127
A37: 35 | B37: 38 | C37: =LOOKUP(A37,ADQUISICIONES!R51:R97,ADQUISICIONES!Y50:Y97) -> 944.4486 | D37: =LOOKUP(A37,ADQUISICIONES!$R$17:$R$63,ADQUISICIONES!$T$17:$T$63) -> 14420 | E37: FALSE | F37: =(C37*18%) -> 170.00075 | G37: CN120269559JP | H37: TRUE | I37: 46063 | J37: 46147 | K37: =J37-I37 -> 84 | L37: =I37+65 -> 46128
A38: 36 | B38: 39 | C38: =LOOKUP(A38,ADQUISICIONES!R52:R98,ADQUISICIONES!Y51:Y98) -> 1292.4433 | D38: =LOOKUP(A38,ADQUISICIONES!$R$17:$R$63,ADQUISICIONES!$T$17:$T$63) -> 17690 | E38: TRUE | F38: =(C38*18%) -> 232.6398 | G38: CN120489311JP | H38: TRUE | I38: 46063 | J38: 46147 | K38: =J38-I38 -> 84 | L38: =I38+65 -> 46128
A39: 37 | B39: 40 | C39: =LOOKUP(A39,ADQUISICIONES!R53:R99,ADQUISICIONES!Y52:Y99) -> 1177.1712 | E39: FALSE | F39: =(C39*18%) -> 211.89081 | G39: CN120179354JP | H39: TRUE | I39: 46066 | J39: 46147 | K39: =J39-I39 -> 81 | L39: =I39+65 -> 46131 | N39: 46220
A40: 38 | B40: 41 | C40: =LOOKUP(A40,ADQUISICIONES!R54:R100,ADQUISICIONES!Y53:Y100) -> 1065.1232 | E40: FALSE | F40: =(C40*18%) -> 191.72218 | G40: CN126224895JP | H40: FALSE | I40: 46154 | K40: =$K$1-I40 -> 49 | L40: =I40+65 -> 46219 | M40: FAB | N40: =$N$39-L40 -> 1
A41: 39 | B41: 42 | C41: =LOOKUP(A41,ADQUISICIONES!R55:R101,ADQUISICIONES!Y54:Y101) -> 806.59239 | E41: FALSE | F41: =(C41*18%) -> 145.18663 | G41: CN125489106JP | H41: FALSE | I41: 46143 | K41: =$K$1-I41 -> 60 | L41: =I41+65 -> 46208 | M41: JEN | N41: =$N$39-L41 -> 12
A42: 40 | B42: 44 | C42: =LOOKUP(A42,ADQUISICIONES!R56:R102,ADQUISICIONES!Y55:Y102) -> 619.37273 | E42: FALSE | F42: =(C42*18%) -> 111.48709 | G42: CN125540914JP | H42: FALSE | I42: 46151 | K42: =$K$1-I42 -> 52 | L42: =I42+65 -> 46216 | M42: ALEX | N42: =$N$39-L42 -> 4
A43: 41 | B43: 45 | C43: =LOOKUP(A43,ADQUISICIONES!R57:R103,ADQUISICIONES!Y56:Y103) -> 761.48334 | E43: FALSE | F43: =(C43*18%) -> 137.067 | G43: CN125435765JP | H43: FALSE | I43: 46143 | K43: =$K$1-I43 -> 60 | L43: =I43+65 -> 46208 | M43: TIA | N43: =$N$39-L43 -> 12
A44: 42 | B44: 46 | C44: =LOOKUP(A44,ADQUISICIONES!R58:R104,ADQUISICIONES!Y57:Y104) -> 816.86218 | E44: FALSE | F44: =(C44*18%) -> 147.03519 | G44: CN125810801JP | H44: FALSE | I44: 46151 | K44: =$K$1-I44 -> 52 | L44: =I44+65 -> 46216 | M44: FAB | N44: =$N$39-L44 -> 4
A45: 43 | B45: 47 | C45: =LOOKUP(A45,ADQUISICIONES!R59:R105,ADQUISICIONES!Y59:Y105) -> 657.02972 | E45: FALSE | F45: =(C45*18%) -> 118.26535 | G45: CN126179587JP | H45: FALSE | I45: 46156 | K45: =$K$1-I45 -> 47 | L45: =I45+65 -> 46221 | M45: FAB | N45: =$N$39-L45 -> -1
A46: 44 | B46: 48 | C46: =LOOKUP(A46,ADQUISICIONES!R60:R106,ADQUISICIONES!Y60:Y106) -> 988.81785 | E46: FALSE | F46: =(C46*18%) -> 177.98721 | G46: CN125595728JP | H46: FALSE | I46: 46151 | K46: =$K$1-I46 -> 52 | L46: =I46+65 -> 46216 | M46: JEN | N46: =$N$39-L46 -> 4
A47: 45 | B47: 49 | C47: =LOOKUP(A47,ADQUISICIONES!R61:R107,ADQUISICIONES!Y61:Y107) -> 1747.1007 | E47: FALSE | F47: =(C47*18%) -> 314.47812 | G47: CN126057331JP | H47: FALSE | I47: 46154 | K47: =$K$1-I47 -> 49 | L47: =I47+65 -> 46219 | M47: ALEX | N47: =$N$39-L47 -> 1
A48: 46 | B48: 50 | C48: =LOOKUP(A48,ADQUISICIONES!R62:R108,ADQUISICIONES!Y62:Y108) -> 617.04736 | E48: FALSE | F48: =(C48*18%) -> 111.06852 | G48: CN126169457JP | H48: FALSE | I48: 46154 | K48: =$K$1-I48 -> 49 | L48: =I48+65 -> 46219 | M48: TIA | N48: =$N$39-L48 -> 1
A49: 47 | B49: 51 | C49: =LOOKUP(A49,ADQUISICIONES!R63:R109,ADQUISICIONES!Y63:Y109) -> 758.21007 | E49: FALSE | F49: =(C49*18%) -> 136.47781 | G49: CN126114983JP | H49: FALSE | I49: 46154 | K49: =$K$1-I49 -> 49 | L49: =I49+65 -> 46219 | M49: JEN | N49: =$N$39-L49 -> 1
A50: 48 | B50: 52 | C50: =LOOKUP(A50,ADQUISICIONES!R64:R110,ADQUISICIONES!Y64:Y110) -> 1573.9249 | E50: FALSE | F50: =(C50*18%) -> 283.30647 | G50: CN125819156JP | H50: FALSE | I50: 46151 | K50: =$K$1-I50 -> 52 | L50: =I50+65 -> 46216 | M50: TIA | N50: =$N$39-L50 -> 4
A51: 49 | B51: 53 | C51: =LOOKUP(A51,ADQUISICIONES!R65:R111,ADQUISICIONES!Y65:Y111) -> 1480.002 | E51: FALSE | F51: =(C51*18%) -> 266.40036 | G51: CN127582656JP | H51: FALSE | I51: 46174 | K51: =$K$1-I51 -> 29 | L51: =I51+65 -> 46239 | M51: FAB | N51: =$N$39-L51 -> -19
A52: 50 | B52: 54 | C52: =LOOKUP(A52,ADQUISICIONES!R66:R112,ADQUISICIONES!Y66:Y112) -> 648.83443 | E52: FALSE | F52: =(C52*18%) -> 116.7902 | H52: FALSE | K52: =$K$1-I52 -> 46203
A53: 51 | B53: 55 | C53: =LOOKUP(A53,ADQUISICIONES!R67:R113,ADQUISICIONES!Y67:Y113) -> 403.38454 | E53: FALSE | F53: =(C53*18%) -> 72.609217 | H53: FALSE | K53: =$K$1-I53 -> 46203
A54: 52 | B54: 56 | C54: =LOOKUP(A54,ADQUISICIONES!R68:R114,ADQUISICIONES!Y68:Y114) -> 679.70013 | E54: FALSE | F54: =(C54*18%) -> 122.34602 | H54: FALSE | K54: =$K$1-I54 -> 46203
A55: 53 | B55: 57 | C55: =LOOKUP(A55,ADQUISICIONES!R69:R115,ADQUISICIONES!Y69:Y115) -> 763.7625 | E55: FALSE | F55: =(C55*18%) -> 137.47725 | H55: FALSE | K55: =$K$1-I55 -> 46203
A56: 54 | B56: 58 | C56: =LOOKUP(A56,ADQUISICIONES!R70:R116,ADQUISICIONES!Y70:Y116) -> 887.90421 | E56: FALSE | F56: =(C56*18%) -> 159.82276 | H56: FALSE | K56: =$K$1-I56 -> 46203
A57: 55 | B57: 59 | C57: =LOOKUP(A57,ADQUISICIONES!R71:R117,ADQUISICIONES!Y71:Y117) -> 738.06129 | E57: FALSE | F57: =(C57*18%) -> 132.85103 | H57: FALSE | K57: =$K$1-I57 -> 46203
A58: 56 | B58: 60 | C58: =LOOKUP(A58,ADQUISICIONES!R72:R118,ADQUISICIONES!Y72:Y118) -> 846.97624 | E58: FALSE | F58: =(C58*18%) -> 152.45572 | H58: FALSE | K58: =$K$1-I58 -> 46203
A59: 57 | B59: 61 | C59: =LOOKUP(A59,ADQUISICIONES!R73:R119,ADQUISICIONES!Y73:Y119) -> 654.62932 | E59: FALSE | F59: =(C59*18%) -> 117.83328 | H59: FALSE | K59: =$K$1-I59 -> 46203
A60: 58 | B60: 62 | C60: =LOOKUP(A60,ADQUISICIONES!R74:R120,ADQUISICIONES!Y74:Y120) -> 1263.2147 | E60: FALSE | F60: =(C60*18%) -> 227.37864 | H60: FALSE | K60: =$K$1-I60 -> 46203

Sheet ADQUISICIONES
A1: LA TIENDITA DE BLUE | R1: CALCULADORA | X1: HORAS | Y1: MINUTOS
A2: MES | B2: TIPO | C2: LOTE | D2: PESO | E2: COMISION | F2: COSTO | G2: ENVIO NAC | H2: TOTAL | I2: ENVIO INT | J2: E INT SOL | K2: SOLES | L2: (+SUNAT) | M2: APROX | N2: REVENUE | O2: N° CAJA | P2: N ENVIO | R2: TIPO DE CAMBIO | T2: =AD4 -> 0.024246429 | U2: 24000 | V2: =(U2*T2)*111.5% -> 648.83443 | W2: =(U2/T3)*111.5% -> 235.97541 | X2: 20 | Y2: 20
A3: DICIEMBRE | B3: JUNK | C3: 1 | D3: 18400 | E3: 1000 | F3: 25500 | G3: 1780 | H3: =SUM(E3:G3) -> 28280 | I3: =(LOOKUP(O3,$R$16:$R$27,$X$16:$X$27)*D3)/LOOKUP(O3,$R$16:$R$27,$T$16:$T$27) -> 15342.466 | J3: =I3*$T$2 -> 372 | K3: =(H3*$T$2)+(I3*$T$2) -> 1057.689 | L3: =(LOOKUP(O3,$R$16:$R$27,$Z$16:$Z$27)*F3)/LOOKUP(O3,$R$16:$R$27,$U$16:$U$27)+K3 -> 1356.2886 | M3: 3000 | N3: =M3-L3 -> 1643.7114 | O3: 1 | P3: 1 | T3: =AE3 -> 113.40164 | V3: SOLES | W3: DOLARES | AC3: 28000 | AD3: 246.91 | AE3: =AC3/AD3 -> 113.40164
A4: DICIEMBRE | B4: JUNK | C4: 4 | D4: 352 | E4: 1000 | F4: 12 | G4: 990 | H4: =SUM(E4:G4) -> 2002 | I4: =(LOOKUP(O4,$R$16:$R$27,$X$16:$X$27)*D4)/LOOKUP(O4,$R$16:$R$27,$T$16:$T$27) -> 293.50804 | J4: =I4*$T$2 -> 7.1165217 | K4: =(H4*$T$2)+(I4*$T$2) -> 55.657872 | L4: =(LOOKUP(O4,$R$16:$R$27,$Z$16:$Z$27)*F4)/LOOKUP(O4,$R$16:$R$27,$U$16:$U$27)+K4 -> 55.798389 | M4: 100 | N4: =M4-L4 -> 44.201611 | O4: 1 | P4: 1 | R4: COSTO COMPRA | S4: =SUM(F:F) -> 1576737 | T4: =$T$2*S4 -> 38230.241 | W4: LIMITE | AC4: 678.9 | AD4: =AC4/AC3 -> 0.024246429
A5: DICIEMBRE | B5: NEW | C5: 5 | D5: 402 | E5: 1000 | F5: 1 | G5: 3350 | H5: =SUM(E5:G5) -> 4351 | I5: =(LOOKUP(O5,$R$16:$R$27,$X$16:$X$27)*D5)/LOOKUP(O5,$R$16:$R$27,$T$16:$T$27) -> 335.19952 | J5: =I5*$T$2 -> 8.1273913 | K5: =(H5*$T$2)+(I5*$T$2) -> 113.6236 | L5: =(LOOKUP(O5,$R$16:$R$27,$Z$16:$Z$27)*F5)/LOOKUP(O5,$R$16:$R$27,$U$16:$U$27)+K5 -> 113.63531 | M5: 60 | N5: =M5-L5 -> -53.635312 | O5: 1 | P5: 1 | R5: ENVIO NAC | S5: =SUM(G:G) -> 147724 | T5: =$T$2*S5 -> 3581.7794 | W5: =NOW()+(2/24)+((X2/24))+(Y2/1440) -> 46204.845
A6: DICIEMBRE | B6: NEW | C6: 14 | D6: 470 | E6: 1000 | F6: 1 | G6: 3800 | H6: =SUM(E6:G6) -> 4801 | I6: =(LOOKUP(O6,$R$16:$R$27,$X$16:$X$27)*D6)/LOOKUP(O6,$R$16:$R$27,$T$16:$T$27) -> 391.89994 | J6: =I6*$T$2 -> 9.5021739 | K6: =(H6*$T$2)+(I6*$T$2) -> 125.90928 | L6: =(LOOKUP(O6,$R$16:$R$27,$Z$16:$Z$27)*F6)/LOOKUP(O6,$R$16:$R$27,$U$16:$U$27)+K6 -> 125.92099 | M6: 55 | N6: =M6-L6 -> -70.920987 | O6: 1 | P6: 1 | R6: ENVIO INT | S6: =SUM(I:I) -> 662748.47 | T6: =$T$2*S6 -> 16069.283
A7: DICIEMBRE | B7: NEW | C7: 26 | D7: 524 | E7: 500 | F7: 1500 | G7: 0 | H7: =SUM(E7:G7) -> 2000 | I7: =(LOOKUP(O7,$R$16:$R$27,$X$16:$X$27)*D7)/LOOKUP(O7,$R$16:$R$27,$T$16:$T$27) -> 436.92674 | J7: =I7*$T$2 -> 10.593913 | K7: =(H7*$T$2)+(I7*$T$2) -> 59.08677 | L7: =(LOOKUP(O7,$R$16:$R$27,$Z$16:$Z$27)*F7)/LOOKUP(O7,$R$16:$R$27,$U$16:$U$27)+K7 -> 76.651454 | M7: 100 | N7: =M7-L7 -> 23.348546 | O7: 1 | P7: 1 | R7: COMISION | S7: =SUM(E:E) -> 119800 | T7: =$T$2*S7 -> 2904.7221
A8: DICIEMBRE | B8: JUNK | C8: 20 | D8: 1826 | E8: 1000 | F8: 5165 | G8: 880 | H8: =SUM(E8:G8) -> 7045 | I8: =(LOOKUP(O8,$R$16:$R$27,$X$16:$X$27)*D8)/LOOKUP(O8,$R$16:$R$27,$T$16:$T$27) -> 1522.1741 | J8: =I8*$T$2 -> 36.907285 | K8: =(H8*$T$2)+(I8*$T$2) -> 207.72337 | L8: =(LOOKUP(O8,$R$16:$R$27,$Z$16:$Z$27)*F8)/LOOKUP(O8,$R$16:$R$27,$U$16:$U$27)+K8 -> 257.79661 | M8: 200 | N8: =M8-L8 -> -57.79661 | O8: 2 | P8: 2 | R8: SUBTOTALES | S8: =SUM(H:H)+M1 -> 1844261 | T8: =$T$2*S8 -> 44716.743
A9: DICIEMBRE | B9: GACHA | C9: 21 | D9: 914 | E9: 500 | F9: 7763 | G9: 880 | H9: =SUM(E9:G9) -> 9143 | I9: =(LOOKUP(O9,$R$16:$R$27,$X$16:$X$27)*D9)/LOOKUP(O9,$R$16:$R$27,$T$16:$T$27) -> 761.92064 | J9: =I9*$T$2 -> 18.473854 | K9: =(H9*$T$2)+(I9*$T$2) -> 240.15895 | L9: =(LOOKUP(O9,$R$16:$R$27,$Z$16:$Z$27)*F9)/LOOKUP(O9,$R$16:$R$27,$U$16:$U$27)+K9 -> 315.41907 | M9: 600 | N9: =M9-L9 -> 284.58093 | O9: 2 | P9: 2 | T9: =SUM(K:K) -> 60786.026 | W9: PERDIDA | X9: =SUMIF(N:N,"<0") -> -10240.152
A10: DICIEMBRE | B10: JUNK | C10: 24 | D10: 13350 | E10: 1000 | F10: 11200 | G10: 1970 | H10: =SUM(E10:G10) -> 14170 | I10: =(LOOKUP(O10,$R$16:$R$27,$X$16:$X$27)*D10)/LOOKUP(O10,$R$16:$R$27,$T$16:$T$27) -> 11128.71 | J10: =I10*$T$2 -> 269.83146 | K10: =(H10*$T$2)+(I10*$T$2) -> 613.40335 | L10: =(LOOKUP(O10,$R$16:$R$27,$Z$16:$Z$27)*F10)/LOOKUP(O10,$R$16:$R$27,$U$16:$U$27)+K10 -> 721.98423 | M10: 1500 | N10: =M10-L10 -> 778.01577 | O10: 2 | P10: 2 | S10: PRECIO APROX | T10: =SUM(M:M) -> 94691.026
A11: DICIEMBRE | B11: NEW | C11: 29 | D11: 1904 | E11: 1000 | F11: 4200 | G11: 0 | H11: =SUM(E11:G11) -> 5200 | I11: =(LOOKUP(O11,$R$16:$R$27,$X$16:$X$27)*D11)/LOOKUP(O11,$R$16:$R$27,$T$16:$T$27) -> 1587.1957 | J11: =I11*$T$2 -> 38.483828 | K11: =(H11*$T$2)+(I11*$T$2) -> 164.56526 | L11: =(LOOKUP(O11,$R$16:$R$27,$Z$16:$Z$27)*F11)/LOOKUP(O11,$R$16:$R$27,$U$16:$U$27)+K11 -> 205.28309 | M11: 300 | N11: =M11-L11 -> 94.716914 | O11: 2 | P11: 2 | T11: REVENUE | U11: =SUM(M:M)-SUM(L:L) -> 22547.833
A12: DICIEMBRE | B12: JUNK | C12: 3 | D12: 12180 | E12: 1000 | F12: 14050 | G12: 0 | H12: =SUM(E12:G12) -> 15050 | I12: =(LOOKUP(O12,$R$16:$R$27,$X$16:$X$27)*D12)/LOOKUP(O12,$R$16:$R$27,$T$16:$T$27) -> 8804.8193 | J12: =I12*$T$2 -> 213.48542 | K12: =(H12*$T$2)+(I12*$T$2) -> 578.39417 | L12: =(LOOKUP(O12,$R$16:$R$27,$Z$16:$Z$27)*F12)/LOOKUP(O12,$R$16:$R$27,$U$16:$U$27)+K12 -> 578.39417 | M12: 1500 | N12: =M12-L12 -> 921.60583 | O12: 4 | P12: 3 | T12: SIN IMPUESTOS | U12: =SUM(M:M)-SUM(K:K) -> 33905
A13: DICIEMBRE | B13: JUNK | C13: 70 | D13: 6910 | E13: 500 | F13: 14780 | G13: 1500 | H13: =SUM(E13:G13) -> 16780 | I13: =(LOOKUP(O13,$R$16:$R$27,$X$16:$X$27)*D13)/LOOKUP(O13,$R$16:$R$27,$T$16:$T$27) -> 4995.1807 | J13: =I13*$T$2 -> 121.11529 | K13: =(H13*$T$2)+(I13*$T$2) -> 527.97036 | L13: =(LOOKUP(O13,$R$16:$R$27,$Z$16:$Z$27)*F13)/LOOKUP(O13,$R$16:$R$27,$U$16:$U$27)+K13 -> 527.97036 | M13: 1200 | N13: =M13-L13 -> 672.02964 | O13: 4 | P13: 3
A14: DICIEMBRE | B14: NEW | C14: 28 | D14: 5048 | E14: 1000 | F14: 6500 | G14: 1780 | H14: =SUM(E14:G14) -> 9280 | I14: =(LOOKUP(O14,$R$16:$R$27,$X$16:$X$27)*D14)/LOOKUP(O14,$R$16:$R$27,$T$16:$T$27) -> 5449.5823 | J14: =I14*$T$2 -> 132.13291 | K14: =(H14*$T$2)+(I14*$T$2) -> 357.13977 | L14: =(LOOKUP(O14,$R$16:$R$27,$Z$16:$Z$27)*F14)/LOOKUP(O14,$R$16:$R$27,$U$16:$U$27)+K14 -> 357.13977 | M14: 600 | N14: =M14-L14 -> 242.86023 | O14: 3 | P14: 5 | R14: ENVIOS
A15: DICIEMBRE | B15: NEW | C15: 30 | D15: 5030 | E15: 1000 | F15: 6250 | G15: 1780 | H15: =SUM(E15:G15) -> 9030 | I15: =(LOOKUP(O15,$R$16:$R$27,$X$16:$X$27)*D15)/LOOKUP(O15,$R$16:$R$27,$T$16:$T$27) -> 5430.1504 | J15: =I15*$T$2 -> 131.66175 | K15: =(H15*$T$2)+(I15*$T$2) -> 350.607 | L15: =(LOOKUP(O15,$R$16:$R$27,$Z$16:$Z$27)*F15)/LOOKUP(O15,$R$16:$R$27,$U$16:$U$27)+K15 -> 350.607 | M15: 600 | N15: =M15-L15 -> 249.393 | O15: 3 | P15: 5 | R15: N CAJA | T15: PESO | U15: COSTO NETO | V15: ESTADO | X15: COSTO ENVIO | Y15: COSTO BRUTO | Z15: IMPUESTO | AA15: COSTE FINAL | AB15: PROFIT
A16: DICIEMBRE | B16: NEW | C16: 34 | D16: 1640 | E16: 500 | F16: 1980 | G16: 1280 | H16: =SUM(E16:G16) -> 3760 | I16: =(LOOKUP(O16,$R$16:$R$27,$X$16:$X$27)*D16)/LOOKUP(O16,$R$16:$R$27,$T$16:$T$27) -> 1770.4665 | J16: =I16*$T$2 -> 42.92749 | K16: =(H16*$T$2)+(I16*$T$2) -> 134.09406 | L16: =(LOOKUP(O16,$R$16:$R$27,$Z$16:$Z$27)*F16)/LOOKUP(O16,$R$16:$R$27,$U$16:$U$27)+K16 -> 134.09406 | M16: 150 | N16: =M16-L16 -> 15.905939 | O16: 3 | P16: 5 | R16: 0 | T16: 1 | U16: 23200 | Y16: 601.22585 | Z16: 132.26969 | AA16: 733.49554 | AB16: 316.50446
A17: DICIEMBRE | B17: USED | C17: 35 | D17: 538 | E17: 500 | F17: 1580 | G17: 640 | H17: =SUM(E17:G17) -> 2720 | I17: =(LOOKUP(O17,$R$16:$R$27,$X$16:$X$27)*D17)/LOOKUP(O17,$R$16:$R$27,$T$16:$T$27) -> 580.79938 | J17: =I17*$T$2 -> 14.082311 | K17: =(H17*$T$2)+(I17*$T$2) -> 80.032596 | L17: =(LOOKUP(O17,$R$16:$R$27,$Z$16:$Z$27)*F17)/LOOKUP(O17,$R$16:$R$27,$U$16:$U$27)+K17 -> 80.032596 | M17: 100 | N17: =M17-L17 -> 19.967404 | O17: 3 | P17: 5 | R17: 1 | S17: 1 | T17: 20148 | U17: 27014 | X17: 16800 | Y17: 1437.8557 | Z17: 316.32825 | AA17: 1754.1839 | AB17: 1244.4878
A18: DICIEMBRE | B18: JUNK | C18: 48 | D18: 2182 | E18: 500 | F18: 2200 | G18: 1130 | H18: =SUM(E18:G18) -> 3830 | I18: =(LOOKUP(O18,$R$16:$R$27,$X$16:$X$27)*D18)/LOOKUP(O18,$R$16:$R$27,$T$16:$T$27) -> 2355.5841 | J18: =I18*$T$2 -> 57.114502 | K18: =(H18*$T$2)+(I18*$T$2) -> 149.97832 | L18: =(LOOKUP(O18,$R$16:$R$27,$Z$16:$Z$27)*F18)/LOOKUP(O18,$R$16:$R$27,$U$16:$U$27)+K18 -> 149.97832 | M18: 500 | N18: =M18-L18 -> 350.02168 | O18: 3 | P18: 5 | R18: 2 | S18: 2 | T18: 17994 | U18: 28328 | X18: 15000 | Y18: 1248.3276 | Z18: 274.63207 | AA18: 1522.9596 | AB18: 802.40829
A19: DICIEMBRE | B19: MERCH | C19: 58 | D19: 1124 | E19: 500 | F19: 1700 | G19: 230 | H19: =SUM(E19:G19) -> 2430 | I19: =(LOOKUP(O19,$R$16:$R$27,$X$16:$X$27)*D19)/LOOKUP(O19,$R$16:$R$27,$T$16:$T$27) -> 1213.4173 | J19: =I19*$T$2 -> 29.421036 | K19: =(H19*$T$2)+(I19*$T$2) -> 88.339857 | L19: =(LOOKUP(O19,$R$16:$R$27,$Z$16:$Z$27)*F19)/LOOKUP(O19,$R$16:$R$27,$U$16:$U$27)+K19 -> 88.339857 | M19: 150 | N19: =M19-L19 -> 61.660143 | O19: 3 | P19: 5 | R19: 3 | S19: 5 | T19: 15562 | U19: 20210 | X19: 16800 | Y19: 1181.4643 | Z19: 0 | AA19: 1181.4643 | AB19: 918.53565
A20: DICIEMBRE | B20: NEW | C20: 56 | D20: 384 | E20: 500 | F20: 1400 | G20: 800 | H20: =SUM(E20:G20) -> 2700 | I20: =(LOOKUP(O20,$R$16:$R$27,$X$16:$X$27)*D20)/LOOKUP(O20,$R$16:$R$27,$T$16:$T$27) -> 328.72022 | J20: =I20*$T$2 -> 7.9702913 | K20: =(H20*$T$2)+(I20*$T$2) -> 73.435648 | L20: =(LOOKUP(O20,$R$16:$R$27,$Z$16:$Z$27)*F20)/LOOKUP(O20,$R$16:$R$27,$U$16:$U$27)+K20 -> 73.435648 | M20: 60 | N20: =M20-L20 -> -13.435648 | O20: 5 | P20: 6 | R20: 4 | S20: 5 | T20: 19090 | U20: 28830 | X20: 13800 | Y20: 1126.6503 | Z20: 0 | AA20: 1126.6503 | AB20: 1573.3497
A21: DICIEMBRE | B21: NEW | C21: 88 | D21: 302 | E21: 500 | F21: 800 | G21: 0 | H21: =SUM(E21:G21) -> 1300 | I21: =(LOOKUP(O21,$R$16:$R$27,$X$16:$X$27)*D21)/LOOKUP(O21,$R$16:$R$27,$T$16:$T$27) -> 258.52475 | J21: =I21*$T$2 -> 6.268302 | K21: =(H21*$T$2)+(I21*$T$2) -> 37.788659 | L21: =(LOOKUP(O21,$R$16:$R$27,$Z$16:$Z$27)*F21)/LOOKUP(O21,$R$16:$R$27,$U$16:$U$27)+K21 -> 37.788659 | M21: 50 | N21: =M21-L21 -> 12.211341 | O21: 5 | P21: 6 | R21: 5 | S21: 6 | T21: 14018 | U21: 23500 | X21: 12000 | Y21: 1051.0959 | Z21: 0 | AA21: 1051.0959 | AB21: 658.90413
A22: DICIEMBRE | B22: NEW | C22: 89 | D22: 13270 | E22: 500 | F22: 20500 | G22: 3980 | H22: =SUM(E22:G22) -> 24980 | I22: =(LOOKUP(O22,$R$16:$R$27,$X$16:$X$27)*D22)/LOOKUP(O22,$R$16:$R$27,$T$16:$T$27) -> 11359.68 | J22: =I22*$T$2 -> 275.43168 | K22: =(H22*$T$2)+(I22*$T$2) -> 881.10747 | L22: =(LOOKUP(O22,$R$16:$R$27,$Z$16:$Z$27)*F22)/LOOKUP(O22,$R$16:$R$27,$U$16:$U$27)+K22 -> 881.10747 | M22: 1600 | N22: =M22-L22 -> 718.89253 | O22: 5 | P22: 6 | R22: 6 | S22: 7 | T22: 22836 | U22: 27350 | X22: 17400 | Y22: 1321.6399 | Z22: 0 | AA22: 1321.6399 | AB22: 928.36006
A23: DICIEMBRE | B23: DANTE | C23: 91 | D23: 62 | E23: 500 | F23: 800 | G23: 290 | H23: =SUM(E23:G23) -> 1590 | I23: =(LOOKUP(O23,$R$16:$R$27,$X$16:$X$27)*D23)/LOOKUP(O23,$R$16:$R$27,$T$16:$T$27) -> 53.074618 | J23: =I23*$T$2 -> 1.2868699 | K23: =(H23*$T$2)+(I23*$T$2) -> 39.838691 | L23: =(LOOKUP(O23,$R$16:$R$27,$Z$16:$Z$27)*F23)/LOOKUP(O23,$R$16:$R$27,$U$16:$U$27)+K23 -> 39.838691 | M23: 0 | N23: =M23-L23 -> -39.838691 | O23: 5 | P23: 6 | R23: 7 | S23: 8 | T23: 1002 | U23: 9200 | X23: 4400 | Y23: 348.1431 | Z23: 0 | AA23: 348.1431 | AB23: 0
A24: DICIEMBRE | B24: USED | C24: 65 | D24: 5830 | E24: 500 | F24: 8250 | G24: 1300 | H24: =SUM(E24:G24) -> 10050 | I24: =(LOOKUP(O24,$R$16:$R$27,$X$16:$X$27)*D24)/LOOKUP(O24,$R$16:$R$27,$T$16:$T$27) -> 4442.1965 | J24: =I24*$T$2 -> 107.7074 | K24: =(H24*$T$2)+(I24*$T$2) -> 351.38401 | L24: =(LOOKUP(O24,$R$16:$R$27,$Z$16:$Z$27)*F24)/LOOKUP(O24,$R$16:$R$27,$U$16:$U$27)+K24 -> 351.38401 | M24: 800 | N24: =M24-L24 -> 448.61599 | O24: 6 | P24: 7 | R24: 8 | S24: 10 | T24: 25918 | U24: 26559 | X24: 20400 | Y24: 1438.1026 | Z24: 316.38257 | AA24: 1754.4852 | AB24: 779.13225
A25: DICIEMBRE | B25: JUNK | C25: 69 | D25: 9368 | E25: 500 | F25: 7950 | G25: 1000 | H25: =SUM(E25:G25) -> 9450 | I25: =(LOOKUP(O25,$R$16:$R$27,$X$16:$X$27)*D25)/LOOKUP(O25,$R$16:$R$27,$T$16:$T$27) -> 7137.9926 | J25: =I25*$T$2 -> 173.07083 | K25: =(H25*$T$2)+(I25*$T$2) -> 402.19958 | L25: =(LOOKUP(O25,$R$16:$R$27,$Z$16:$Z$27)*F25)/LOOKUP(O25,$R$16:$R$27,$U$16:$U$27)+K25 -> 402.19958 | M25: 700 | N25: =M25-L25 -> 297.80042 | O25: 6 | P25: 7 | R25: 9 | S25: 14 | T25: 16178 | U25: 27759 | X25: 13200 | Y25: 1175.02 | Z25: 258.5044 | AA25: 1433.5244 | AB25: 272.9712
A26: DICIEMBRE | B26: GACHA | C26: 93 | D26: 4852 | E26: 500 | F26: 8250 | G26: 1000 | H26: =SUM(E26:G26) -> 9750 | I26: =(LOOKUP(O26,$R$16:$R$27,$X$16:$X$27)*D26)/LOOKUP(O26,$R$16:$R$27,$T$16:$T$27) -> 3697.0047 | J26: =I26*$T$2 -> 89.639161 | K26: =(H26*$T$2)+(I26*$T$2) -> 326.04184 | L26: =(LOOKUP(O26,$R$16:$R$27,$Z$16:$Z$27)*F26)/LOOKUP(O26,$R$16:$R$27,$U$16:$U$27)+K26 -> 326.04184 | M26: 450 | N26: =M26-L26 -> 123.95816 | O26: 6 | P26: 7 | R26: 10 | S26: 11 | T26: 10632 | U26: 28311 | X26: 10200 | Y26: 1053.3428 | Z26: 231.73541 | AA26: 1285.0782 | AB26: 583.18644
A27: DICIEMBRE | B27: MERCH | C27: 94 | D27: 2786 | E27: 500 | F27: 2900 | G27: 1250 | H27: =SUM(E27:G27) -> 4650 | I27: =(SUMIFS($X$16:$X$27,$R$16:$R$27,O27))/(COUNTIF(O:O,O27)) -> 4350 | J27: =I27*$T$2 -> 105.47196 | K27: =(H27*$T$2)+(I27*$T$2) -> 218.21786 | L27: =(LOOKUP(O27,$R$16:$R$27,$Z$16:$Z$27)*F27)/LOOKUP(O27,$R$16:$R$27,$U$16:$U$27)+K27 -> 218.21786 | M27: 300 | N27: =M27-L27 -> 81.782143 | O27: 6 | P27: 7 | R27: 11 | S27: 16 | T27: 10442 | U27: 28755 | X27: 9600 | Y27: 986.52891 | Z27: 217.03636 | AA27: 1203.5653 | AB27: -18.61422
A28: DICIEMBRE | B28: ROXANA | C28: 96 | D28: 1002 | E28: 500 | F28: 9200 | G28: 0 | H28: =SUM(E28:G28) -> 9700 | I28: 4400 | J28: =I28*$T$2 -> 106.68429 | K28: =(H28*$T$2)+(I28*$T$2) -> 341.87464 | L28: =(LOOKUP(O28,$R$16:$R$27,$Z$16:$Z$27)*F28)/LOOKUP(O28,$R$16:$R$27,$U$16:$U$27)+K28 -> 341.87464 | M28: =K28 -> 341.87464 | N28: =M28-L28 -> 0 | O28: 7 | P28: 8 | R28: 12 | S28: 13 | T28: 15170 | U28: 28943 | X28: 13200 | Y28: 1080.0584 | Z28: 237.61285 | AA28: 1317.6713 | AB28: -162.97883
A29: DICIEMBRE | B29: USED | C29: 98 | D29: 6404 | E29: 500 | F29: 6959 | G29: 1915 | H29: =SUM(E29:G29) -> 9374 | I29: =(LOOKUP(O29,$R$16:$R$27,$X$16:$X$27)*D29)/LOOKUP(O29,$R$16:$R$27,$T$16:$T$27) -> 5040.5741 | J29: =I29*$T$2 -> 122.21592 | K29: =(H29*$T$2)+(I29*$T$2) -> 349.50194 | L29: =(LOOKUP(O29,$R$16:$R$27,$Z$16:$Z$27)*F29)/LOOKUP(O29,$R$16:$R$27,$U$16:$U$27)+K29 -> 432.40063 | M29: 1000 | N29: =M29-L29 -> 567.59937 | O29: 8 | P29: 10 | R29: 13 | S29: 17 | T29: 14560 | U29: 28277 | X29: 13200 | Y29: 1063.6142 | Z29: 233.99513 | AA29: 1297.6093 | AB29: -0.23808072
A30: DICIEMBRE | B30: USED | C30: 100 | D30: 5810 | E30: 500 | F30: 6600 | G30: 2010 | H30: =SUM(E30:G30) -> 9110 | I30: =(LOOKUP(O30,$R$16:$R$27,$X$16:$X$27)*D30)/LOOKUP(O30,$R$16:$R$27,$T$16:$T$27) -> 4573.038 | J30: =I30*$T$2 -> 110.87984 | K30: =(H30*$T$2)+(I30*$T$2) -> 331.7648 | L30: =(LOOKUP(O30,$R$16:$R$27,$Z$16:$Z$27)*F30)/LOOKUP(O30,$R$16:$R$27,$U$16:$U$27)+K30 -> 410.38693 | M30: 750 | N30: =M30-L30 -> 339.61307 | O30: 8 | P30: 10 | R30: 14 | S30: 15 | T30: 11042 | U30: 29000 | X30: 10800 | Y30: 1041.9602 | Z30: 229.23124 | AA30: 1271.1914 | AB30: -20.698768
A31: DICIEMBRE | B31: NEW | C31: 104 | D31: 2464 | E31: 500 | F31: 4200 | G31: 1620 | H31: =SUM(E31:G31) -> 6320 | I31: =(LOOKUP(O31,$R$16:$R$27,$X$16:$X$27)*D31)/LOOKUP(O31,$R$16:$R$27,$T$16:$T$27) -> 1939.4089 | J31: =I31*$T$2 -> 47.023739 | K31: =(H31*$T$2)+(I31*$T$2) -> 200.26117 | L31: =(LOOKUP(O31,$R$16:$R$27,$Z$16:$Z$27)*F31)/LOOKUP(O31,$R$16:$R$27,$U$16:$U$27)+K31 -> 250.29343 | M31: 350 | N31: =M31-L31 -> 99.706571 | O31: 8 | P31: 10 | R31: 15 | S31: 12 | T31: 9450 | U31: 28459 | X31: 10800 | Y31: 1048.3552 | Z31: 230.63814 | AA31: 1278.9933 | AB31: 254.589
A32: DICIEMBRE | B32: USED | C32: 109 | D32: 5022 | E32: 500 | F32: 4400 | G32: 1620 | H32: =SUM(E32:G32) -> 6520 | I32: =(LOOKUP(O32,$R$16:$R$27,$X$16:$X$27)*D32)/LOOKUP(O32,$R$16:$R$27,$T$16:$T$27) -> 3952.805 | J32: =I32*$T$2 -> 95.841404 | K32: =(H32*$T$2)+(I32*$T$2) -> 253.92812 | L32: =(LOOKUP(O32,$R$16:$R$27,$Z$16:$Z$27)*F32)/LOOKUP(O32,$R$16:$R$27,$U$16:$U$27)+K32 -> 306.34287 | M32: 450 | N32: =M32-L32 -> 143.65713 | O32: 8 | P32: 10 | R32: 16 | S32: 18 | T32: 16574 | U32: 29046 | X32: 14400 | Y32: 1225.8094 | Z32: 269.67806 | AA32: 1495.4875 | AB32: 410.02293
A33: DICIEMBRE | B33: USED | C33: 111 | D33: 6218 | E33: 500 | F33: 4400 | G33: 1620 | H33: =SUM(E33:G33) -> 6520 | I33: =(LOOKUP(O33,$R$16:$R$27,$X$16:$X$27)*D33)/LOOKUP(O33,$R$16:$R$27,$T$16:$T$27) -> 4894.1739 | J33: =I33*$T$2 -> 118.66624 | K33: =(H33*$T$2)+(I33*$T$2) -> 276.75295 | L33: =(LOOKUP(O33,$R$16:$R$27,$Z$16:$Z$27)*F33)/LOOKUP(O33,$R$16:$R$27,$U$16:$U$27)+K33 -> 329.1677 | M33: 450 | N33: =M33-L33 -> 120.8323 | O33: 8 | P33: 10 | R33: 17 | S33: 19 | T33: 15602 | U33: 29449 | X33: 13200 | Y33: 1294.0306 | Z33: 284.68674 | AA33: 1578.7174 | AB33: 276.99599
A34: ENERO | B34: NEW | C34: 107 | D34: 1698 | E34: 500 | F34: 1511 | G34: 1620 | H34: =SUM(E34:G34) -> 3631 | I34: =(LOOKUP(O34,$R$16:$R$40,$X$16:$X$40)*D34)/LOOKUP(O34,$R$16:$R$40,$T$16:$T$40) -> 1629.0068 | J34: =I34*$T$2 -> 39.497596 | K34: =(H34*$T$2)+(I34*$T$2) -> 127.53638 | L34: =(LOOKUP(O34,$R$16:$R$27,$Z$16:$Z$27)*F34)/LOOKUP(O34,$R$16:$R$27,$U$16:$U$27)+K34 -> 139.90444 | M34: 300 | N34: =M34-L34 -> 160.09556 | O34: 10 | P34: 11 | R34: 18 | S34: 20 | T34: 22719 | U34: 29949 | X34: 17400 | Y34: 1393.0074 | Z34: 306.46163 | AA34: 1699.469 | AB34: 1848.3179
A35: ENERO | B35: USED | C35: 137 | D35: 8934 | E35: 500 | F35: 26800 | G35: 1530 | H35: =SUM(E35:G35) -> 28830 | I35: =(LOOKUP(O35,$R$16:$R$40,$X$16:$X$40)*D35)/LOOKUP(O35,$R$16:$R$40,$T$16:$T$40) -> 8570.9932 | J35: =I35*$T$2 -> 207.81598 | K35: =(H35*$T$2)+(I35*$T$2) -> 906.84051 | L35: =(LOOKUP(O35,$R$16:$R$27,$Z$16:$Z$27)*F35)/LOOKUP(O35,$R$16:$R$27,$U$16:$U$27)+K35 -> 1126.2079 | M35: 1800 | N35: =M35-L35 -> 673.79215 | O35: 10 | P35: 11 | R35: 19 | S35: 22 | T35: 17138 | U35: 29175 | X35: 14400 | Y35: 1159.2116 | Z35: 255.02654 | AA35: 1414.2381 | AB35: -20.450431
A36: ENERO | B36: NEW | C36: 135 | D36: 1058 | E36: 800 | F36: 5980 | G36: 0 | H36: =SUM(E36:G36) -> 6780 | I36: =(LOOKUP(O36,$R$16:$R$40,$X$16:$X$40)*D36)/LOOKUP(O36,$R$16:$R$40,$T$16:$T$40) -> 1209.1429 | J36: =I36*$T$2 -> 29.317396 | K36: =(H36*$T$2)+(I36*$T$2) -> 193.70818 | L36: =(LOOKUP(O36,$R$16:$R$27,$Z$16:$Z$27)*F36)/LOOKUP(O36,$R$16:$R$27,$U$16:$U$27)+K36 -> 238.84389 | M36: 350 | N36: =M36-L36 -> 111.15611 | O36: 15 | P36: 12 | R36: 20 | S36: 21 | T36: =SUMIFS(D:D,O:O,R36) -> 11890 | U36: =SUMIFS($F:$F,$O:$O,R36) -> 47079 | X36: 10800 | Y36: =SUMIFS(K:K,O:O,R36) -> 1491.8585 | Z36: =Y36*22% -> 328.20887 | AA36: =Y36+Z36 -> 1820.0674 | AB36: =(SUMIFS(N:N,O:O,R36))-Z36 -> 514.59078
A37: ENERO | B37: NEW | C37: 149 | D37: 3910 | E37: 800 | F37: 8500 | G37: 0 | H37: =SUM(E37:G37) -> 9300 | I37: =(LOOKUP(O37,$R$16:$R$40,$X$16:$X$40)*D37)/LOOKUP(O37,$R$16:$R$40,$T$16:$T$40) -> 4468.5714 | J37: =I37*$T$2 -> 108.3469 | K37: =(H37*$T$2)+(I37*$T$2) -> 333.83868 | L37: =(LOOKUP(O37,$R$16:$R$27,$Z$16:$Z$27)*F37)/LOOKUP(O37,$R$16:$R$27,$U$16:$U$27)+K37 -> 397.9948 | M37: 700 | N37: =M37-L37 -> 302.0052 | O37: 15 | P37: 12 | R37: 21 | S37: 23 | T37: =SUMIFS(D:D,O:O,R37) -> 17597 | U37: =SUMIFS($F:$F,$O:$O,R37) -> 27566 | X37: 13800 | Y37: =SUMIFS(K:K,O:O,R37) -> 1231.864 | Z37: =Y37*22% -> 271.01009 | AA37: =Y37+Z37 -> 1502.8741 | AB37: =(SUMIFS(N:N,O:O,R37))-Z37 -> 639.06381
A38: ENERO | B38: NEW | C38: 152 | D38: 2060 | E38: 800 | F38: 6980 | G38: 0 | H38: =SUM(E38:G38) -> 7780 | I38: =(LOOKUP(O38,$R$16:$R$40,$X$16:$X$40)*D38)/LOOKUP(O38,$R$16:$R$40,$T$16:$T$40) -> 2354.2857 | J38: =I38*$T$2 -> 57.08302 | K38: =(H38*$T$2)+(I38*$T$2) -> 245.72023 | L38: =(LOOKUP(O38,$R$16:$R$27,$Z$16:$Z$27)*F38)/LOOKUP(O38,$R$16:$R$27,$U$16:$U$27)+K38 -> 298.40373 | M38: 280 | N38: =M38-L38 -> -18.403726 | O38: 15 | P38: 12 | R38: 22 | S38: 23 | T38: =SUMIFS(D:D,O:O,R38) -> 14436 | U38: =SUMIFS($F:$F,$O:$O,R38) -> 29999 | X38: 12600 | Y38: =SUMIFS(K:K,O:O,R38) -> 1146.1044 | Z38: =Y38*22% -> 252.14298 | AA38: =Y38+Z38 -> 1398.2474 | AB38: =(SUMIFS(N:N,O:O,R38))-Z38 -> 310.3268
A39: ENERO | B39: NEW | C39: 156 | D39: 2422 | E39: 800 | F39: 6999 | G39: 0 | H39: =SUM(E39:G39) -> 7799 | I39: =(LOOKUP(O39,$R$16:$R$40,$X$16:$X$40)*D39)/LOOKUP(O39,$R$16:$R$40,$T$16:$T$40) -> 2768 | J39: =I39*$T$2 -> 67.114114 | K39: =(H39*$T$2)+(I39*$T$2) -> 256.21201 | L39: =(LOOKUP(O39,$R$16:$R$27,$Z$16:$Z$27)*F39)/LOOKUP(O39,$R$16:$R$27,$U$16:$U$27)+K39 -> 309.03891 | M39: 400 | N39: =M39-L39 -> 90.96109 | O39: 15 | P39: 12 | R39: 23 | S39: 25 | T39: =SUMIFS(D:D,O:O,R39) -> 25978 | U39: =SUMIFS($F:$F,$O:$O,R39) -> 63829 | X39: 24600 | Y39: =SUMIFS(K:K,O:O,R39) -> 2390.4311 | Z39: =Y39*22% -> 525.89485 | AA39: =Y39+Z39 -> 2916.326 | AB39: =(SUMIFS(N:N,O:O,R39))-Z39 -> 301.90687
A40: ENERO | B40: NEW | C40: 126 | D40: 14120 | E40: 800 | F40: 24444 | G40: 0 | H40: =SUM(E40:G40) -> 25244 | I40: =(LOOKUP(O40,$R$16:$R$40,$X$16:$X$40)*D40)/LOOKUP(O40,$R$16:$R$40,$T$16:$T$40) -> 12286.355 | J40: =I40*$T$2 -> 297.90022 | K40: =(H40*$T$2)+(I40*$T$2) -> 909.97706 | L40: =(LOOKUP(O40,$R$16:$R$27,$Z$16:$Z$27)*F40)/LOOKUP(O40,$R$16:$R$27,$U$16:$U$27)+K40 -> 1094.475 | M40: 1300 | N40: =M40-L40 -> 205.52505 | O40: 12 | P40: 13 | R40: 24 | S40: 27 | T40: =SUMIFS(D:D,O:O,R40) -> 17922 | U40: =SUMIFS($F:$F,$O:$O,R40) -> 29929 | X40: 16200 | Y40: =SUMIFS(K:K,O:O,R40) -> 1329.8924 | Z40: =Y40*22% -> 292.57632 | AA40: =Y40+Z40 -> 1622.4687 | AB40: =(SUMIFS(N:N,O:O,R40))-Z40 -> 781.63387
A41: ENERO | B41: NEW | C41: 155 | D41: 1050 | E41: 800 | F41: 4499 | G41: 0 | H41: =SUM(E41:G41) -> 5299 | I41: =(LOOKUP(O41,$R$16:$R$40,$X$16:$X$40)*D41)/LOOKUP(O41,$R$16:$R$40,$T$16:$T$40) -> 913.64535 | J41: =I41*$T$2 -> 22.152637 | K41: =(H41*$T$2)+(I41*$T$2) -> 150.63446 | L41: =(LOOKUP(O41,$R$16:$R$27,$Z$16:$Z$27)*F41)/LOOKUP(O41,$R$16:$R$27,$U$16:$U$27)+K41 -> 184.59192 | M41: 170 | N41: =M41-L41 -> -14.591915 | O41: 12 | P41: 13 | R41: 25 | S41: 28 | T41: =SUMIFS(D:D,O:O,R41) -> 20506 | U41: =SUMIFS($F:$F,$O:$O,R41) -> 29609 | X41: 16200 | Y41: =SUMIFS(K:K,O:O,R41) -> 1344.3365 | Z41: =Y41*22% -> 295.75403 | AA41: =Y41+Z41 -> 1640.0905 | AB41: =(SUMIFS(N:N,O:O,R41))-Z41 -> 496.42733
A42: ENERO | B42: GACHA | C42: 99 | D42: 760 | E42: 500 | F42: 10285 | G42: 860 | H42: =SUM(E42:G42) -> 11645 | I42: =(LOOKUP(O42,$R$16:$R$40,$X$16:$X$40)*D42)/LOOKUP(O42,$R$16:$R$40,$T$16:$T$40) -> 620.10137 | J42: =I42*$T$2 -> 15.035244 | K42: =(H42*$T$2)+(I42*$T$2) -> 297.3849 | L42: =(LOOKUP(O42,$R$16:$R$27,$Z$16:$Z$27)*F42)/LOOKUP(O42,$R$16:$R$27,$U$16:$U$27)+K42 -> 393.16349 | M42: 650 | N42: =M42-L42 -> 256.83651 | O42: 9 | P42: 14 | R42: 26 | S42: 29 | T42: =SUMIFS(D:D,O:O,R42) -> 17366 | U42: =SUMIFS($F:$F,$O:$O,R42) -> 29403 | X42: 14400 | Y42: =SUMIFS(K:K,O:O,R42) -> 1251.126 | Z42: =Y42*22% -> 275.24771 | AA42: =Y42+Z42 -> 1526.3737 | AB42: =(SUMIFS(N:N,O:O,R42))-Z42 -> 921.69902
A43: ENERO | B43: USED | C43: 115 | D43: 2494 | E43: 500 | F43: 6062 | G43: 910 | H43: =SUM(E43:G43) -> 7472 | I43: =(LOOKUP(O43,$R$16:$R$40,$X$16:$X$40)*D43)/LOOKUP(O43,$R$16:$R$40,$T$16:$T$40) -> 2034.9116 | J43: =I43*$T$2 -> 49.339339 | K43: =(H43*$T$2)+(I43*$T$2) -> 230.50865 | L43: =(LOOKUP(O43,$R$16:$R$27,$Z$16:$Z$27)*F43)/LOOKUP(O43,$R$16:$R$27,$U$16:$U$27)+K43 -> 286.96075 | M43: 350 | N43: =M43-L43 -> 63.039253 | O43: 9 | P43: 14 | R43: 27 | S43: 30 | T43: =SUMIFS(D:D,O:O,R43) -> 9802 | U43: =SUMIFS($F:$F,$O:$O,R43) -> 41280 | X43: 9000 | Y43: =SUMIFS(K:K,O:O,R43) -> 1304.2201 | Z43: =Y43*22% -> 286.92842 | AA43: =Y43+Z43 -> 1591.1485 | AB43: =(SUMIFS(N:N,O:O,R43))-Z43 -> -302.7208
A44: ENERO | B44: MERCH | C44: 118 | D44: 6262 | E44: 500 | F44: 12 | G44: 1760 | H44: =SUM(E44:G44) -> 2272 | I44: =(LOOKUP(O44,$R$16:$R$40,$X$16:$X$40)*D44)/LOOKUP(O44,$R$16:$R$40,$T$16:$T$40) -> 5109.3089 | J44: =I44*$T$2 -> 123.88249 | K44: =(H44*$T$2)+(I44*$T$2) -> 178.97038 | L44: =(LOOKUP(O44,$R$16:$R$27,$Z$16:$Z$27)*F44)/LOOKUP(O44,$R$16:$R$27,$U$16:$U$27)+K44 -> 179.08213 | M44: 100 | N44: =M44-L44 -> -79.082129 | O44: 9 | P44: 14 | R44: 28 | S44: 31 | T44: =SUMIFS(D:D,O:O,R44) -> 12444 | U44: =SUMIFS($F:$F,$O:$O,R44) -> 28297 | X44: 11400 | Y44: =SUMIFS(K:K,O:O,R44) -> 1017.0248 | Z44: =Y44*22% -> 223.74545 | AA44: =Y44+Z44 -> 1240.7702 | AB44: =(SUMIFS(N:N,O:O,R44))-Z44 -> 445.65032
A45: ENERO | B45: NEW | C45: 131 | D45: 6410 | E45: 800 | F45: 10200 | G45: 0 | H45: =SUM(E45:G45) -> 11000 | I45: =(LOOKUP(O45,$R$16:$R$40,$X$16:$X$40)*D45)/LOOKUP(O45,$R$16:$R$40,$T$16:$T$40) -> 5230.0655 | J45: =I45*$T$2 -> 126.81041 | K45: =(H45*$T$2)+(I45*$T$2) -> 393.52112 | L45: =(LOOKUP(O45,$R$16:$R$27,$Z$16:$Z$27)*F45)/LOOKUP(O45,$R$16:$R$27,$U$16:$U$27)+K45 -> 488.50815 | M45: 800 | N45: =M45-L45 -> 311.49185 | O45: 9 | P45: 14 | R45: 29 | S45: 32 | T45: =SUMIFS(D:D,O:O,R45) -> 0 | U45: =SUMIFS($F:$F,$O:$O,R45) -> 0 | X45: 10800 | Y45: =SUMIFS(K:K,O:O,R45) -> 0 | Z45: =Y45*22% -> 0 | AA45: =Y45+Z45 -> 0 | AB45: =(SUMIFS(N:N,O:O,R45))-Z45 -> 0
A46: ENERO | B46: NEW | C46: 153 | D46: 252 | E46: 800 | F46: 1200 | G46: 0 | H46: =SUM(E46:G46) -> 2000 | I46: =(LOOKUP(O46,$R$16:$R$40,$X$16:$X$40)*D46)/LOOKUP(O46,$R$16:$R$40,$T$16:$T$40) -> 205.61256 | J46: =I46*$T$2 -> 4.9853703 | K46: =(H46*$T$2)+(I46*$T$2) -> 53.478227 | L46: =(LOOKUP(O46,$R$16:$R$27,$Z$16:$Z$27)*F46)/LOOKUP(O46,$R$16:$R$27,$U$16:$U$27)+K46 -> 64.653172 | M46: 65 | N46: =M46-L46 -> 0.34682827 | O46: 9 | P46: 14 | R46: 30 | S46: 33 | T46: =SUMIFS(D:D,O:O,R46) -> 0 | U46: =SUMIFS($F:$F,$O:$O,R46) -> 0 | X46: 12600 | Y46: =SUMIFS(K:K,O:O,R46) -> 0 | Z46: =Y46*22% -> 0 | AA46: =Y46+Z46 -> 0 | AB46: =(SUMIFS(N:N,O:O,R46))-Z46 -> 0
A47: ENERO | B47: NEW | C47: 133 | D47: 154 | E47: 800 | F47: 3500 | G47: 0 | H47: =SUM(E47:G47) -> 4300 | I47: =(LOOKUP(O47,$R$16:$R$40,$X$16:$X$40)*D47)/LOOKUP(O47,$R$16:$R$40,$T$16:$T$40) -> 150.62489 | J47: =I47*$T$2 -> 3.6521156 | K47: =(H47*$T$2)+(I47*$T$2) -> 107.91176 | L47: =(LOOKUP(O47,$R$16:$R$27,$Z$16:$Z$27)*F47)/LOOKUP(O47,$R$16:$R$27,$U$16:$U$27)+K47 -> 134.32898 | M47: 160 | N47: =M47-L47 -> 25.671018 | O47: 14 | P47: 15 | R47: 31 | S47: 32 | T47: =SUMIFS(D:D,O:O,R47) -> 10616 | U47: =SUMIFS($F:$F,$O:$O,R47) -> 21100 | X47: 9000 | Y47: =SUMIFS(K:K,O:O,R47) -> 855.80152 | Z47: =Y47*22% -> 188.27633 | AA47: =Y47+Z47 -> 1044.0779 | AB47: =(SUMIFS(N:N,O:O,R47))-Z47 -> 436.66403
... A50: ENERO | B50: NEW | C50: 132 | D50: 10300 | E50: 800 | F50: 25555 | G50: 0 | H50: =SUM(E50:G50) -> 26355 | I50: =(LOOKUP(O50,$R$16:$R$40,$X$16:$X$40)*D50)/LOOKUP(O50,$R$16:$R$40,$T$16:$T$40) -> 9469.4503 | J50: =I50*$T$2 -> 229.60035 | K50: =(H50*$T$2)+(I50*$T$2) -> 868.61498 | L50: =(LOOKUP(O50,$R$16:$R$27,$Z$16:$Z$27)*F50)/LOOKUP(O50,$R$16:$R$27,$U$16:$U$27)+K50 -> 1061.4984 | M50: 1300 | N50: =M50-L50 -> 238.50156 | O50: 11 | P50: 16 | R50: 34 | S50: 35 | T50: =SUMIFS(D:D,O:O,R50) -> 16204 | U50: =SUMIFS($F:$F,$O:$O,R50) -> 19345 | X50: 14400 | Y50: =SUMIFS(K:K,O:O,R50) -> 944.4486 | Z50: =Y50*22% -> 207.77869 | AA50: =Y50+Z50 -> 1152.2273 | AB50: =(SUMIFS(N:N,O:O,R50))-Z50 -> -348.23906
A51: ENERO | B51: ROXANA | C51: 158 | D51: 142 | E51: 800 | F51: 3200 | G51: 0 | H51: =SUM(E51:G51) -> 4000 | I51: =(LOOKUP(O51,$R$16:$R$40,$X$16:$X$40)*D51)/LOOKUP(O51,$R$16:$R$40,$T$16:$T$40) -> 130.5497 | J51: =I51*$T$2 -> 3.1653641 | K51: =(H51*$T$2)+(I51*$T$2) -> 100.15108 | L51: =(LOOKUP(O51,$R$16:$R$27,$Z$16:$Z$27)*F51)/LOOKUP(O51,$R$16:$R$27,$U$16:$U$27)+K51 -> 124.30397 | M51: =K51 -> 100.15108 | N51: =M51-L51 -> -24.15289 | O51: 11 | P51: 16 | R51: 35 | S51: 36 | T51: =SUMIFS(D:D,O:O,R51) -> 14420 | U51: =SUMIFS($F:$F,$O:$O,R51) -> 35420 | X51: 11400 | Y51: =SUMIFS(K:K,O:O,R51) -> 1292.4433 | Z51: =Y51*22% -> 284.33753 | AA51: =Y51+Z51 -> 1576.7809 | AB51: =(SUMIFS(N:N,O:O,R51))-Z51 -> 50.876833
A52: ENERO | B52: NEW | C52: 130 | D52: 10950 | E52: 800 | F52: 20777 | G52: 0 | H52: =SUM(E52:G52) -> 21577 | I52: =(LOOKUP(O52,$R$16:$R$40,$X$16:$X$40)*D52)/LOOKUP(O52,$R$16:$R$40,$T$16:$T$40) -> 9927.1978 | J52: =I52*$T$2 -> 240.69909 | K52: =(H52*$T$2)+(I52*$T$2) -> 763.86428 | L52: =(LOOKUP(O52,$R$16:$R$27,$Z$16:$Z$27)*F52)/LOOKUP(O52,$R$16:$R$27,$U$16:$U$27)+K52 -> 920.68447 | M52: 1100 | N52: =M52-L52 -> 179.31553 | O52: 13 | P52: 17 | R52: 36 | S52: 37 | T52: =SUMIFS(D:D,O:O,R52) -> 17690 | U52: =SUMIFS($F:$F,$O:$O,R52) -> 29000 | X52: 12600 | Y52: =SUMIFS(K:K,O:O,R52) -> 1177.1712 | Z52: =Y52*22% -> 258.97766 | AA52: =Y52+Z52 -> 1436.1488 | AB52: =(SUMIFS(N:N,O:O,R52))-Z52 -> 144.96561
A53: ENERO | B53: NEW | C53: 159 | D53: 3610 | E53: 800 | F53: 7500 | G53: 0 | H53: =SUM(E53:G53) -> 8300 | I53: =(LOOKUP(O53,$R$16:$R$40,$X$16:$X$40)*D53)/LOOKUP(O53,$R$16:$R$40,$T$16:$T$40) -> 3272.8022 | J53: =I53*$T$2 -> 79.353765 | K53: =(H53*$T$2)+(I53*$T$2) -> 280.59912 | L53: =(LOOKUP(O53,$R$16:$R$27,$Z$16:$Z$27)*F53)/LOOKUP(O53,$R$16:$R$27,$U$16:$U$27)+K53 -> 337.20746 | M53: 500 | N53: =M53-L53 -> 162.79254 | O53: 13 | P53: 17 | R53: 37 | S53: 38 | T53: =SUMIFS(D:D,O:O,R53) -> 13040 | U53: =SUMIFS($F:$F,$O:$O,R53) -> 28132 | X53: 14400 | Y53: =SUMIFS(K:K,O:O,R53) -> 1065.1232 | Z53: =Y53*22% -> 234.32711 | AA53: =Y53+Z53 -> 1299.4503 | AB53: =(SUMIFS(N:N,O:O,R53))-Z53 -> 438.21556
A54: ENERO | B54: NEW | C54: 134 | D54: 1204 | E54: 800 | F54: 6666 | G54: 0 | H54: =SUM(E54:G54) -> 7466 | I54: =(LOOKUP(O54,$R$16:$R$40,$X$16:$X$40)*D54)/LOOKUP(O54,$R$16:$R$40,$T$16:$T$40) -> 1046.0722 | J54: =I54*$T$2 -> 25.363514 | K54: =(H54*$T$2)+(I54*$T$2) -> 206.38735 | L54: =(LOOKUP(O54,$R$16:$R$27,$Z$16:$Z$27)*F54)/LOOKUP(O54,$R$16:$R$27,$U$16:$U$27)+K54 -> 256.70084 | M54: 300 | N54: =M54-L54 -> 43.299162 | O54: 16 | P54: 18 | R54: 38 | S54: 39 | T54: =SUMIFS(D:D,O:O,R54) -> 14920 | U54: =SUMIFS($F:$F,$O:$O,R54) -> 16750 | X54: 11400 | Y54: =SUMIFS(K:K,O:O,R54) -> 806.59239 | Z54: =Y54*22% -> 177.45033 | AA54: =Y54+Z54 -> 984.04272 | AB54: =(SUMIFS(N:N,O:O,R54))-Z54 -> 358.532
A55: ENERO | B55: NEW | C55: 146 | D55: 2376 | E55: 800 | F55: 4980 | G55: 0 | H55: =SUM(E55:G55) -> 5780 | I55: =(LOOKUP(O55,$R$16:$R$40,$X$16:$X$40)*D55)/LOOKUP(O55,$R$16:$R$40,$T$16:$T$40) -> 2064.3417 | J55: =I55*$T$2 -> 50.052915 | K55: =(H55*$T$2)+(I55*$T$2) -> 190.19727 | L55: =(LOOKUP(O55,$R$16:$R$27,$Z$16:$Z$27)*F55)/LOOKUP(O55,$R$16:$R$27,$U$16:$U$27)+K55 -> 227.78521 | M55: 250 | N55: =M55-L55 -> 22.214793 | O55: 16 | P55: 18 | R55: 39 | S55: 40 | T55: =SUMIFS(D:D,O:O,R55) -> 4990 | U55: =SUMIFS($F:$F,$O:$O,R55) -> 16499 | X55: 12600 | Y55: =SUMIFS(K:K,O:O,R55) -> 619.37273 | Z55: =Y55*22% -> 136.262 | AA55: =Y55+Z55 -> 755.63472 | AB55: =(SUMIFS(N:N,O:O,R55))-Z55 -> 69.834484
A56: ENERO | B56: JUNK | C56: 160 | D56: 6834 | E56: 500 | F56: 9000 | G56: 1620 | H56: =SUM(E56:G56) -> 11120 | I56: =(LOOKUP(O56,$R$16:$R$40,$X$16:$X$40)*D56)/LOOKUP(O56,$R$16:$R$40,$T$16:$T$40) -> 5937.589 | J56: =I56*$T$2 -> 143.96533 | K56: =(H56*$T$2)+(I56*$T$2) -> 413.58561 | L56: =(LOOKUP(O56,$R$16:$R$27,$Z$16:$Z$27)*F56)/LOOKUP(O56,$R$16:$R$27,$U$16:$U$27)+K56 -> 481.51562 | M56: 1000 | N56: =M56-L56 -> 518.48438 | O56: 16 | P56: 18 | R56: 40 | S56: 41 | T56: =SUMIFS(D:D,O:O,R56) -> 9476 | U56: =SUMIFS($F:$F,$O:$O,R56) -> 19616 | X56: 9600 | Y56: =SUMIFS(K:K,O:O,R56) -> 761.48334 | Z56: =Y56*22% -> 167.52633 | AA56: =Y56+Z56 -> 929.00967 | AB56: =(SUMIFS(N:N,O:O,R56))-Z56 -> 372.93312
A57: ENERO | B57: NEW | C57: 163 | D57: 6160 | E57: 500 | F57: 8400 | G57: 1980 | H57: =SUM(E57:G57) -> 10880 | I57: =(LOOKUP(O57,$R$16:$R$40,$X$16:$X$40)*D57)/LOOKUP(O57,$R$16:$R$40,$T$16:$T$40) -> 5351.9971 | J57: =I57*$T$2 -> 129.76682 | K57: =(H57*$T$2)+(I57*$T$2) -> 393.56796 | L57: =(LOOKUP(O57,$R$16:$R$27,$Z$16:$Z$27)*F57)/LOOKUP(O57,$R$16:$R$27,$U$16:$U$27)+K57 -> 456.96929 | M57: 700 | N57: =M57-L57 -> 243.03071 | O57: 16 | P57: 18 | R57: 41 | S57: 42 | T57: =SUMIFS(D:D,O:O,R57) -> 8530 | U57: =SUMIFS($F:$F,$O:$O,R57) -> 20800 | X57: 9000 | Y57: =SUMIFS(K:K,O:O,R57) -> 816.86218 | Z57: =Y57*22% -> 179.70968 | AA57: =Y57+Z57 -> 996.57186 | AB57: =(SUMIFS(N:N,O:O,R57))-Z57 -> 316.43436
A58: FEBRERO | B58: NEW | C58: 151 | D58: 1480 | E58: 800 | F58: 3999 | G58: 0 | H58: =SUM(E58:G58) -> 4799 | I58: =(LOOKUP(O58,$R$16:$R$40,$X$16:$X$40)*D58)/LOOKUP(O58,$R$16:$R$40,$T$16:$T$40) -> 1252.1472 | J58: =I58*$T$2 -> 30.360097 | K58: =(H58*$T$2)+(I58*$T$2) -> 146.71871 | L58: =(LOOKUP(O58,$R$16:$R$27,$Z$16:$Z$27)*F58)/LOOKUP(O58,$R$16:$R$27,$U$16:$U$27)+K58 -> 176.90227 | M58: 220 | N58: =M58-L58 -> 43.097728 | O58: 17 | P58: 19 | R58: 42 | S58: 44 | T58: =SUMIFS(D:D,O:O,R58) -> 8060 | U58: =SUMIFS($F:$F,$O:$O,R58) -> 18888 | X58: 8300 | Y58: =SUMIFS(K:K,O:O,R58) -> 678.60904 | Z58: =Y58*22% -> 149.29399 | AA58: =Y58+Z58 -> 827.90303 | AB58: =(SUMIFS(N:N,O:O,R58))-Z58 -> 79.534535
A59: FEBRERO | B59: JUNK | C59: 161 | D59: 898 | E59: 800 | F59: 2200 | G59: 0 | H59: =SUM(E59:G59) -> 3000 | I59: =(LOOKUP(O59,$R$16:$R$40,$X$16:$X$40)*D59)/LOOKUP(O59,$R$16:$R$40,$T$16:$T$40) -> 759.74875 | J59: =I59*$T$2 -> 18.421194 | K59: =(H59*$T$2)+(I59*$T$2) -> 91.16048 | L59: =(LOOKUP(O59,$R$16:$R$27,$Z$16:$Z$27)*F59)/LOOKUP(O59,$R$16:$R$27,$U$16:$U$27)+K59 -> 107.76559 | M59: 200 | N59: =M59-L59 -> 92.234409 | O59: 17 | P59: 19 | R59: 43 | S59: 45 | T59: =SUMIFS(D:D,O:O,R59) -> 4625 | U59: =SUMIFS($F:$F,$O:$O,R59) -> 18498 | X59: 6200 | Y59: =SUMIFS(K:K,O:O,R59) -> 657.02972 | Z59: =Y59*22% -> 144.54654 | AA59: =Y59+Z59 -> 801.57626 | AB59: =(SUMIFS(N:N,O:O,R59))-Z59 -> 158.80494
B60: USED | C60: 162 | D60: 7190 | E60: 500 | F60: 12500 | G60: 2120 | H60: =SUM(E60:G60) -> 15120 | I60: =(LOOKUP(O60,$R$16:$R$40,$X$16:$X$40)*D60)/LOOKUP(O60,$R$16:$R$40,$T$16:$T$40) -> 6083.0663 | J60: =I60*$T$2 -> 147.49263 | K60: =(H60*$T$2)+(I60*$T$2) -> 514.09863 | L60: =(LOOKUP(O60,$R$16:$R$27,$Z$16:$Z$27)*F60)/LOOKUP(O60,$R$16:$R$27,$U$16:$U$27)+K60 -> 608.44586 | M60: 750 | N60: =M60-L60 -> 141.55414 | O60: 17 | P60: 19 | R60: 44 | S60: 46 | T60: =SUMIFS(D:D,O:O,R60) -> 10220 | U60: =SUMIFS($F:$F,$O:$O,R60) -> 27646 | X60: 10200 | Y60: =SUMIFS(K:K,O:O,R60) -> 988.81785 | Z60: =Y60*22% -> 217.53993 | AA60: =Y60+Z60 -> 1206.3578 | AB60: =(SUMIFS(N:N,O:O,R60))-Z60 -> 294.97635
B61: JUNK | C61: 166 | D61: 4628 | E61: 500 | F61: 3500 | G61: 1980 | H61: =SUM(E61:G61) -> 5980 | I61: =(LOOKUP(O61,$R$16:$R$40,$X$16:$X$40)*D61)/LOOKUP(O61,$R$16:$R$40,$T$16:$T$40) -> 3915.498 | J61: =I61*$T$2 -> 94.936843 | K61: =(H61*$T$2)+(I61*$T$2) -> 239.93049 | L61: =(LOOKUP(O61,$R$16:$R$27,$Z$16:$Z$27)*F61)/LOOKUP(O61,$R$16:$R$27,$U$16:$U$27)+K61 -> 266.34771 | M61: 600 | N61: =M61-L61 -> 333.65229 | O61: 17 | P61: 19 | R61: 45 | S61: 47 | T61: =SUMIFS(D:D,O:O,R61) -> 11559 | U61: =SUMIFS($F:$F,$O:$O,R61) -> 59016 | X61: 10200 | Y61: =SUMIFS(K:K,O:O,R61) -> 1747.1007 | Z61: =Y61*22% -> 384.36214 | AA61: =Y61+Z61 -> 2131.4628 | AB61: =(SUMIFS(N:N,O:O,R61))-Z61 -> 373.09753
B62: MOCHI | C62: 169 | D62: 98 | E62: 500 | F62: 2550 | G62: 450 | H62: =SUM(E62:G62) -> 3500 | I62: =(LOOKUP(O62,$R$16:$R$40,$X$16:$X$40)*D62)/LOOKUP(O62,$R$16:$R$40,$T$16:$T$40) -> 82.912447 | J62: =I62*$T$2 -> 2.0103307 | K62: =(H62*$T$2)+(I62*$T$2) -> 86.872831 | L62: =(LOOKUP(O62,$R$16:$R$27,$Z$16:$Z$27)*F62)/LOOKUP(O62,$R$16:$R$27,$U$16:$U$27)+K62 -> 106.11966 | M62: 0 | N62: =M62-L62 -> -106.11966 | O62: 17 | P62: 19 | R62: 46 | S62: 48 | T62: =SUMIFS(D:D,O:O,R62) -> 4002 | U62: =SUMIFS($F:$F,$O:$O,R62) -> 17849 | X62: 5500 | Y62: =SUMIFS(K:K,O:O,R62) -> 617.04736 | Z62: =Y62*22% -> 135.75042 | AA62: =Y62+Z62 -> 752.79778 | AB62: =(SUMIFS(N:N,O:O,R62))-Z62 -> 502.48193
B63: POKE | C63: 170 | D63: 414 | E63: 500 | F63: 1000 | G63: 810 | H63: =SUM(E63:G63) -> 2310 | I63: =(LOOKUP(O63,$R$16:$R$40,$X$16:$X$40)*D63)/LOOKUP(O63,$R$16:$R$40,$T$16:$T$40) -> 350.26279 | J63: =I63*$T$2 -> 8.4926216 | K63: =(H63*$T$2)+(I63*$T$2) -> 64.501872 | L63: =(LOOKUP(O63,$R$16:$R$27,$Z$16:$Z$27)*F63)/LOOKUP(O63,$R$16:$R$27,$U$16:$U$27)+K63 -> 72.04965 | M63: 150 | N63: =M63-L63 -> 77.95035 | O63: 17 | P63: 19 | R63: 47 | S63: 49 | T63: =SUMIFS(D:D,O:O,R63) -> 5382 | U63: =SUMIFS($F:$F,$O:$O,R63) -> 20471 | X63: 7600 | Y63: =SUMIFS(K:K,O:O,R63) -> 758.21007 | Z63: =Y63*22% -> 166.80621 | AA63: =Y63+Z63 -> 925.01628 | AB63: =(SUMIFS(N:N,O:O,R63))-Z63 -> 300.47315
B64: PED-JEAN | C64: 172 | D64: 894 | E64: 800 | F64: 3700 | G64: 0 | H64: =SUM(E64:G64) -> 4500 | I64: =(LOOKUP(O64,$R$16:$R$40,$X$16:$X$40)*D64)/LOOKUP(O64,$R$16:$R$40,$T$16:$T$40) -> 756.36457 | J64: =I64*$T$2 -> 18.339139 | K64: =(H64*$T$2)+(I64*$T$2) -> 127.44807 | L64: =(LOOKUP(O64,$R$16:$R$27,$Z$16:$Z$27)*F64)/LOOKUP(O64,$R$16:$R$27,$U$16:$U$27)+K64 -> 155.37485 | M64: 260 | N64: =M64-L64 -> 104.62515 | O64: 17 | P64: 19 | R64: 48 | S64: 50 | T64: =SUMIFS(D:D,O:O,R64) -> 12828 | U64: =SUMIFS($F:$F,$O:$O,R64) -> 50977 | X64: 12000 | Y64: =SUMIFS(K:K,O:O,R64) -> 1573.9249 | Z64: =Y64*22% -> 346.26347 | AA64: =Y64+Z64 -> 1920.1883 | AB64: =(SUMIFS(N:N,O:O,R64))-Z64 -> 170.15705
B65: USED | C65: 165 | D65: 4122 | E65: 800 | F65: 11111 | G65: 0 | H65: =SUM(E65:G65) -> 11911 | I65: =(LOOKUP(O65,$R$16:$R$40,$X$16:$X$40)*D65)/LOOKUP(O65,$R$16:$R$40,$T$16:$T$40) -> 3156.9523 | J65: =I65*$T$2 -> 76.544819 | K65: =(H65*$T$2)+(I65*$T$2) -> 365.34403 | L65: =(LOOKUP(O65,$R$16:$R$27,$Z$16:$Z$27)*F65)/LOOKUP(O65,$R$16:$R$27,$U$16:$U$27)+K65 -> 449.20739 | M65: 1080 | N65: =M65-L65 -> 630.79261 | O65: 18 | P65: 20 | R65: 49 | S65: 51 | T65: =SUMIFS(D:D,O:O,R65) -> 21900 | U65: =SUMIFS($F:$F,$O:$O,R65) -> 39017 | X65: 14400 | Y65: =SUMIFS(K:K,O:O,R65) -> 1480.002 | Z65: =Y65*22% -> 325.60044 | AA65: =Y65+Z65 -> 1805.6024 | AB65: =(SUMIFS(N:N,O:O,R65))-Z65 -> 489.9059
B66: JUNK | C66: 167 | D66: 6030 | E66: 500 | F66: 4300 | G66: 1620 | H66: =SUM(E66:G66) -> 6420 | I66: =(LOOKUP(O66,$R$16:$R$40,$X$16:$X$40)*D66)/LOOKUP(O66,$R$16:$R$40,$T$16:$T$40) -> 4618.249 | J66: =I66*$T$2 -> 111.97605 | K66: =(H66*$T$2)+(I66*$T$2) -> 267.63812 | L66: =(LOOKUP(O66,$R$16:$R$27,$Z$16:$Z$27)*F66)/LOOKUP(O66,$R$16:$R$27,$U$16:$U$27)+K66 -> 300.09356 | M66: 850 | N66: =M66-L66 -> 549.90644 | O66: 18 | P66: 20 | R66: 50 | S66: 52 | T66: =SUMIFS(D:D,O:O,R66) -> 7000 | U66: =SUMIFS($F:$F,$O:$O,R66) -> 15980 | X66: 6900 | Y66: =SUMIFS(K:K,O:O,R66) -> 648.83443 | Z66: =Y66*22% -> 142.74357 | AA66: =Y66+Z66 -> 791.578 | AB66: =(SUMIFS(N:N,O:O,R66))-Z66 -> 637.8085
B67: JUNK | C67: 168 | D67: 4916 | E67: 500 | F67: 6700 | G67: 1620 | H67: =SUM(E67:G67) -> 8820 | I67: =(LOOKUP(O67,$R$16:$R$40,$X$16:$X$40)*D67)/LOOKUP(O67,$R$16:$R$40,$T$16:$T$40) -> 3765.0601 | J67: =I67*$T$2 -> 91.28926 | K67: =(H67*$T$2)+(I67*$T$2) -> 305.14276 | L67: =(LOOKUP(O67,$R$16:$R$27,$Z$16:$Z$27)*F67)/LOOKUP(O67,$R$16:$R$27,$U$16:$U$27)+K67 -> 355.71287 | M67: 800 | N67: =M67-L67 -> 444.28713 | O67: 18 | P67: 20 | R67: 51 | S67: 53 | T67: =SUMIFS(D:D,O:O,R67) -> 1600 | U67: =SUMIFS($F:$F,$O:$O,R67) -> 10900 | X67: 4100 | Y67: =SUMIFS(K:K,O:O,R67) -> 403.38454 | Z67: =Y67*22% -> 88.744598 | AA67: =Y67+Z67 -> 492.12914 | AB67: =(SUMIFS(N:N,O:O,R67))-Z67 -> -574.39992
B68: JUNK | C68: 171 | D68: 7091 | E68: 500 | F68: 4950 | G68: 2010 | H68: =SUM(E68:G68) -> 7460 | I68: =(LOOKUP(O68,$R$16:$R$40,$X$16:$X$40)*D68)/LOOKUP(O68,$R$16:$R$40,$T$16:$T$40) -> 5430.8464 | J68: =I68*$T$2 -> 131.67863 | K68: =(H68*$T$2)+(I68*$T$2) -> 312.55699 | L68: =(LOOKUP(O68,$R$16:$R$27,$Z$16:$Z$27)*F68)/LOOKUP(O68,$R$16:$R$27,$U$16:$U$27)+K68 -> 349.91849 | M68: 1100 | N68: =M68-L68 -> 750.08151 | O68: 18 | P68: 20 | R68: 52 | S68: 54 | T68: =SUMIFS(D:D,O:O,R68) -> 6300 | U68: =SUMIFS($F:$F,$O:$O,R68) -> 18833 | X68: 7600 | Y68: =SUMIFS(K:K,O:O,R68) -> 679.70013 | Z68: =Y68*22% -> 149.53403 | AA68: =Y68+Z68 -> 829.23416 | AB68: =(SUMIFS(N:N,O:O,R68))-Z68 -> -971.38147
B69: PED-NICO | C69: 175 | D69: 560 | E69: 800 | F69: 2888 | G69: 0 | H69: =SUM(E69:G69) -> 3688 | I69: =(LOOKUP(O69,$R$16:$R$40,$X$16:$X$40)*D69)/LOOKUP(O69,$R$16:$R$40,$T$16:$T$40) -> 428.89212 | J69: =I69*$T$2 -> 10.399102 | K69: =(H69*$T$2)+(I69*$T$2) -> 99.819931 | L69: =(LOOKUP(O69,$R$16:$R$27,$Z$16:$Z$27)*F69)/LOOKUP(O69,$R$16:$R$27,$U$16:$U$27)+K69 -> 121.61791 | M69: 190 | N69: =M69-L69 -> 68.382086 | O69: 18 | P69: 20 | R69: 53 | S69: 55 | T69: =SUMIFS(D:D,O:O,R69) -> 7790 | U69: =SUMIFS($F:$F,$O:$O,R69) -> 20900 | X69: 8300 | Y69: =SUMIFS(K:K,O:O,R69) -> 763.7625 | Z69: =Y69*22% -> 168.02775 | AA69: =Y69+Z69 -> 931.79025 | AB69: =(SUMIFS(N:N,O:O,R69))-Z69 -> -1089.5388
B70: CARTAS | C70: 177 | D70: 3348 | E70: 500 | F70: 580 | G70: 750 | H70: =SUM(E70:G70) -> 1830 | I70: =(LOOKUP(O70,$R$16:$R$40,$X$16:$X$40)*D70)/LOOKUP(O70,$R$16:$R$40,$T$16:$T$40) -> 3041.0765 | J70: =I70*$T$2 -> 73.735245 | K70: =(H70*$T$2)+(I70*$T$2) -> 118.10621 | L70: =(LOOKUP(O70,$R$16:$R$27,$Z$16:$Z$27)*F70)/LOOKUP(O70,$R$16:$R$27,$U$16:$U$27)+K70 -> 122.48392 | M70: 400 | N70: =M70-L70 -> 277.51608 | O70: 20 | P70: 21 | R70: 54 | S70: 56 | T70: =SUMIFS(D:D,O:O,R70) -> 14800 | U70: =SUMIFS($F:$F,$O:$O,R70) -> 19980 | X70: 12600 | Y70: =SUMIFS(K:K,O:O,R70) -> 887.90421 | Z70: =Y70*22% -> 195.33893 | AA70: =Y70+Z70 -> 1083.2431 | AB70: =(SUMIFS(N:N,O:O,R70))-Z70 -> -1234.0477
B71: NEW | C71: 180 | D71: 2206 | E71: 800 | F71: 11999 | G71: 0 | H71: =SUM(E71:G71) -> 12799 | I71: =(LOOKUP(O71,$R$16:$R$40,$X$16:$X$40)*D71)/LOOKUP(O71,$R$16:$R$40,$T$16:$T$40) -> 2003.7679 | J71: =I71*$T$2 -> 48.584215 | K71: =(H71*$T$2)+(I71*$T$2) -> 358.91425 | L71: =(LOOKUP(O71,$R$16:$R$27,$Z$16:$Z$27)*F71)/LOOKUP(O71,$R$16:$R$27,$U$16:$U$27)+K71 -> 449.48004 | M71: 500 | N71: =M71-L71 -> 50.519957 | O71: 20 | P71: 21 | R71: 55 | S71: 57 | T71: =SUMIFS(D:D,O:O,R71) -> 9090 | U71: =SUMIFS($F:$F,$O:$O,R71) -> 18350 | X71: 9600 | Y71: =SUMIFS(K:K,O:O,R71) -> 738.06129 | Z71: =Y71*22% -> 162.37348 | AA71: =Y71+Z71 -> 900.43477 | AB71: =(SUMIFS(N:N,O:O,R71))-Z71 -> -1038.9365
... B74: JUNK | C74: 174 | D74: 13830 | E74: 500 | F74: 20350 | G74: 1210 | H74: =SUM(E74:G74) -> 22060 | I74: =(LOOKUP(O74,$R$16:$R$40,$X$16:$X$40)*D74)/LOOKUP(O74,$R$16:$R$40,$T$16:$T$40) -> 11620.492 | J74: =I74*$T$2 -> 281.75544 | K74: =(H74*$T$2)+(I74*$T$2) -> 816.63166 | L74: =(LOOKUP(O74,$R$16:$R$27,$Z$16:$Z$27)*F74)/LOOKUP(O74,$R$16:$R$27,$U$16:$U$27)+K74 -> 970.22894 | M74: 1200 | N74: =M74-L74 -> 229.77106 | O74: 19 | P74: 22 | R74: 58 | S74: 60 | T74: =SUMIFS(D:D,O:O,R74) -> 9460 | U74: =SUMIFS($F:$F,$O:$O,R74) -> 39499 | X74: 9600 | Y74: =SUMIFS(K:K,O:O,R74) -> 1263.2147 | Z74: =Y74*22% -> 277.90723 | AA74: =Y74+Z74 -> 1541.1219 | AB74: =(SUMIFS(N:N,O:O,R74))-Z74 -> -1839.2516
B75: PELUCHE | C75: 176 | D75: 3308 | E75: 500 | F75: 8825 | G75: 902 | H75: =SUM(E75:G75) -> 10227 | I75: =(LOOKUP(O75,$R$16:$R$40,$X$16:$X$40)*D75)/LOOKUP(O75,$R$16:$R$40,$T$16:$T$40) -> 2779.5075 | J75: =I75*$T$2 -> 67.393131 | K75: =(H75*$T$2)+(I75*$T$2) -> 315.36136 | L75: =(LOOKUP(O75,$R$16:$R$27,$Z$16:$Z$27)*F75)/LOOKUP(O75,$R$16:$R$27,$U$16:$U$27)+K75 -> 381.9705 | M75: 550 | N75: =M75-L75 -> 168.0295 | O75: 19 | P75: 22 | R75: 59 | T75: =SUMIFS(D:D,O:O,R75) -> 0 | U75: =SUMIFS($F:$F,$O:$O,R75) -> 0 | Y75: =SUMIFS(K:K,O:O,R75) -> 0 | Z75: =Y75*22% -> 0 | AA75: =Y75+Z75 -> 0 | AB75: =(SUMIFS(N:N,O:O,R75))-Z75 -> 0
B76: USED | C76: 184 | D76: 1566 | E76: 800 | F76: 10500 | G76: 0 | H76: =SUM(E76:G76) -> 11300 | I76: =(LOOKUP(O76,$R$16:$R$40,$X$16:$X$40)*D76)/LOOKUP(O76,$R$16:$R$40,$T$16:$T$40) -> 1228.0957 | J76: =I76*$T$2 -> 29.776935 | K76: =(H76*$T$2)+(I76*$T$2) -> 303.76158 | L76: =(LOOKUP(O76,$R$16:$R$27,$Z$16:$Z$27)*F76)/LOOKUP(O76,$R$16:$R$27,$U$16:$U$27)+K76 -> 383.01325 | M76: 500 | N76: =M76-L76 -> 116.98675 | O76: 21 | P76: 23 | R76: 60 | T76: =SUMIFS(D:D,O:O,R76) -> 0 | U76: =SUMIFS($F:$F,$O:$O,R76) -> 0 | Y76: =SUMIFS(K:K,O:O,R76) -> 0 | Z76: =Y76*22% -> 0 | AA76: =Y76+Z76 -> 0 | AB76: =(SUMIFS(N:N,O:O,R76))-Z76 -> 0
B77: PELUCHE | C77: 186 | D77: 6136 | E77: 500 | F77: 6025 | G77: 2440 | H77: =SUM(E77:G77) -> 8965 | I77: =(LOOKUP(O77,$R$16:$R$40,$X$16:$X$40)*D77)/LOOKUP(O77,$R$16:$R$40,$T$16:$T$40) -> 4812.002 | J77: =I77*$T$2 -> 116.67386 | K77: =(H77*$T$2)+(I77*$T$2) -> 334.0431 | L77: =(LOOKUP(O77,$R$16:$R$27,$Z$16:$Z$27)*F77)/LOOKUP(O77,$R$16:$R$27,$U$16:$U$27)+K77 -> 379.51846 | M77: 750 | N77: =M77-L77 -> 370.48154 | O77: 21 | P77: 23 | R77: 61 | T77: =SUMIFS(D:D,O:O,R77) -> 0 | U77: =SUMIFS($F:$F,$O:$O,R77) -> 0 | Y77: =SUMIFS(K:K,O:O,R77) -> 0 | Z77: =Y77*22% -> 0 | AA77: =Y77+Z77 -> 0 | AB77: =(SUMIFS(N:N,O:O,R77))-Z77 -> 0
B78: PELUCHE | C78: 187 | D78: 6147 | E78: 500 | F78: 10051 | G78: 2440 | H78: =SUM(E78:G78) -> 12991 | I78: =(LOOKUP(O78,$R$16:$R$40,$X$16:$X$40)*D78)/LOOKUP(O78,$R$16:$R$40,$T$16:$T$40) -> 4820.6285 | J78: =I78*$T$2 -> 116.88303 | K78: =(H78*$T$2)+(I78*$T$2) -> 431.86838 | L78: =(LOOKUP(O78,$R$16:$R$27,$Z$16:$Z$27)*F78)/LOOKUP(O78,$R$16:$R$27,$U$16:$U$27)+K78 -> 507.7311 | M78: 1000 | N78: =M78-L78 -> 492.2689 | O78: 21 | P78: 23 | R78: 62 | T78: =SUMIFS(D:D,O:O,R78) -> 0 | U78: =SUMIFS($F:$F,$O:$O,R78) -> 0 | Y78: =SUMIFS(K:K,O:O,R78) -> 0 | Z78: =Y78*22% -> 0 | AA78: =Y78+Z78 -> 0 | AB78: =(SUMIFS(N:N,O:O,R78))-Z78 -> 0
B79: MERCH | C79: 195 | D79: 3748 | E79: 500 | F79: 990 | G79: 2260 | H79: =SUM(E79:G79) -> 3750 | I79: =(LOOKUP(O79,$R$16:$R$40,$X$16:$X$40)*D79)/LOOKUP(O79,$R$16:$R$40,$T$16:$T$40) -> 2939.2737 | J79: =I79*$T$2 -> 71.266891 | K79: =(H79*$T$2)+(I79*$T$2) -> 162.191 | L79: =(LOOKUP(O79,$R$16:$R$27,$Z$16:$Z$27)*F79)/LOOKUP(O79,$R$16:$R$27,$U$16:$U$27)+K79 -> 169.6633 | M79: 100 | N79: =M79-L79 -> -69.663298 | O79: 21 | P79: 23 | R79: 63 | T79: =SUMIFS(D:D,O:O,R79) -> 0 | U79: =SUMIFS($F:$F,$O:$O,R79) -> 0 | Y79: =SUMIFS(K:K,O:O,R79) -> 0 | Z79: =Y79*22% -> 0 | AA79: =Y79+Z79 -> 0 | AB79: =(SUMIFS(N:N,O:O,R79))-Z79 -> 0
B80: NEW | C80: 183 | D80: 7160 | E80: 800 | F80: 13999 | G80: 0 | H80: =SUM(E80:G80) -> 14799 | I80: =(LOOKUP(O80,$R$16:$R$40,$X$16:$X$40)*D80)/LOOKUP(O80,$R$16:$R$40,$T$16:$T$40) -> 6249.3766 | J80: =I80*$T$2 -> 151.52506 | K80: =(H80*$T$2)+(I80*$T$2) -> 510.34796 | L80: =(LOOKUP(O80,$R$16:$R$27,$Z$16:$Z$27)*F80)/LOOKUP(O80,$R$16:$R$27,$U$16:$U$27)+K80 -> 616.0093 | M80: 1000 | N80: =M80-L80 -> 383.9907 | O80: 22 | P80: 24 | R80: 64 | T80: =SUMIFS(D:D,O:O,R80) -> 0 | U80: =SUMIFS($F:$F,$O:$O,R80) -> 0 | Y80: =SUMIFS(K:K,O:O,R80) -> 0 | Z80: =Y80*22% -> 0 | AA80: =Y80+Z80 -> 0 | AB80: =(SUMIFS(N:N,O:O,R80))-Z80 -> 0
B81: PA MI | C81: 188 | D81: 6046 | E81: 500 | F81: 12000 | G81: 2570 | H81: =SUM(E81:G81) -> 15070 | I81: =(LOOKUP(O81,$R$16:$R$40,$X$16:$X$40)*D81)/LOOKUP(O81,$R$16:$R$40,$T$16:$T$40) -> 5277.0574 | J81: =I81*$T$2 -> 127.94979 | K81: =(H81*$T$2)+(I81*$T$2) -> 493.34347 | L81: =(LOOKUP(O81,$R$16:$R$27,$Z$16:$Z$27)*F81)/LOOKUP(O81,$R$16:$R$27,$U$16:$U$27)+K81 -> 583.91681 | M81: 635 | N81: =M81-L81 -> 51.08319 | O81: 22 | P81: 24 | R81: 65 | T81: =SUMIFS(D:D,O:O,R81) -> 0 | U81: =SUMIFS($F:$F,$O:$O,R81) -> 0 | Y81: =SUMIFS(K:K,O:O,R81) -> 0 | Z81: =Y81*22% -> 0 | AA81: =Y81+Z81 -> 0 | AB81: =(SUMIFS(N:N,O:O,R81))-Z81 -> 0
B82: NEW | C82: 203 | D82: 1230 | E82: 800 | F82: 4000 | G82: 0 | H82: =SUM(E82:G82) -> 4800 | I82: =(LOOKUP(O82,$R$16:$R$40,$X$16:$X$40)*D82)/LOOKUP(O82,$R$16:$R$40,$T$16:$T$40) -> 1073.5661 | J82: =I82*$T$2 -> 26.030143 | K82: =(H82*$T$2)+(I82*$T$2) -> 142.413 | L82: =(LOOKUP(O82,$R$16:$R$27,$Z$16:$Z$27)*F82)/LOOKUP(O82,$R$16:$R$27,$U$16:$U$27)+K82 -> 172.60411 | M82: 300 | N82: =M82-L82 -> 127.39589 | O82: 22 | P82: 24 | R82: 66 | T82: =SUMIFS(D:D,O:O,R82) -> 0 | U82: =SUMIFS($F:$F,$O:$O,R82) -> 0 | Y82: =SUMIFS(K:K,O:O,R82) -> 0 | Z82: =Y82*22% -> 0 | AA82: =Y82+Z82 -> 0 | AB82: =(SUMIFS(N:N,O:O,R82))-Z82 -> 0
B83: NEW | C83: 182 | D83: 1962 | E83: 800 | F83: 10500 | G83: 0 | H83: =SUM(E83:G83) -> 11300 | I83: =(LOOKUP(O83,$R$16:$R$40,$X$16:$X$40)*D83)/LOOKUP(O83,$R$16:$R$40,$T$16:$T$40) -> 1857.9259 | J83: =I83*$T$2 -> 45.048069 | K83: =(H83*$T$2)+(I83*$T$2) -> 319.03271 | L83: =(LOOKUP(O83,$R$16:$R$27,$Z$16:$Z$27)*F83)/LOOKUP(O83,$R$16:$R$27,$U$16:$U$27)+K83 -> 398.28438 | M83: 650 | N83: =M83-L83 -> 251.71562 | O83: 23 | P83: 25 | R83: 67 | T83: =SUMIFS(D:D,O:O,R83) -> 0 | U83: =SUMIFS($F:$F,$O:$O,R83) -> 0 | Y83: =SUMIFS(K:K,O:O,R83) -> 0 | Z83: =Y83*22% -> 0 | AA83: =Y83+Z83 -> 0 | AB83: =(SUMIFS(N:N,O:O,R83))-Z83 -> 0
B84: NEW | C84: 200 | D84: 21720 | E84: 500 | F84: 46599 | G84: 7260 | H84: =SUM(E84:G84) -> 54359 | I84: =(LOOKUP(O84,$R$16:$R$40,$X$16:$X$40)*D84)/LOOKUP(O84,$R$16:$R$40,$T$16:$T$40) -> 20567.865 | J84: =I84*$T$2 -> 498.69727 | K84: =(H84*$T$2)+(I84*$T$2) -> 1816.7089 | L84: =(LOOKUP(O84,$R$16:$R$27,$Z$16:$Z$27)*F84)/LOOKUP(O84,$R$16:$R$27,$U$16:$U$27)+K84 -> 2168.4278 | M84: 2600 | N84: =M84-L84 -> 431.57221 | O84: 23 | P84: 25 | R84: 68 | T84: =SUMIFS(D:D,O:O,R84) -> 0 | U84: =SUMIFS($F:$F,$O:$O,R84) -> 0 | Y84: =SUMIFS(K:K,O:O,R84) -> 0 | Z84: =Y84*22% -> 0 | AA84: =Y84+Z84 -> 0 | AB84: =(SUMIFS(N:N,O:O,R84))-Z84 -> 0
B85: USED | C85: 204 | D85: 1322 | E85: 800 | F85: 4280 | G85: 0 | H85: =SUM(E85:G85) -> 5080 | I85: =(LOOKUP(O85,$R$16:$R$40,$X$16:$X$40)*D85)/LOOKUP(O85,$R$16:$R$40,$T$16:$T$40) -> 1251.8747 | J85: =I85*$T$2 -> 30.35349 | K85: =(H85*$T$2)+(I85*$T$2) -> 153.52535 | L85: =(LOOKUP(O85,$R$16:$R$27,$Z$16:$Z$27)*F85)/LOOKUP(O85,$R$16:$R$27,$U$16:$U$27)+K85 -> 185.82984 | M85: 250 | N85: =M85-L85 -> 64.170163 | O85: 23 | P85: 25 | R85: 69 | T85: =SUMIFS(D:D,O:O,R85) -> 0 | U85: =SUMIFS($F:$F,$O:$O,R85) -> 0 | Y85: =SUMIFS(K:K,O:O,R85) -> 0 | Z85: =Y85*22% -> 0 | AA85: =Y85+Z85 -> 0 | AB85: =(SUMIFS(N:N,O:O,R85))-Z85 -> 0
B86: NEW | C86: 205 | D86: 974 | E86: 800 | F86: 2450 | G86: 0 | H86: =SUM(E86:G86) -> 3250 | I86: =(LOOKUP(O86,$R$16:$R$40,$X$16:$X$40)*D86)/LOOKUP(O86,$R$16:$R$40,$T$16:$T$40) -> 922.33428 | J86: =I86*$T$2 -> 22.363312 | K86: =(H86*$T$2)+(I86*$T$2) -> 101.16421 | L86: =(LOOKUP(O86,$R$16:$R$27,$Z$16:$Z$27)*F86)/LOOKUP(O86,$R$16:$R$27,$U$16:$U$27)+K86 -> 119.65626 | M86: 200 | N86: =M86-L86 -> 80.343739 | O86: 23 | P86: 25 | R86: 70 | T86: =SUMIFS(D:D,O:O,R86) -> 0 | U86: =SUMIFS($F:$F,$O:$O,R86) -> 0 | Y86: =SUMIFS(K:K,O:O,R86) -> 0 | Z86: =Y86*22% -> 0 | AA86: =Y86+Z86 -> 0 | AB86: =(SUMIFS(N:N,O:O,R86))-Z86 -> 0
... B97: JUNK | C97: 248 | D97: 620 | E97: 500 | F97: 1300 | G97: 750 | H97: =SUM(E97:G97) -> 2550 | I97: =(LOOKUP(O97,$R$16:$R$40,$X$16:$X$40)*D97)/LOOKUP(O97,$R$16:$R$40,$T$16:$T$40) -> 560.42852 | J97: =I97*$T$2 -> 13.58839 | K97: =(H97*$T$2)+(I97*$T$2) -> 75.416783 | L97: =(LOOKUP(O97,$R$16:$R$27,$Z$16:$Z$27)*F97)/LOOKUP(O97,$R$16:$R$27,$U$16:$U$27)+K97 -> 85.228895 | M97: 200 | N97: =M97-L97 -> 114.77111 | O97: 26 | P97: 29 | R97: 81 | T97: =SUMIFS(D:D,O:O,R97) -> 0 | U97: =SUMIFS($F:$F,$O:$O,R97) -> 0 | Y97: =SUMIFS(K:K,O:O,R97) -> 0 | Z97: =Y97*22% -> 0 | AA97: =Y97+Z97 -> 0 | AB97: =(SUMIFS(N:N,O:O,R97))-Z97 -> 0
B98: JUNK | C98: 254 | D98: 1018 | E98: 500 | F98: 3135 | G98: 0 | H98: =SUM(E98:G98) -> 3635 | I98: =(LOOKUP(O98,$R$16:$R$40,$X$16:$X$40)*D98)/LOOKUP(O98,$R$16:$R$40,$T$16:$T$40) -> 920.18748 | J98: =I98*$T$2 -> 22.31126 | K98: =(H98*$T$2)+(I98*$T$2) -> 110.44703 | L98: =(LOOKUP(O98,$R$16:$R$27,$Z$16:$Z$27)*F98)/LOOKUP(O98,$R$16:$R$27,$U$16:$U$27)+K98 -> 134.10931 | M98: 250 | N98: =M98-L98 -> 115.89069 | O98: 26 | P98: 29
B99: NEW | C99: 273 | D99: 508 | E99: 500 | F99: 1100 | G99: 770 | H99: =SUM(E99:G99) -> 2370 | I99: =(LOOKUP(O99,$R$16:$R$40,$X$16:$X$40)*D99)/LOOKUP(O99,$R$16:$R$40,$T$16:$T$40) -> 459.18982 | J99: =I99*$T$2 -> 11.133713 | K99: =(H99*$T$2)+(I99*$T$2) -> 68.597749 | L99: =(LOOKUP(O99,$R$16:$R$27,$Z$16:$Z$27)*F99)/LOOKUP(O99,$R$16:$R$27,$U$16:$U$27)+K99 -> 76.900305 | M99: 100 | N99: =M99-L99 -> 23.099695 | O99: 26 | P99: 29
B100: MERCH | C100: 277 | D100: 520 | E100: 800 | F100: 777 | G100: 0 | H100: =SUM(E100:G100) -> 1577 | I100: =(LOOKUP(O100,$R$16:$R$40,$X$16:$X$40)*D100)/LOOKUP(O100,$R$16:$R$40,$T$16:$T$40) -> 470.03683 | J100: =I100*$T$2 -> 11.396714 | K100: =(H100*$T$2)+(I100*$T$2) -> 49.633332 | L100: =(LOOKUP(O100,$R$16:$R$27,$Z$16:$Z$27)*F100)/LOOKUP(O100,$R$16:$R$27,$U$16:$U$27)+K100 -> 55.497956 | M100: 120 | N100: =M100-L100 -> 64.502044 | O100: 26 | P100: 29
B101: NEW | C101: 278 | D101: 1010 | E101: 800 | F101: 2000 | G101: 0 | H101: =SUM(E101:G101) -> 2800 | I101: =(LOOKUP(O101,$R$16:$R$40,$X$16:$X$40)*D101)/LOOKUP(O101,$R$16:$R$40,$T$16:$T$40) -> 912.95614 | J101: =I101*$T$2 -> 22.135926 | K101: =(H101*$T$2)+(I101*$T$2) -> 90.025926 | L101: =(LOOKUP(O101,$R$16:$R$27,$Z$16:$Z$27)*F101)/LOOKUP(O101,$R$16:$R$27,$U$16:$U$27)+K101 -> 105.12148 | M101: 200 | N101: =M101-L101 -> 94.878518 | O101: 27 | P101: 30
B102: CARTAS | C102: 280 | D102: 5318 | E102: 500 | F102: 1280 | G102: 750 | H102: =SUM(E102:G102) -> 2530 | I102: =(LOOKUP(O102,$R$16:$R$40,$X$16:$X$40)*D102)/LOOKUP(O102,$R$16:$R$40,$T$16:$T$40) -> 4807.0305 | J102: =I102*$T$2 -> 116.55332 | K102: =(H102*$T$2)+(I102*$T$2) -> 177.89679 | L102: =(LOOKUP(O102,$R$16:$R$27,$Z$16:$Z$27)*F102)/LOOKUP(O102,$R$16:$R$27,$U$16:$U$27)+K102 -> 187.55794 | M102: 200 | N102: =M102-L102 -> 12.442059 | O102: 27 | P102: 30
B103: UKU | C103: 281 | D103: 3282 | E103: 800 | F103: 35000 | G103: 0 | H103: =SUM(E103:G103) -> 35800 | I103: =(LOOKUP(O103,$R$16:$R$40,$X$16:$X$40)*D103)/LOOKUP(O103,$R$16:$R$40,$T$16:$T$40) -> 2966.6555 | J103: =I103*$T$2 -> 71.930801 | K103: =(H103*$T$2)+(I103*$T$2) -> 939.95294 | L103: =(LOOKUP(O103,$R$16:$R$27,$Z$16:$Z$27)*F103)/LOOKUP(O103,$R$16:$R$27,$U$16:$U$27)+K103 -> 1204.1252 | M103: 1080 | N103: =M103-L103 -> -124.12518 | O103: 27 | P103: 30
B104: UKU | C104: 283 | D104: 192 | E104: 800 | F104: 3000 | G104: 0 | H104: =SUM(E104:G104) -> 3800 | I104: =(LOOKUP(O104,$R$16:$R$40,$X$16:$X$40)*D104)/LOOKUP(O104,$R$16:$R$40,$T$16:$T$40) -> 173.55206 | J104: =I104*$T$2 -> 4.2080176 | K104: =(H104*$T$2)+(I104*$T$2) -> 96.344446 | L104: =(LOOKUP(O104,$R$16:$R$27,$Z$16:$Z$27)*F104)/LOOKUP(O104,$R$16:$R$27,$U$16:$U$27)+K104 -> 118.98778 | M104: 120 | N104: =M104-L104 -> 1.0122195 | O104: 27 | P104: 30
B105: NEW | C105: 250 | D105: 2410 | E105: 800 | F105: 6299 | G105: 0 | H105: =SUM(E105:G105) -> 7099 | I105: =(LOOKUP(O105,$R$16:$R$40,$X$16:$X$40)*D105)/LOOKUP(O105,$R$16:$R$40,$T$16:$T$40) -> 2178.4399 | J105: =I105*$T$2 -> 52.819388 | K105: =(H105*$T$2)+(I105*$T$2) -> 224.94478 | L105: =(LOOKUP(O105,$R$16:$R$27,$Z$16:$Z$27)*F105)/LOOKUP(O105,$R$16:$R$27,$U$16:$U$27)+K105 -> 272.48824 | M105: 350 | N105: =M105-L105 -> 77.511762 | O105: 28 | P105: 31
B106: USED | C106: 251 | D106: 4690 | E106: 800 | F106: 7999 | G106: 0 | H106: =SUM(E106:G106) -> 8799 | I106: =(LOOKUP(O106,$R$16:$R$40,$X$16:$X$40)*D106)/LOOKUP(O106,$R$16:$R$40,$T$16:$T$40) -> 4239.3706 | J106: =I106*$T$2 -> 102.7896 | K106: =(H106*$T$2)+(I106*$T$2) -> 316.13392 | L106: =(LOOKUP(O106,$R$16:$R$27,$Z$16:$Z$27)*F106)/LOOKUP(O106,$R$16:$R$27,$U$16:$U$27)+K106 -> 376.5086 | M106: 700 | N106: =M106-L106 -> 323.4914 | O106: 28 | P106: 31
B107: NEW | C107: 284 | D107: 5344 | E107: 800 | F107: 13999 | G107: 0 | H107: =SUM(E107:G107) -> 14799 | I107: =(LOOKUP(O107,$R$16:$R$40,$X$16:$X$40)*D107)/LOOKUP(O107,$R$16:$R$40,$T$16:$T$40) -> 4830.5323 | J107: =I107*$T$2 -> 117.12316 | K107: =(H107*$T$2)+(I107*$T$2) -> 475.94605 | L107: =(LOOKUP(O107,$R$16:$R$27,$Z$16:$Z$27)*F107)/LOOKUP(O107,$R$16:$R$27,$U$16:$U$27)+K107 -> 581.6074 | M107: 850 | N107: =M107-L107 -> 268.3926 | O107: 28 | P107: 31
B108: NEW | C108: 289 | D108: 10300 | E108: 500 | F108: 18800 | G108: 3300 | H108: =SUM(E108:G108) -> 22600 | I108: =(LOOKUP(O108,$R$16:$R$40,$X$16:$X$40)*D108)/LOOKUP(O108,$R$16:$R$40,$T$16:$T$40) -> 9310.3448 | J108: =I108*$T$2 -> 225.74261 | K108: =(H108*$T$2)+(I108*$T$2) -> 773.7119 | L108: =(LOOKUP(O108,$R$16:$R$27,$Z$16:$Z$27)*F108)/LOOKUP(O108,$R$16:$R$27,$U$16:$U$27)+K108 -> 915.61012 | M108: 1500 | N108: =M108-L108 -> 584.38988 | O108: =P108-1 -> 31 | P108: 32
B109: 005JAROLD | C109: 342 | D109: 316 | E109: 800 | F109: 2300 | G109: 0 | H109: =SUM(E109:G109) -> 3100 | I109: =(LOOKUP(O109,$R$16:$R$40,$X$16:$X$40)*D109)/LOOKUP(O109,$R$16:$R$40,$T$16:$T$40) -> 285.63776 | J109: =I109*$T$2 -> 6.9256956 | K109: =(H109*$T$2)+(I109*$T$2) -> 82.089624 | L109: =(LOOKUP(O109,$R$16:$R$27,$Z$16:$Z$27)*F109)/LOOKUP(O109,$R$16:$R$27,$U$16:$U$27)+K109 -> 99.449514 | M109: 140 | N109: =M109-L109 -> 40.550486 | O109: =P109-1 -> 31 | P109: 32
B110: NEW | C110: 291 | D110: 2940 | E110: 500 | F110: 5995 | G110: 910 | H110: =SUM(E110:G110) -> 7405 | I110: =(LOOKUP(O110,$R$16:$R$40,$X$16:$X$40)*D110)/LOOKUP(O110,$R$16:$R$40,$T$16:$T$40) -> 2657.5159 | J110: =I110*$T$2 -> 64.43527 | K110: =(H110*$T$2)+(I110*$T$2) -> 243.98007 | L110: =(LOOKUP(O110,$R$16:$R$27,$Z$16:$Z$27)*F110)/LOOKUP(O110,$R$16:$R$27,$U$16:$U$27)+K110 -> 289.229 | M110: 500 | N110: =M110-L110 -> 210.771 | O110: =P110-1 -> 32 | P110: 33
B111: NEW | C111: 297 | D111: 7650 | E111: 500 | F111: 16324 | G111: 1500 | H111: =SUM(E111:G111) -> 18324 | I111: =(LOOKUP(O111,$R$16:$R$40,$X$16:$X$40)*D111)/LOOKUP(O111,$R$16:$R$40,$T$16:$T$40) -> 6914.9648 | J111: =I111*$T$2 -> 167.6632 | K111: =(H111*$T$2)+(I111*$T$2) -> 611.95476 | L111: =(LOOKUP(O111,$R$16:$R$27,$Z$16:$Z$27)*F111)/LOOKUP(O111,$R$16:$R$27,$U$16:$U$27)+K111 -> 735.16469 | M111: 1050 | N111: =M111-L111 -> 314.83531 | O111: =P111-1 -> 32 | P111: 33
B112: NEW | C112: 301 | D112: 4864 | E112: 500 | F112: 7000 | G112: 1200 | H112: =SUM(E112:G112) -> 8700 | I112: =(LOOKUP(O112,$R$16:$R$40,$X$16:$X$40)*D112)/LOOKUP(O112,$R$16:$R$40,$T$16:$T$40) -> 4396.6522 | J112: =I112*$T$2 -> 106.60311 | K112: =(H112*$T$2)+(I112*$T$2) -> 317.54704 | L112: =(LOOKUP(O112,$R$16:$R$27,$Z$16:$Z$27)*F112)/LOOKUP(O112,$R$16:$R$27,$U$16:$U$27)+K112 -> 370.38149 | M112: 500 | N112: =M112-L112 -> 129.61851 | O112: =P112-1 -> 32 | P112: 33
B113: NEW | C113: 326 | D113: 758 | E113: 500 | F113: 27500 | G113: 1840 | H113: =SUM(E113:G113) -> 29840 | I113: =(LOOKUP(O113,$R$16:$R$40,$X$16:$X$40)*D113)/LOOKUP(O113,$R$16:$R$40,$T$16:$T$40) -> 685.16907 | J113: =I113*$T$2 -> 16.612903 | K113: =(H113*$T$2)+(I113*$T$2) -> 740.12633 | L113: =(LOOKUP(O113,$R$16:$R$27,$Z$16:$Z$27)*F113)/LOOKUP(O113,$R$16:$R$27,$U$16:$U$27)+K113 -> 947.69023 | M113: 1100 | N113: =M113-L113 -> 152.30977 | O113: =P113-1 -> 33 | P113: 34
B114: NEW | C114: 333 | D114: 536 | E114: 800 | F114: 1800 | G114: 0 | H114: =SUM(E114:G114) -> 2600 | I114: =(LOOKUP(O114,$R$16:$R$40,$X$16:$X$40)*D114)/LOOKUP(O114,$R$16:$R$40,$T$16:$T$40) -> 484.4995 | J114: =I114*$T$2 -> 11.747382 | K114: =(H114*$T$2)+(I114*$T$2) -> 74.788097 | L114: =(LOOKUP(O114,$R$16:$R$27,$Z$16:$Z$27)*F114)/LOOKUP(O114,$R$16:$R$27,$U$16:$U$27)+K114 -> 88.374097 | M114: 150 | N114: =M114-L114 -> 61.625903 | O114: =P114-1 -> 33 | P114: 34
...

Sheet Hoja 5
F3: <
E4: 2 o mas figuras | F4: 100 | G4: 5 | H4: =F4-(G4*F4) % -> 95
F5: 200 | G5: 7.5 | H5: =F5-(G5*F5) % -> 185
F6: 700 | G6: 10 | H6: =F6-(G6*F6) % -> 630

Sheet CUENTAS 2025
B1: CUENTAS | D1: SUBTOTAL | E1: 3223.99 | N1: Hola buenas hermano(a/e) tienes una cuentita pendiente:
A2: FECHA | B2: CLIENTE | C2: FIGURA | D2: MES | E2: LOTE | F2: PRECIO | G2: ADELANTO | H2: RESTANTE | I2: ENTREGADO | J2: TIPO DE ENTR | K2: FECHA LIMITE | L2: ALMACEN | O2: PAGADO | P2: =SUM(G:G) -> 24977.3 | Q2: =SUM(H2:H950) -> 5407.99
A3: 45988 | B3: DAN | C3: RIFA MERCH TOALLA CHOPPER | D3: STOCK | E3: 0 | F3: 5 | G3: 5 | H3: =F3-G3 -> 0 | I3: TRUE | J3: PENDIENTE | K3: =A3+15 -> 46003 | L3: =A3+30 -> 46018
A4: 46017 | B4: ALPHONSE | C4: CHIBI PELIAZUL | D4: MARZO | E4: 232 | F4: 20 | G4: 20 | H4: =F4-G4 -> 0 | I4: FALSE | J4: PREVENTA | K4: =A4+15 -> 46032 | L4: =A4+30 -> 46047
A5: 46017 | B5: ALPHONSE | C5: GLITTER EN TANGA | D5: ABRIL | E5: 999 | F5: 65 | G5: 65 | H5: =F5-G5 -> 0 | I5: FALSE | J5: PREVENTA | K5: =A5+15 -> 46032 | L5: =A5+30 -> 46047
A6: 45987 | B6: BUBUN | C6: 2 LLAVEROS | D6: STOCK | E6: 0 | F6: 6 | G6: 6 | H6: =F6-G6 -> 0 | I6: TRUE | J6: PENDIENTE | K6: =A6+15 -> 46002 | L6: =A6+30 -> 46017
A7: 46017 | B7: ALPHONSE | C7: GLITTER TO LOVE RU | D7: STOCK | E7: 0 | F7: 65 | G7: 65 | H7: =F7-G7 -> 0 | I7: FALSE | J7: PENDIENTE | K7: =A7+15 -> 46032 | L7: =A7+30 -> 46047
A8: 45980 | B8: JOSE ANDRE | C8: 2.5 DIMEN X2 | D8: STOCK | E8: 0 | F8: 110 | G8: 110 | H8: =F8-G8 -> 0 | I8: TRUE | J8: TREINTA | K8: =A8+15 -> 45995 | L8: =A8+30 -> 46010
A9: 45997 | B9: ARANCIEA | C9: 2.5 MIRIEL CORAZON | D9: STOCK | E9: 0 | F9: 55 | G9: 55 | H9: =F9-G9 -> 0 | I9: TRUE | J9: PENDIENTE | K9: =A9+15 -> 46012 | L9: =A9+30 -> 46027
A10: 46017 | B10: ALPHONSE | C10: UNIFORM PERU | D10: FEBRERO | E10: 174 | F10: 50 | G10: 50 | H10: =F10-G10 -> 0 | I10: FALSE | J10: PENDIENTE | K10: =A10+15 -> 46032 | L10: =A10+30 -> 46047
A11: 45954 | B11: RENZO | C11: 3 ALMIRANTES | D11: ENERO | E11: 0 | F11: 165 | G11: 165 | H11: =F11-G11 -> 0 | I11: TRUE | J11: PENDIENTE | K11: =A11+15 -> 45969 | L11: =A11+30 -> 45984
A12: 46001 | B12: BUBUN | C12: 3 PINES + MINIFILE | D12: STOCK | E12: 0 | F12: 13 | G12: 13 | H12: =F12-G12 -> 0 | I12: TRUE | J12: PENDIENTE | K12: =A12+15 -> 46016 | L12: =A12+30 -> 46031
A13: 45933 | B13: UKU | C13: 3 SELLADOS+CUADRO | D13: STOCK | F13: 185 | G13: 185 | H13: =F13-G13 -> 0 | I13: TRUE | J13: PENDIENTE | K13: =A13+15 -> 45948 | L13: =A13+30 -> 45963
A14: 45915 | B14: HUGO | C14: 3 SIN BASE | D14: STOCK | E14: 0 | F14: 60 | G14: 60 | H14: =F14-G14 -> 0 | I14: TRUE | J14: PENDIENTE | K14: =A14+15 -> 45930 | L14: =A14+30 -> 45945
A15: 46021 | B15: ALPHONSE | C15: BOLSA POKEMON | D15: STOCK | E15: 0 | F15: 10 | G15: 10 | H15: =F15-G15 -> 0 | I15: FALSE | J15: PENDIENTE | K15: =A15+15 -> 46036 | L15: =A15+30 -> 46051
A16: 46010 | B16: ARGONAUTA | C16: 4 CHIBIS MONOGATARI | D16: STOCK | E16: 0 | F16: 143.5 | G16: 143.5 | H16: =F16-G16 -> 0 | I16: TRUE | J16: PENDIENTE | K16: =A16+15 -> 46025 | L16: =A16+30 -> 46040
A17: 46021 | B17: ALPHONSE | C17: POSTER SAO | D17: STOCK | E17: 0 | F17: 15 | G17: 15 | H17: =F17-G17 -> 0 | I17: FALSE | J17: PENDIENTE | K17: =A17+15 -> 46036 | L17: =A17+30 -> 46051
A18: 45993 | B18: ARANCIEA | C18: 7 LLAVEROS | D18: STOCK | E18: 0 | F18: 21 | G18: 21 | H18: =F18-G18 -> 0 | I18: TRUE | J18: PENDIENTE | K18: =A18+15 -> 46008 | L18: =A18+30 -> 46023
A19: 45971 | B19: CHRISTIAN CONTRERAS | C19: ACE ENDEAVOR GOYO CAJA | D19: STOCK | E19: 0 | F19: 175 | G19: 175 | H19: =F19-G19 -> 0 | I19: TRUE | J19: PENDIENTE | K19: =A19+15 -> 45986 | L19: =A19+30 -> 46001
A20: 45980 | B20: DAN | C20: ACE GRANDE | D20: STOCK | E20: 0 | F20: 50 | G20: 50 | H20: =F20-G20 -> 0 | I20: TRUE | J20: PENDIENTE | K20: =A20+15 -> 45995 | L20: =A20+30 -> 46010
A21: 45981 | B21: VD | C21: ACE SIN BASE | D21: STOCK | E21: 0 | F21: 20 | G21: 20 | H21: =F21-G21 -> 0 | I21: TRUE | J21: PENDIENTE | K21: =A21+15 -> 45996 | L21: =A21+30 -> 46011
A22: 45945 | B22: ANTHONY | C22: PELUCHE TORCHIK | D22: FEBRERO | E22: 186 | F22: 30 | G22: 15 | H22: =F22-G22 -> 15 | I22: FALSE | J22: PENDIENTE | K22: =A22+15 -> 45960 | L22: =A22+30 -> 45975
A23: 45953 | B23: ANTHONY | C23: PELUCHE TOTODILE | D23: FEBRERO | E23: 186 | F23: 45 | G23: 15 | H23: =F23-G23 -> 30 | I23: FALSE | J23: PENDIENTE | K23: =A23+15 -> 45968 | L23: =A23+30 -> 45983
A24: 45997 | B24: ARANCIEA | C24: PELUCHE MORENO | D24: ABRIL | E24: 326 | F24: 90 | G24: 25 | H24: =F24-G24 -> 65 | I24: FALSE | J24: PREVENTA | K24: =A24+15 -> 46012 | L24: =A24+30 -> 46027
A25: 45959 | B25: CLEO | C25: AIN | D25: STOCK | E25: 0 | F25: 39 | G25: 39 | H25: =F25-G25 -> 0 | I25: TRUE | J25: PENDIENTE | K25: =A25+15 -> 45974 | L25: =A25+30 -> 45989
... A33: 45971 | B33: JORGEPEDRO | C33: ANYA CHIQUI | D33: STOCK | E33: 0 | F33: 23 | G33: 23 | H33: =F33-G33 -> 0 | I33: TRUE | J33: PENDIENTE | K33: =A33+15 -> 45986 | L33: =A33+30 -> 46001
A34: 45924 | B34: MARSHALL | C34: ANYA QPOSKET | D34: STOCK | F34: 21 | G34: 21 | H34: =F34-G34 -> 0 | I34: TRUE | J34: PENDIENTE | K34: =A34+15 -> 45939 | L34: =A34+30 -> 45954
A35: 46021 | B35: ARMILENK | C35: CABALLA PLOMA | D35: ABRIL | E35: 301 | F35: 85 | G35: 85 | H35: =F35-G35 -> 0 | I35: FALSE | J35: PENDIENTE | K35: =A35+15 -> 46036 | L35: =A35+30 -> 46051
A36: 45939 | B36: BASTOFORD | C36: NESUKO GLITTER | D36: STOCK | E36: 0 | F36: 48 | G36: 48 | H36: =F36-G36 -> 0 | I36: FALSE | J36: PENDIENTE | K36: =A36+15 -> 45954 | L36: =A36+30 -> 45969
A37: 45930 | B37: TROUBLE | C37: AZUNA | D37: STOCK | F37: 40 | G37: 40 | H37: =F37-G37 -> 0 | I37: TRUE | J37: PENDIENTE | K37: =A37+15 -> 45945 | L37: =A37+30 -> 45960
A38: 45966 | B38: KIWI | C38: BAKUGO | D38: STOCK | E38: 0 | F38: 45 | G38: 45 | H38: =F38-G38 -> 0 | I38: TRUE | J38: PENDIENTE | K38: =A38+15 -> 45981 | L38: =A38+30 -> 45996
A39: 46014 | B39: DAASH | C39: DEKU SENTADO | D39: MARZO | E39: 223 | F39: 50 | G39: 25 | H39: =F39-G39 -> 25 | I39: FALSE | J39: PREVENTA | K39: =A39+15 -> 46029 | L39: =A39+30 -> 46044
A40: 45965 | B40: DAN | C40: TETONA MAID | D40: MARZO | E40: 240 | F40: 90 | G40: 90 | H40: =F40-G40 -> 0 | I40: FALSE | J40: PREVENTA | K40: =A40+15 -> 45980 | L40: =A40+30 -> 45995
A41: 46021 | B41: DAVID | C41: FILE URARAKA | D41: STOCK | E41: 0 | F41: 5 | G41: 5 | H41: =F41-G41 -> 0 | I41: FALSE | J41: PENDIENTE | K41: =A41+15 -> 46036 | L41: =A41+30 -> 46051
A42: 46021 | B42: DEMONSLAYERPE | C42: GENYA POSTER | D42: STOCK | E42: 0 | F42: 5 | G42: 5 | H42: =F42-G42 -> 0 | I42: FALSE | J42: PENDIENTE | K42: =A42+15 -> 46036 | L42: =A42+30 -> 46051
A43: 45945 | B43: KIWI | C43: BARBABLANCA GRAND | D43: ENERO | E43: 0 | F43: 75 | G43: 75 | H43: =F43-G43 -> 0 | I43: TRUE | J43: PENDIENTE | K43: =A43+15 -> 45960 | L43: =A43+30 -> 45975
A44: 46001 | B44: LUIS DIAZ | C44: BARBABLANCA GRANDISTA | D44: STOCK | E44: 0 | F44: 40 | G44: 40 | H44: =F44-G44 -> 0 | I44: TRUE | J44: PENDIENTE | K44: =A44+15 -> 46016 | L44: =A44+30 -> 46031
A45: 45985 | B45: DIXON | C45: BARBABLANCA MANHOOD | D45: STOCK | E45: 0 | F45: 45 | G45: 45 | H45: =F45-G45 -> 0 | I45: TRUE | J45: PENDIENTE | K45: =A45+15 -> 46000 | L45: =A45+30 -> 46015
A46: 46009 | B46: KAEL | C46: BARDOK | D46: STOCK | E46: 0 | F46: 52 | G46: 52 | H46: =F46-G46 -> 0 | I46: TRUE | J46: PENDIENTE | K46: =A46+15 -> 46024 | L46: =A46+30 -> 46039
A47: 45915 | B47: SHOHAI | C47: BATTLE REC LUFFY | D47: STOCK | E47: 0 | F47: 55 | G47: 55 | H47: =F47-G47 -> 0 | I47: TRUE | J47: PENDIENTE | K47: =A47+15 -> 45930 | L47: =A47+30 -> 45945
A48: 45960 | B48: OZPINARC | C48: BEBAS | D48: DICIEMBRE | E48: 28 | F48: 110 | G48: 110 | H48: =F48-G48 -> 0 | I48: TRUE | J48: PENDIENTE | K48: =A48+15 -> 45975 | L48: =A48+30 -> 45990
A49: 46003 | B49: HERNANDEZ | C49: BENIMARU | D49: STOCK | E49: 0 | F49: 65 | G49: 65 | H49: =F49-G49 -> 0 | I49: TRUE | J49: PENDIENTE | K49: =A49+15 -> 46018 | L49: =A49+30 -> 46033
... A60: 45987 | B60: BUBUN | C60: BOTICARIA PIN | D60: STOCK | E60: 0 | F60: 5 | G60: 5 | H60: =F60-G60 -> 0 | I60: TRUE | J60: PENDIENTE | K60: =A60+15 -> 46002 | L60: =A60+30 -> 46017
A61: 45929 | B61: LUIS | C61: BOTICARIA+MIKU | D61: ENERO | E61: 132-154 | F61: 135 | G61: 135 | H61: =F61-G61 -> 0 | I61: TRUE | J61: PENDIENTE | K61: =A61+15 -> 45944 | L61: =A61+30 -> 45959
A62: 45981 | B62: HUGO | C62: BROLY SIN BASE | D62: STOCK | E62: 0 | F62: 25 | G62: 25 | H62: =F62-G62 -> 0 | I62: TRUE | J62: PENDIENTE | K62: =A62+15 -> 45996 | L62: =A62+30 -> 46011
A63: 45915 | B63: ALVARO LUCK | C63: BROOK | D63: STOCK | E63: 0 | F63: 50 | G63: 50 | H63: =F63-G63 -> 0 | I63: TRUE | J63: PENDIENTE | K63: =A63+15 -> 45930 | L63: =A63+30 -> 45945
A64: 46021 | B64: DEMONSLAYERPE | C64: TOKITO POSTER | D64: STOCK | E64: 0 | F64: 7 | G64: 7 | H64: =F64-G64 -> 0 | I64: FALSE | J64: PENDIENTE | K64: =A64+15 -> 46036 | L64: =A64+30 -> 46051
A65: 45972 | B65: JORGEPEDRO | C65: BUNNY SAO+ GATA | D65: STOCK | E65: 0 | F65: 100 | G65: 100 | H65: =F65-G65 -> 0 | I65: TRUE | J65: PENDIENTE | K65: =A65+15 -> 45987 | L65: =A65+30 -> 46002
A66: 46021 | B66: DEMONSLAYERPE | C66: TOMIOKA POSTER | D66: STOCK | E66: 0 | F66: 6 | G66: 6 | H66: =F66-G66 -> 0 | I66: FALSE | J66: PENDIENTE | K66: =A66+15 -> 46036 | L66: =A66+30 -> 46051
A67: 46021 | B67: DEMONSLAYERPE | C67: ZENITSU POSTER | D67: STOCK | E67: 0 | F67: 5 | G67: 5 | H67: =F67-G67 -> 0 | I67: FALSE | J67: PENDIENTE | K67: =A67+15 -> 46036 | L67: =A67+30 -> 46051
A68: 45954 | B68: DEYNA | C68: LEVI | D68: FEBRERO | E68: 0 | F68: 40 | G68: 40 | H68: =F68-G68 -> 0 | I68: FALSE | J68: PENDIENTE | K68: =A68+15 -> 45969 | L68: =A68+30 -> 45984
A69: 45978 | B69: DINAMICA NATH | C69: AI OSHI NO KO | D69: STOCK | E69: 0 | F69: 60 | G69: 60 | H69: =F69-G69 -> 0 | I69: FALSE | J69: PENDIENTE | K69: =A69+15 -> 45993 | L69: =A69+30 -> 46008
A70: 45978 | B70: DINAMICA NATH | C70: DEKU ICHI | D70: STOCK | E70: 0 | F70: 70 | G70: 70 | H70: =F70-G70 -> 0 | I70: FALSE | J70: PENDIENTE | K70: =A70+15 -> 45993 | L70: =A70+30 -> 46008
A71: 45978 | B71: DINAMICA NATH | C71: IDOL OSHI NO KO | D71: STOCK | E71: 0 | F71: 30 | G71: 30 | H71: =F71-G71 -> 0 | I71: FALSE | J71: PENDIENTE | K71: =A71+15 -> 45993 | L71: =A71+30 -> 46008
A72: 45902 | B72: KHALED | C72: CABALLAS | D72: DICIEMBRE | E72: 0 | F72: 660 | G72: 660 | H72: =F72-G72 -> 0 | I72: TRUE | J72: PENDIENTE | K72: =A72+15 -> 45917 | L72: =A72+30 -> 45932
A73: 45988 | B73: OSCAR RAMIREZ | C73: CASCO VERDE CHIBI | D73: STOCK | E73: 0 | F73: 25 | G73: 25 | H73: =F73-G73 -> 0 | I73: TRUE | J73: PENDIENTE | K73: =A73+15 -> 46003 | L73: =A73+30 -> 46018
... A115: 45917 | B115: RENZO | C115: DUO WANO | D115: STOCK | E115: 0 | F115: 60 | G115: 60 | H115: =F115-G115 -> 0 | I115: TRUE | J115: PENDIENTE | K115: =A115+15 -> 45932 | L115: =A115+30 -> 45947
A116: 45931 | B116: UKU | C116: ENANAS | D116: STOCK | F116: 5 | G116: 5 | H116: =F116-G116 -> 0 | I116: TRUE | J116: PENDIENTE | K116: =A116+15 -> 45946 | L116: =A116+30 -> 45961
A117: 45994 | B117: JAROLD005 | C117: GATITA RUBIA | D117: STOCK | E117: 0 | F117: 35 | G117: 35 | H117: =F117-G117 -> 0 | I117: FALSE | J117: PENDIENTE | K117: =A117+15 -> 46009 | L117: =A117+30 -> 46024
A118: 45985 | B118: DIXON | C118: ENEL | D118: STOCK | E118: 0 | F118: 30 | G118: 30 | H118: =F118-G118 -> 0 | I118: TRUE | J118: PENDIENTE | K118: =A118+15 -> 46000 | L118: =A118+30 -> 46015
A119: 45994 | B119: JAROLD005 | C119: ICHIKA VESTIDO FIESTA | D119: STOCK | E119: 0 | F119: 50 | G119: 50 | H119: =F119-G119 -> 0 | I119: FALSE | J119: PENDIENTE | K119: =A119+15 -> 46009 | L119: =A119+30 -> 46024
A120: 45973 | B120: LENY | C120: EQUIDNA+TOGA | D120: STOCK | E120: 0 | F120: 100 | G120: 100 | H120: =F120-G120 -> 0 | I120: TRUE | J120: PENDIENTE | K120: =A120+15 -> 45988 | L120: =A120+30 -> 46003
A121: 45997 | B121: JAROLD005 | C121: REZE POP UP | D121: ABRIL | E121: 287 | F121: 320 | G121: 200 | H121: =F121-G121 -> 120 | I121: FALSE | J121: PREVENTA | K121: =A121+15 -> 46012 | L121: =A121+30 -> 46027
A122: 45997 | B122: JAROLD005 | C122: TRIO TRY PEDIDO | D122: ABRIL | E122: 342 | F122: 140 | G122: 100 | H122: =F122-G122 -> 40 | I122: FALSE | J122: PREVENTA | K122: =A122+15 -> 46012 | L122: =A122+30 -> 46027
A123: 46003 | B123: JAROLD005 | C123: ICHIKA VESTIDO NOVIA | D123: STOCK | E123: 0 | F123: 75 | G123: 75 | H123: =F123-G123 -> 0 | I123: FALSE | J123: PENDIENTE | K123: =A123+15 -> 46018 | L123: =A123+30 -> 46033
A124: 46014 | B124: WONEJO | C124: FATE ROJA | D124: STOCK | E124: 0 | F124: 75 | G124: 75 | H124: =F124-G124 -> 0 | I124: TRUE | J124: PENDIENTE | K124: =A124+15 -> 46029 | L124: =A124+30 -> 46044
A125: 46003 | B125: JAROLD005 | C125: NINO VESTIDO NOVIA | D125: STOCK | E125: 0 | F125: 75 | G125: 75 | H125: =F125-G125 -> 0 | I125: FALSE | J125: PENDIENTE | K125: =A125+15 -> 46018 | L125: =A125+30 -> 46033
A126: 45914 | B126: JEAN | C126: DUO NAMI-BOA | D126: STOCK | E126: 0 | F126: 90 | G126: 90 | H126: =F126-G126 -> 0 | I126: FALSE | J126: PENDIENTE | K126: =A126+15 -> 45929 | L126: =A126+30 -> 45944
A127: 45914 | B127: JEAN | C127: MINI QUINTI | D127: DICIEMBRE | E127: 0 | F127: 130 | G127: 130 | H127: =F127-G127 -> 0 | I127: FALSE | J127: PENDIENTE | K127: =A127+15 -> 45929 | L127: =A127+30 -> 45944
A128: 45915 | B128: JEAN | C128: NAMI | D128: STOCK | E128: 0 | F128: 21 | G128: 21 | H128: =F128-G128 -> 0 | I128: FALSE | J128: PENDIENTE | K128: =A128+15 -> 45930 | L128: =A128+30 -> 45945
... A138: 45954 | B138: RENZO | C138: G4 KOA | D138: ENERO | E138: 0 | F138: 50 | G138: 50 | H138: =F138-G138 -> 0 | I138: TRUE | J138: PENDIENTE | K138: =A138+15 -> 45969 | L138: =A138+30 -> 45984
A139: 45925 | B139: GUS | C139: G5 MEGAHOUSE | D139: STOCK | F139: 45 | G139: 45 | H139: =F139-G139 -> 0 | I139: TRUE | J139: PENDIENTE | K139: =A139+15 -> 45940 | L139: =A139+30 -> 45955
A140: 45897 | B140: RODOLFO | C140: GABIMARU | D140: STOCK | E140: 0 | F140: 42 | G140: 42 | H140: =F140-G140 -> 0 | I140: TRUE | J140: PENDIENTE | K140: =A140+15 -> 45912 | L140: =A140+30 -> 45927
A141: 45936 | B141: JEAN | C141: SANJI + PUDDING GLITTER | D141: FEBRERO | E141: 172 | F141: 260 | G141: 260 | H141: =F141-G141 -> 0 | I141: FALSE | J141: PENDIENTE | K141: =A141+15 -> 45951 | L141: =A141+30 -> 45966
A142: 45977 | B142: OSCAR RAMIREZ | C142: GACHA LUFFY G5 | D142: STOCK | E142: 0 | F142: 25 | G142: 25 | H142: =F142-G142 -> 0 | I142: TRUE | J142: PENDIENTE | K142: =A142+15 -> 45992 | L142: =A142+30 -> 46007
A143: 45940 | B143: JEAN | C143: SONICO MEGUMIN | D143: MARZO | E143: 201 | F143: 1050 | G143: =715 -> 715 | H143: =F143-G143 -> 335 | I143: FALSE | J143: PREVENTA | K143: =A143+15 -> 45955 | L143: =A143+30 -> 45970
A144: 45941 | B144: JEAN | C144: MAKIMA | D144: STOCK | E144: 0 | F144: 40 | G144: 40 | H144: =F144-G144 -> 0 | I144: FALSE | J144: PENDIENTE | K144: =A144+15 -> 45956 | L144: =A144+30 -> 45971
A145: 45951 | B145: JEAN | C145: CABALLA GORRA | D145: FEBRERO | E145: 165 | F145: 45 | G145: 45 | H145: =F145-G145 -> 0 | I145: FALSE | J145: PENDIENTE | K145: =A145+15 -> 45966 | L145: =A145+30 -> 45981
A146: 45925 | B146: KHALI | C146: GACHAPONES NAKA | D146: STOCK | F146: 120 | G146: 120 | H146: =F146-G146 -> 0 | I146: TRUE | J146: PENDIENTE | K146: =A146+15 -> 45940 | L146: =A146+30 -> 45955
A147: 45988 | B147: OSCAR RAMIREZ | C147: GANCHITO CHIBI | D147: STOCK | E147: 0 | F147: 30 | G147: 30 | H147: =F147-G147 -> 0 | I147: TRUE | J147: PENDIENTE | K147: =A147+15 -> 46003 | L147: =A147+30 -> 46018
A148: 45936 | B148: RENZO | C148: GARP | D148: DICIEMBRE | E148: 0 | F148: 55 | G148: 55 | H148: =F148-G148 -> 0 | I148: TRUE | J148: PENDIENTE | K148: =A148+15 -> 45951 | L148: =A148+30 -> 45966
A149: 45956 | B149: JEAN | C149: DENJI | D149: STOCK | E149: 0 | F149: 38 | G149: 38 | H149: =F149-G149 -> 0 | I149: FALSE | J149: PENDIENTE | K149: =A149+15 -> 45971 | L149: =A149+30 -> 45986 | P149: gintoki
A150: 45972 | B150: JEAN | C150: LLAVERO BOCHI DE ROCK | D150: STOCK | E150: 0 | F150: 15 | G150: 15 | H150: =F150-G150 -> 0 | I150: FALSE | J150: PENDIENTE | K150: =A150+15 -> 45987 | L150: =A150+30 -> 46002
A151: 46012 | B151: JEAN MIKU NOVIA | C151: MIKU NOVIA | D151: STOCK | E151: 0 | F151: 30 | G151: 30 | H151: =F151-G151 -> 0 | I151: FALSE | J151: PENDIENTE | K151: =A151+15 -> 46027 | L151: =A151+30 -> 46042
A152: 45968 | B152: LENY | C152: GETO | D152: STOCK | E152: 0 | F152: 50 | G152: 50 | H152: =F152-G152 -> 0 | I152: TRUE | J152: PENDIENTE | K152: =A152+15 -> 45983 | L152: =A152+30 -> 45998
A153: 46012 | B153: JORGE | C153: ZOMBIFRANKY | D153: STOCK | E153: 0 | F153: 90 | G153: 10 | H153: =F153-G153 -> 80 | I153: FALSE | J153: PENDIENTE | K153: =A153+15 -> 46027 | L153: =A153+30 -> 46042
A154: 45929 | B154: JORGEPEDRO | C154: GATA DESKTOP CUTE | D154: ENERO | E154: 0 | F154: 60 | G154: 30 | H154: =F154-G154 -> 30 | I154: FALSE | J154: PENDIENTE | K154: =A154+15 -> 45944 | L154: =A154+30 -> 45959
A155: 45978 | B155: JER | C155: GOGETA SS2 | D155: STOCK | E155: 0 | F155: 75 | G155: 75 | H155: =F155-G155 -> 0 | I155: TRUE | J155: PENDIENTE | K155: =A155+15 -> 45993 | L155: =A155+30 -> 46008
A156: 45985 | B156: DIXON | C156: GOHAN | D156: STOCK | E156: 0 | F156: 35 | G156: 35 | H156: =F156-G156 -> 0 | I156: TRUE | J156: PENDIENTE | K156: =A156+15 -> 46000 | L156: =A156+30 -> 46015
A157: 45973 | B157: NANALI ROS | C157: GOJO | D157: STOCK | E157: 0 | F157: 55 | G157: 55 | H157: =F157-G157 -> 0 | I157: TRUE | J157: PENDIENTE | K157: =A157+15 -> 45988 | L157: =A157+30 -> 46003
A158: 45929 | B158: JORGEPEDRO | C158: MONA CHICHONA | D158: ENERO | E158: 0 | F158: 60 | G158: 60 | H158: =F158-G158 -> 0 | I158: FALSE | J158: PENDIENTE | K158: =A158+15 -> 45944 | L158: =A158+30 -> 45959
A159: 45923 | B159: SCARLEX | C159: GOJO SUELTO | D159: STOCK | E159: 0 | F159: 35 | G159: 35 | H159: =F159-G159 -> 0 | I159: TRUE | J159: PENDIENTE | K159: =A159+15 -> 45938 | L159: =A159+30 -> 45953
A160: 45980 | B160: JORDANO | C160: GOKU HAMME | D160: STOCK | E160: 0 | F160: 60 | G160: 60 | H160: =F160-G160 -> 0 | I160: TRUE | J160: PENDIENTE | K160: =A160+15 -> 45995 | L160: =A160+30 -> 46010
A161: 46012 | B161: KAEL | C161: GOKU SCULTURE | D161: STOCK | E161: 0 | F161: 67.5 | G161: 67.5 | H161: =F161-G161 -> 0 | I161: TRUE | J161: PENDIENTE | K161: =A161+15 -> 46027 | L161: =A161+30 -> 46042
... A170: 46003 | B170: ANDRES79 | C170: GYUTARO | D170: STOCK | E170: 0 | F170: 55 | G170: 55 | H170: =F170-G170 -> 0 | I170: TRUE | J170: PENDIENTE | K170: =A170+15 -> 46018 | L170: =A170+30 -> 46033
A171: 45948 | B171: KHALED | C171: 17 UMAS | D171: FEBRERO | E171: 165 | F171: =17*45 -> 765 | G171: =17*45 -> 765 | H171: =F171-G171 -> 0 | I171: FALSE | J171: PREVENTA | K171: =A171+15 -> 45963 | L171: =A171+30 -> 45978
A172: 46009 | B172: KIARA | C172: DEKU CAJA | D172: STOCK | E172: 0 | F172: 50 | G172: 50 | H172: =F172-G172 -> 0 | I172: FALSE | J172: PENDIENTE | K172: =A172+15 -> 46024 | L172: =A172+30 -> 46039
A173: 46010 | B173: KIARA | C173: RENGOKU ARRODILLADO | D173: STOCK | E173: 0 | F173: 50 | G173: 50 | H173: =F173-G173 -> 0 | I173: FALSE | J173: PENDIENTE | K173: =A173+15 -> 46025 | L173: =A173+30 -> 46040
A174: 46014 | B174: KIARA | C174: MUZAN | D174: STOCK | E174: 0 | F174: 45 | G174: 5 | H174: =F174-G174 -> 40 | I174: FALSE | J174: PENDIENTE | K174: =A174+15 -> 46029 | L174: =A174+30 -> 46044
A175: 46014 | B175: KIARA | C175: SABITO | D175: STOCK | E175: 0 | F175: 45 | G175: 45 | H175: =F175-G175 -> 0 | I175: FALSE | J175: PENDIENTE | K175: =A175+15 -> 46029 | L175: =A175+30 -> 46044
...

Sheet CUENTAS 2026
B1: CUENTAS | D1: TOTALSUB | E1: 3223.99
A2: FECHA | B2: CLIENTE | C2: FIGURA | D2: MES | E2: LOTE | F2: PRECIO | G2: ADELANTO | H2: RESTANTE | I2: ENTREGADO | J2: TIPO DE ENTR | K2: FECHA LIMITE | L2: ALMACEN | M2: BASE
A3: 46124 | B3: 17JEAN | C3: REI NEGRA | D3: STOCK | E3: REMATE | F3: 30 | G3: 30 | H3: =F3-G3 -> 0 | I3: FALSE | J3: PENDIENTE | K3: =A3+15 -> 46139 | L3: =A3+30 -> 46154 | M3: FALSE
A4: 46124 | B4: 17JEAN | C4: DUO G5 V LUCCI + ICHIBAN | D4: STOCK | E4: 0 | F4: 180 | G4: 180 | H4: =F4-G4 -> 0 | I4: FALSE | J4: PENDIENTE | K4: =A4+15 -> 46139 | L4: =A4+30 -> 46154 | M4: FALSE
A5: 46052 | B5: A | C5: SHANKS+LAW GRAND | D5: STOCK | E5: 0 | F5: 120 | G5: 120 | H5: =F5-G5 -> 0 | I5: TRUE | J5: PENDIENTE | K5: =A5+15 -> 46067 | L5: =A5+30 -> 46082
A6: 46196 | B6: AARON | C6: GOJO CAMISA BLANCA + FERN SENTADA + REM CHIQUITA | D6: STOCK | E6: CAJA | F6: 170 | G6: 30 | H6: =F6-G6 -> 140 | I6: FALSE | J6: PENDIENTE | K6: =A6+15 -> 46211 | L6: =A6+30 -> 46226
A7: 46146 | B7: ADRIAN | C7: SHIGARAKI CAJA | D7: STOCK | E7: 0 | F7: 55 | G7: 55 | H7: =F7-G7 -> 0 | I7: TRUE | J7: PENDIENTE | K7: =A7+15 -> 46161 | L7: =A7+30 -> 46176
A8: 46147 | B8: ADRIAN | C8: CELL | D8: STOCK | E8: CAJA | F8: 60 | G8: 60 | H8: =F8-G8 -> 0 | I8: TRUE | J8: PENDIENTE | K8: =A8+15 -> 46162 | L8: =A8+30 -> 46177
A9: 46023 | B9: AGOS | C9: LUMINASTA CHICA HIELO | D9: AGOSTO | E9: 473 | F9: 40 | G9: 0 | H9: =F9-G9 -> 40 | I9: FALSE | J9: PENDIENTE
A10: 46135 | B10: AGOS | C10: BARBA BLANCA SIN ARMA | D10: STOCK | E10: REMATE | F10: 20 | G10: 20 | H10: =F10-G10 -> 0 | I10: TRUE | J10: PENDIENTE | K10: =A10+15 -> 46150 | L10: =A10+30 -> 46165 | M10: FALSE
A11: 46135 | B11: AGOS | C11: ANYA QPOSKET | D11: STOCK | E11: REMATE | F11: 10 | G11: 10 | H11: =F11-G11 -> 0 | I11: TRUE | J11: PENDIENTE | K11: =A11+15 -> 46150 | L11: =A11+30 -> 46165 | M11: FALSE
A12: 46135 | B12: AGOS | C12: REM VESTIDO | D12: STOCK | E12: REMATE | F12: 34 | G12: 34 | H12: =F12-G12 -> 0 | I12: TRUE | J12: PENDIENTE | K12: =A12+15 -> 46150 | L12: =A12+30 -> 46165 | M12: TRUE
A13: 46166 | B13: AGOS | C13: NICO LOVELIVE | D13: STOCK | E13: SUELTA | F13: 43 | G13: 43 | H13: =F13-G13 -> 0 | I13: FALSE | J13: PENDIENTE | K13: =A13+15 -> 46181 | L13: =A13+30 -> 46196 | M13: QUINCENA -19
A14: 46166 | B14: AGOS | C14: CONEJA BLANCA | D14: STOCK | E14: CAJA | F14: 56 | G14: 56 | H14: =F14-G14 -> 0 | I14: FALSE | J14: PENDIENTE | K14: =A14+15 -> 46181 | L14: =A14+30 -> 46196 | M14: QUINCENA -19
A15: 46187 | B15: AGOS | C15: MERCURI | D15: STOCK | E15: SUELTA | F15: 40 | G15: 40 | H15: =F15-G15 -> 0 | I15: FALSE | J15: PENDIENTE | K15: =A15+15 -> 46202 | L15: =A15+30 -> 46217
A16: 46187 | B16: AGOS | C16: ROBOT EQUUUX | D16: STOCK | E16: CAJA | F16: 60 | G16: 1 | H16: =F16-G16 -> 59 | I16: FALSE | J16: PENDIENTE | K16: =A16+15 -> 46202 | L16: =A16+30 -> 46217
A17: 46190 | B17: AGOS | C17: CONEJA TRILLIZAS | D17: STOCK | E17: SUELTA | F17: 33 | G17: 0 | H17: =F17-G17 -> 33 | I17: FALSE | J17: PENDIENTE | K17: =A17+15 -> 46205 | L17: =A17+30 -> 46220
A18: 46192 | B18: AGOS | C18: RELAX MORADA HOLO | D18: STOCK | E18: CAJA | F18: 56 | G18: 0 | H18: =F18-G18 -> 56 | I18: FALSE | J18: PENDIENTE | K18: =A18+15 -> 46207 | L18: =A18+30 -> 46222
A19: 46192 | B19: AGOS | C19: CONEJA HERMANA ALBINA | D19: STOCK | E19: CAJA | F19: 62 | G19: 0 | H19: =F19-G19 -> 62 | I19: FALSE | J19: PENDIENTE | K19: =A19+15 -> 46207 | L19: =A19+30 -> 46222
A20: 46124 | B20: AGOS | C20: GUERRERA PELIVERDE | D20: STOCK | E20: REMATE | F20: 15 | G20: 15 | H20: =F20-G20 -> 0 | I20: TRUE | J20: PENDIENTE | K20: =A20+15 -> 46139 | L20: =A20+30 -> 46154 | M20: FALSE
A21: 46124 | B21: AGOS | C21: NIKKE GATITA | D21: STOCK | E21: REMATE | F21: 25 | G21: 25 | H21: =F21-G21 -> 0 | I21: TRUE | J21: PENDIENTE | K21: =A21+15 -> 46139 | L21: =A21+30 -> 46154 | M21: FALSE
A22: 46124 | B22: AGOS | C22: RUBIA GUNDAM | D22: STOCK | E22: REMATE | F22: 29 | G22: 29 | H22: =F22-G22 -> 0 | I22: TRUE | J22: PENDIENTE | K22: =A22+15 -> 46139 | L22: =A22+30 -> 46154 | M22: TRUE
A23: 46124 | B23: AGOS | C23: MADOKA SIN MANO | D23: STOCK | E23: REMATE | F23: 15 | G23: 15 | H23: =F23-G23 -> 0 | I23: TRUE | J23: PENDIENTE | K23: =A23+15 -> 46139 | L23: =A23+30 -> 46154 | M23: FALSE
A24: 46124 | B24: AGOS | C24: RLOVELIVE | D24: STOCK | E24: REMATE | F24: 25 | G24: 25 | H24: =F24-G24 -> 0 | I24: TRUE | J24: PENDIENTE | K24: =A24+15 -> 46139 | L24: =A24+30 -> 46154 | M24: FALSE
A25: 46124 | B25: AGOS | C25: LOVELIVEPELIMORADA | D25: STOCK | E25: REMATE | F25: 24 | G25: 24 | H25: =F25-G25 -> 0 | I25: TRUE | J25: PENDIENTE | K25: =A25+15 -> 46139 | L25: =A25+30 -> 46154 | M25: TRUE
A26: 46124 | B26: AGOS | C26: SHIRAHOSHI GLITTER | D26: STOCK | E26: REMATE | F26: 25 | G26: 25 | H26: =F26-G26 -> 0 | I26: TRUE | J26: PENDIENTE | K26: =A26+15 -> 46139 | L26: =A26+30 -> 46154 | M26: FALSE
A27: 46124 | B27: AGOS | C27: MIKU GITANA | D27: STOCK | E27: REMATE | F27: 15 | G27: 15 | H27: =F27-G27 -> 0 | I27: TRUE | J27: PENDIENTE | K27: =A27+15 -> 46139 | L27: =A27+30 -> 46154 | M27: FALSE
A28: 46124 | B28: AGOS | C28: MIKU 12 AÑOS | D28: STOCK | E28: REMATE | F28: 15 | G28: 15 | H28: =F28-G28 -> 0 | I28: TRUE | J28: PENDIENTE | K28: =A28+15 -> 46139 | L28: =A28+30 -> 46154 | M28: FALSE
A29: 46124 | B29: AGOS | C29: CABALLA ROPA CHILL | D29: STOCK | E29: REMATE | F29: 29 | G29: 29 | H29: =F29-G29 -> 0 | I29: TRUE | J29: PENDIENTE | K29: =A29+15 -> 46139 | L29: =A29+30 -> 46154 | M29: TRUE
A30: 46124 | B30: AGOS | C30: BARCO SIN PIE | D30: STOCK | E30: REMATE | F30: 15 | G30: 15 | H30: =F30-G30 -> 0 | I30: TRUE | J30: PENDIENTE | K30: =A30+15 -> 46139 | L30: =A30+30 -> 46154 | M30: FALSE
A31: 46124 | B31: AGOS | C31: SAKURA GATITA S | D31: STOCK | E31: REMATE | F31: 10 | G31: 10 | H31: =F31-G31 -> 0 | I31: TRUE | J31: PENDIENTE | K31: =A31+15 -> 46139 | L31: =A31+30 -> 46154 | M31: FALSE
... A34: 46125 | B34: AGOS | C34: LL VEST ROJO PELO NARA | D34: STOCK | E34: REMATE | F34: 24 | G34: 24 | H34: =F34-G34 -> 0 | I34: TRUE | J34: PENDIENTE | K34: =A34+15 -> 46140 | L34: =A34+30 -> 46155 | M34: TRUE
A35: 46023 | B35: AGOS | C35: PELIROJA EQUUUUX | D35: AGOSTO | E35: 473 | F35: 35 | G35: 0 | H35: =F35-G35 -> 35 | I35: FALSE | J35: PENDIENTE
A36: 46143 | B36: AGOS | C36: ALBEDO + SHALTEAR | D36: STOCK | E36: REMATE | F36: 105 | G36: 105 | H36: =F36-G36 -> 0 | I36: TRUE | J36: PENDIENTE | K36: =A36+15 -> 46158 | L36: =A36+30 -> 46173 | M36: FALSE
A37: 46192 | B37: AGOS | C37: RELAX SHINECOLOR | D37: STOCK | E37: CAJA | F37: 41 | G37: 0 | H37: =F37-G37 -> 41 | I37: FALSE | J37: PENDIENTE | K37: =A37+15 -> 46207 | L37: =A37+30 -> 46222
A38: 46192 | B38: AGOS | C38: ICHIKA NAKANO | D38: STOCK | E38: CAJA | F38: 41 | G38: 0 | H38: =F38-G38 -> 41 | I38: FALSE | J38: PENDIENTE | K38: =A38+15 -> 46207 | L38: =A38+30 -> 46222
A39: 46192 | B39: AGOS | C39: NINO BLANCA | D39: STOCK | E39: CAJA | F39: 45 | G39: 0 | H39: =F39-G39 -> 45 | I39: FALSE | J39: PENDIENTE | K39: =A39+15 -> 46207 | L39: =A39+30 -> 46222
A40: 46147 | B40: ALEX | C40: GINTOKI | D40: STOCK | E40: 0 | F40: 55 | G40: 55 | H40: =F40-G40 -> 0 | I40: TRUE | J40: PENDIENTE | K40: =A40+15 -> 46162 | L40: =A40+30 -> 46177
A41: 46154 | B41: ALEX | C41: MIKU LOLITA | D41: STOCK | E41: 0 | F41: 70 | G41: 70 | H41: =F41-G41 -> 0 | I41: TRUE | J41: PENDIENTE | K41: =A41+15 -> 46169 | L41: =A41+30 -> 46184
A42: 46059 | B42: ALEXGP | C42: NAMI PILSEN | D42: STOCK | E42: 0 | F42: 40 | G42: 40 | H42: =F42-G42 -> 0 | I42: TRUE | J42: PENDIENTE | K42: =A42+15 -> 46074 | L42: =A42+30 -> 46089
A43: 46059 | B43: ALEXGP | C43: NESUKO GLITTER | D43: STOCK | E43: 0 | F43: 40 | G43: 40 | H43: =F43-G43 -> 0 | I43: TRUE | J43: PENDIENTE | K43: =A43+15 -> 46074 | L43: =A43+30 -> 46089
A44: 46125 | B44: ALEXGP | C44: MIKU S PELO | D44: STOCK | E44: REMATE | F44: 15 | G44: 15 | H44: =F44-G44 -> 0 | I44: TRUE | J44: PENDIENTE | K44: =A44+15 -> 46140 | L44: =A44+30 -> 46155 | M44: FALSE
A45: 46060 | B45: ALEXUS29 | C45: OSHINOKO ROJA | D45: STOCK | E45: 0 | F45: 45 | G45: 45 | H45: =F45-G45 -> 0 | I45: TRUE | J45: PENDIENTE | K45: =A45+15 -> 46075 | L45: =A45+30 -> 46090
A46: 46152 | B46: ALI PALACIOS | C46: MIRKO LAST ONE | D46: STOCK | E46: 0 | F46: 90 | G46: 90 | H46: =F46-G46 -> 0 | I46: TRUE | J46: PENDIENTE | K46: =A46+15 -> 46167 | L46: =A46+30 -> 46182
A47: 46181 | B47: ALI PALACIOS | C47: TOMIOKA Y NESUKO COMELON | D47: STOCK | E47: SUELTA | F47: 80 | G47: 80 | H47: =F47-G47 -> 0 | I47: TRUE | J47: PENDIENTE | K47: =A47+15 -> 46196 | L47: =A47+30 -> 46211
A48: 46183 | B48: ALI PALACIOS | C48: 3 QPOSKET PRINCESAS | D48: STOCK | E48: SUELTA | F48: 110 | G48: 110 | H48: =F48-G48 -> 0 | I48: TRUE | J48: PENDIENTE | K48: =A48+15 -> 46198 | L48: =A48+30 -> 46213
A49: 46017 | B49: ALPHONSE | C49: UNIFORM PERU | D49: FEBRERO | E49: 174 | F49: 50 | G49: 50 | H49: =F49-G49 -> 0 | I49: TRUE | J49: PENDIENTE | K49: =A49+15 -> 46032 | L49: =A49+30 -> 46047 | M49: FALSE
A50: 46017 | B50: ALPHONSE | C50: GLITTER TO LOVE RU | D50: STOCK | E50: 0 | F50: 65 | G50: 65 | H50: =F50-G50 -> 0 | I50: TRUE | J50: PENDIENTE | K50: =A50+15 -> 46032 | L50: =A50+30 -> 46047 | M50: FALSE
A51: 46021 | B51: ALPHONSE | C51: POSTER SAO | D51: STOCK | E51: 0 | F51: 15 | G51: 15 | H51: =F51-G51 -> 0 | I51: TRUE | J51: PENDIENTE | K51: =A51+15 -> 46036 | L51: =A51+30 -> 46051 | M51: FALSE
A52: 46021 | B52: ALPHONSE | C52: BOLSA POKEMON | D52: STOCK | E52: 0 | F52: 10 | G52: 10 | H52: =F52-G52 -> 0 | I52: TRUE | J52: PENDIENTE | K52: =A52+15 -> 46036 | L52: =A52+30 -> 46051 | M52: FALSE
A53: 46127 | B53: ALPHONSE | C53: DUO SNK | D53: ABRIL | E53: - | F53: 150 | G53: 150 | H53: =F53-G53 -> 0 | I53: TRUE | J53: PENDIENTE | K53: =A53+15 -> 46142 | L53: =A53+30 -> 46157 | M53: FALSE
A54: 46070 | B54: ANATSUKA | C54: QPOSKET NAOMI | D54: STOCK | E54: 0 | F54: 40 | G54: 40 | H54: =F54-G54 -> 0 | I54: TRUE | J54: PENDIENTE | K54: =A54+15 -> 46085 | L54: =A54+30 -> 46100
A55: 46056 | B55: ANDERSONANTICONA | C55: LUM | D55: STOCK | E55: 0 | F55: 55 | G55: 55 | H55: =F55-G55 -> 0 | I55: TRUE | J55: PENDIENTE | K55: =A55+15 -> 46071 | L55: =A55+30 -> 46086
A56: 46060 | B56: ANDRE | C56: NAMI | D56: STOCK | E56: 0 | F56: 36 | G56: 36 | H56: =F56-G56 -> 0 | I56: TRUE | J56: PENDIENTE | K56: =A56+15 -> 46075 | L56: =A56+30 -> 46090 | M56: FALSE
A57: 45945 | B57: ANTHONY | C57: PELUCHE TORCHIK | D57: FEBRERO | E57: 186 | F57: 30 | G57: 30 | H57: =F57-G57 -> 0 | I57: TRUE | J57: PENDIENTE | K57: =A57+15 -> 45960 | L57: =A57+30 -> 45975
A58: 45953 | B58: ANTHONY | C58: PELUCHE TOTODILE | D58: FEBRERO | E58: 186 | F58: 45 | G58: 45 | H58: =F58-G58 -> 0 | I58: TRUE | J58: PENDIENTE | K58: =A58+15 -> 45968 | L58: =A58+30 -> 45983
A59: 46039 | B59: ANTHONY ALVARO | C59: SAKURA | D59: STOCK | E59: 0 | F59: 90 | G59: 90 | H59: =F59-G59 -> 0 | I59: TRUE | J59: PENDIENTE | K59: =A59+15 -> 46054 | L59: =A59+30 -> 46069
A60: 46052 | B60: ANTHONY ALVARO | C60: SAKURA QPOSKET | D60: STOCK | E60: 0 | F60: 40 | G60: 40 | H60: =F60-G60 -> 0 | I60: TRUE | J60: PENDIENTE | K60: =A60+15 -> 46067 | L60: =A60+30 -> 46082
A61: 46052 | B61: ANTHONY ALVARO | C61: MIKU COLETAS | D61: STOCK | E61: 0 | F61: 45 | G61: 45 | H61: =F61-G61 -> 0 | I61: TRUE | J61: PENDIENTE | K61: =A61+15 -> 46067 | L61: =A61+30 -> 46082
A62: 46054 | B62: ANTONELLA R | C62: DUO REM REMATE | D62: STOCK | E62: 0 | F62: 60 | G62: 60 | H62: =F62-G62 -> 0 | I62: TRUE | J62: PENDIENTE | K62: =A62+15 -> 46069 | L62: =A62+30 -> 46084
A63: 46052 | B63: ARANCIEA | C63: PELUCHE MARRON | D63: STOCK | E63: 0 | F63: 90 | G63: 90 | H63: 0 | I63: TRUE | J63: PENDIENTE | K63: =A63+15 -> 46067 | L63: =A63+30 -> 46082 | M63: FALSE
A64: 46052 | B64: ARANCIEA | C64: DR STONE FILES | D64: STOCK | E64: 0 | F64: 25 | G64: 25 | H64: =F64-G64 -> 0 | I64: TRUE | J64: PENDIENTE | K64: =A64+15 -> 46067 | L64: =A64+30 -> 46082 | M64: FALSE
A65: 46075 | B65: ARANCIEA | C65: LLAVERO LOVELIVE X6 | D65: STOCK | E65: 0 | F65: 48 | G65: 48 | H65: =F65-G65 -> 0 | I65: TRUE | J65: PENDIENTE | K65: =A65+15 -> 46090 | L65: =A65+30 -> 46105
A66: 46023 | B66: AGOS | C66: PELINEGRA EQUUUUUX | D66: AGOSTO | E66: 473 | F66: 30 | G66: 0 | H66: =F66-G66 -> 30 | I66: FALSE | J66: PENDIENTE
A67: 46075 | B67: ARANCIEA | C67: LUPIN CARRO | D67: STOCK | E67: 0 | F67: 35 | G67: 35 | H67: =F67-G67 -> 0 | I67: TRUE | J67: PENDIENTE | K67: =A67+15 -> 46090 | L67: =A67+30 -> 46105
A68: 46023 | B68: AGOS | C68: FRIEREN GRANDISTA | D68: JULIO | E68: 433 | F68: 70 | G68: 10 | H68: =F68-G68 -> 60 | I68: FALSE | J68: PENDIENTE
A69: 46023 | B69: AGOS | C69: ALBEDO BECUTE | D69: JULIO | E69: 442 | F69: 75 | G69: 10 | H69: =F69-G69 -> 65 | I69: FALSE | J69: PENDIENTE
A70: 46023 | B70: AGOS | C70: PELIROJO SENTADO | D70: JULIO | E70: 426 | F70: 40 | G70: 0 | H70: =F70-G70 -> 40 | I70: FALSE | J70: PENDIENTE
A71: 46023 | B71: AGOS | C71: AINZ OOAL GOWN | D71: SEPTIEMBRE | E71: 520 | F71: 95 | G71: 0 | H71: =F71-G71 -> 95 | I71: FALSE | J71: PENDIENTE
A72: 46075 | B72: ARANCIEA | C72: IS THE ORDER A RABBIT | D72: STOCK | E72: 0 | F72: 30 | G72: 30 | H72: =F72-G72 -> 0 | I72: TRUE | J72: PENDIENTE | K72: =A72+15 -> 46090 | L72: =A72+30 -> 46105
A73: 46077 | B73: ARANCIEA | C73: BROOK ROSA | D73: STOCK | E73: 0 | F73: 50 | G73: 50 | H73: =F73-G73 -> 0 | I73: TRUE | J73: PENDIENTE | K73: =A73+15 -> 46092 | L73: =A73+30 -> 46107
A74: 46078 | B74: ARANCIEA | C74: CHIBI PELICELESTE | D74: STOCK | E74: 0 | F74: 40 | G74: 40 | H74: =F74-G74 -> 0 | I74: TRUE | J74: PENDIENTE | K74: =A74+15 -> 46093 | L74: =A74+30 -> 46108
A75: 46084 | B75: ARANCIEA | C75: ZORO STYL | D75: STOCK | E75: 0 | F75: 45 | G75: 45 | H75: =F75-G75 -> 0 | I75: TRUE | J75: PENDIENTE | K75: =A75+15 -> 46099 | L75: =A75+30 -> 46114
A76: 46097 | B76: ARANCIEA | C76: PELUCHE MIMIKYU | D76: STOCK | E76: 0 | F76: 55 | G76: 55 | H76: =F76-G76 -> 0 | I76: TRUE | J76: PENDIENTE | K76: =A76+15 -> 46112 | L76: =A76+30 -> 46127
A77: 46097 | B77: ARANCIEA | C77: PINES MIKU | D77: STOCK | E77: 0 | F77: 15 | G77: 15 | H77: =F77-G77 -> 0 | I77: TRUE | J77: PENDIENTE | K77: =A77+15 -> 46112 | L77: =A77+30 -> 46127
A78: 46097 | B78: ARANCIEA | C78: MIKU CAPERUCITA | D78: STOCK | E78: 0 | F78: 70 | G78: 70 | H78: =F78-G78 -> 0 | I78: TRUE | J78: PENDIENTE | K78: =A78+15 -> 46112 | L78: =A78+30 -> 46127
A79: 46102 | B79: ARANCIEA | C79: LOVELIVE PELINEGRA | D79: STOCK | E79: 0 | F79: 15 | G79: 15 | H79: =F79-G79 -> 0 | I79: TRUE | J79: PENDIENTE | K79: =A79+15 -> 46117 | L79: =A79+30 -> 46132
A80: 46102 | B80: ARANCIEA | C80: LUFFY AMERICANO | D80: STOCK | E80: 0 | F80: 65 | G80: 65 | H80: =F80-G80 -> 0 | I80: TRUE | J80: PENDIENTE | K80: =A80+15 -> 46117 | L80: =A80+30 -> 46132
A81: 46102 | B81: ARANCIEA | C81: SANJI ICHIBAN | D81: STOCK | E81: 0 | F81: 65 | G81: 65 | H81: =F81-G81 -> 0 | I81: TRUE | J81: PENDIENTE | K81: =A81+15 -> 46117 | L81: =A81+30 -> 46132
A82: 46135 | B82: ARANCIEA | C82: KURUMI COREFUL | D82: STOCK | E82: 0 | F82: 85 | G82: 85 | H82: =F82-G82 -> 0 | I82: TRUE | J82: PENDIENTE | K82: =A82+15 -> 46150 | L82: =A82+30 -> 46165
A83: 46150 | B83: ARANCIEA | C83: ANDJA APPLEFIELD | D83: STOCK | E83: 0 | F83: 65 | G83: 65 | H83: =F83-G83 -> 0 | I83: TRUE | J83: PENDIENTE | K83: =A83+15 -> 46165 | L83: =A83+30 -> 46180
... A86: 46039 | B86: ARANCIEA | C86: MIKU WINTER | D86: STOCK | E86: 0 | F86: 80 | G86: 80 | H86: =F86-G86 -> 0 | I86: TRUE | J86: PENDIENTE | K86: =A86+15 -> 46054 | L86: =A86+30 -> 46069
A87: 46023 | B87: AGOS | C87: ALBEDO CONEJA BLANCA | D87: SEPTIEMBRE | E87: 530 | F87: 80 | G87: 0 | H87: =F87-G87 -> 80 | I87: FALSE | J87: PENDIENTE
A88: 46039 | B88: ARANCIEA | C88: NAMI EGG | D88: STOCK | E88: 0 | F88: 40 | G88: 40 | H88: =F88-G88 -> 0 | I88: TRUE | J88: PENDIENTE | K88: =A88+15 -> 46054 | L88: =A88+30 -> 46069
A89: 46044 | B89: ARANCIEA | C89: RENGOKU SEPIA | D89: STOCK | E89: 0 | F89: 55 | G89: 55 | H89: =F89-G89 -> 0 | I89: TRUE | J89: PENDIENTE | K89: =A89+15 -> 46059 | L89: =A89+30 -> 46074
A90: 46052 | B90: ARANCIEA | C90: SANJI GACHA | D90: STOCK | E90: 0 | F90: 20 | G90: 20 | H90: =F90-G90 -> 0 | I90: TRUE | J90: PENDIENTE | K90: =A90+15 -> 46067 | L90: =A90+30 -> 46082 | O90: DANIELMILLAR
A91: 46056 | B91: ARANCIEA | C91: ONONOKI + MANDARINO | D91: STOCK | E91: 0 | F91: 80 | G91: 80 | H91: =F91-G91 -> 0 | I91: TRUE | J91: PENDIENTE | K91: =A91+15 -> 46071 | L91: =A91+30 -> 46086 | O91: ANDRE
A92: 46056 | B92: ARANCIEA | C92: CAJA ENANO | D92: STOCK | E92: 0 | F92: 10 | G92: 10 | H92: =F92-G92 -> 0 | I92: TRUE | J92: PENDIENTE | K92: =A92+15 -> 46071 | L92: =A92+30 -> 46086
A93: 46023 | B93: AGOS | C93: AI HOSHINO - PREMIUM FIGURE A1 | D93: SEPTIEMBRE | E93: OD3 | F93: 55 | G93: 0 | H93: =F93-G93 -> 55 | I93: FALSE | J93: PENDIENTE
A94: 46063 | B94: ARANCIEA | C94: SANJI ICHIBAN EGGH | D94: STOCK | E94: 0 | F94: 85 | G94: 85 | H94: =F94-G94 -> 0 | I94: TRUE | J94: PENDIENTE | K94: =A94+15 -> 46078 | L94: =A94+30 -> 46093
A95: 46064 | B95: ARANCIEA | C95: TRIO POTTER | D95: STOCK | E95: 0 | F95: 100 | G95: 100 | H95: =F95-G95 -> 0 | I95: TRUE | J95: PENDIENTE | K95: =A95+15 -> 46079 | L95: =A95+30 -> 46094
A96: 46071 | B96: ARANCIEA | C96: SANJI TOLACA | D96: STOCK | E96: 0 | F96: 40 | G96: 40 | H96: =F96-G96 -> 0 | I96: TRUE | J96: PENDIENTE | K96: =A96+15 -> 46086 | L96: =A96+30 -> 46101
A97: 46075 | B97: ARANCIEA | C97: LLAVERO LOVELIVE X2 | D97: STOCK | E97: 0 | F97: 19 | G97: 19 | H97: =F97-G97 -> 0 | I97: TRUE | J97: PENDIENTE | K97: =A97+15 -> 46090 | L97: =A97+30 -> 46105
A98: 46075 | B98: ARANCIEA | C98: LLAVERO LOVELIVE X3 | D98: STOCK | E98: 0 | F98: 27 | G98: 27 | H98: =F98-G98 -> 0 | I98: TRUE | J98: PENDIENTE | K98: =A98+15 -> 46090 | L98: =A98+30 -> 46105
A99: 46075 | B99: ARANCIEA | C99: LUPIN REGALO | D99: STOCK | E99: 0 | F99: 1 | G99: 1 | H99: =F99-G99 -> 0 | I99: TRUE | J99: PENDIENTE | K99: =A99+15 -> 46090 | L99: =A99+30 -> 46105
A100: 46078 | B100: ARANCIEA | C100: LLAVEROS LL + METAL | D100: STOCK | E100: 0 | F100: 30 | G100: 30 | H100: =F100-G100 -> 0 | I100: TRUE | J100: PENDIENTE | K100: =A100+15 -> 46093 | L100: =A100+30 -> 46108
A101: 46150 | B101: ARANCIEA | C101: NOVIA VESTIDOTE | D101: STOCK | E101: 0 | F101: 55 | G101: 55 | H101: =F101-G101 -> 0 | I101: FALSE | J101: PENDIENTE | K101: =A101+15 -> 46165 | L101: =A101+30 -> 46180
A102: 46152 | B102: ARANCIEA | C102: LICORIS RECOIL DESKTOP | D102: STOCK | E102: 0 | F102: 50 | G102: 50 | H102: =F102-G102 -> 0 | I102: FALSE | J102: PENDIENTE | K102: =A102+15 -> 46167 | L102: =A102+30 -> 46182
A103: 46154 | B103: ARANCIEA | C103: MIKU DIVA + ESPRESTO VEST BLAN | D103: STOCK | E103: 0 | F103: 180 | G103: 180 | H103: =F103-G103 -> 0 | I103: FALSE | J103: PENDIENTE | K103: =A103+15 -> 46169 | L103: =A103+30 -> 46184
A104: 46159 | B104: ARANCIEA | C104: 2 RELAX IDOL + NIKKE TETONA | D104: STOCK | E104: CAJA | F104: 160 | G104: 5 | H104: =F104-G104 -> 155 | I104: FALSE | J104: PENDIENTE | K104: =A104+15 -> 46174 | L104: =A104+30 -> 46189
...

Sheet PREVENTAS
A1: CLIENTE | B1: FIGURA | C1: MES | D1: LOTE | E1: PRECIO | F1: ADELANTO | G1: RESTANTE
A3: 17JEAN | B3: ANYA BREAKTIME | C3: JULIO | D3: 417 | E3: 60 | F3: 10 | G3: =E3-F3 -> 50
A4: AGOS | B4: FRIEREN GRANDISTA | C4: JULIO | D4: 433 | E4: 70 | F4: 10 | G4: =E4-F4 -> 60
A5: AGOS | B5: ALBEDO BECUTE | C5: JULIO | D5: 442 | E5: 75 | F5: 10 | G5: =E5-F5 -> 65
A6: AGOS | B6: PELIROJO SENTADO | C6: JULIO | D6: 426 | E6: 40 | F6: 0 | G6: =E6-F6 -> 40
A7: AGOS | B7: AINZ OOAL GOWN | C7: SEPTIEMBRE | D7: 520 | E7: 95 | F7: 0 | G7: =E7-F7 -> 95
A8: AGOS | B8: ALBEDO CONEJA BLANCA | C8: SEPTIEMBRE | D8: 530 | E8: 80 | F8: 0 | G8: =E8-F8 -> 80
A9: AGOS | B9: AI HOSHINO - PREMIUM FIGURE A1 | C9: SEPTIEMBRE | D9: OD3 | E9: 55 | F9: 0 | G9: =E9-F9 -> 55
A10: AGOS | B10: KANA SAKURAGI & HITOMI KOSHIGAYA | C10: SEPTIEMBRE | D10: OD3 | E10: 80 | F10: 0 | G10: =E10-F10 -> 80
A11: AGOS | B11: TOMOE KOGA - Rascal Does Not Dream of Bunny Girl Senpai | C11: SEPTIEMBRE | D11: OD3 | E11: 40 | F11: 0 | G11: =E11-F11 -> 40
A12: AGOS | B12: RUBIA EN SILLA | C12: SEPTIEMBRE | D12: 539 | E12: 45 | F12: 0 | G12: =E12-F12 -> 45
A13: AGOS | B13: MERCURI WITCH | C13: SEPTIEMBRE | D13: 539 | E13: 40 | F13: 0 | G13: =E13-F13 -> 40
A14: AGOS | B14: GUITARRA STELLAR | C14: SEPTIEMBRE | D14: 535 | E14: 40 | F14: 0 | G14: =E14-F14 -> 40
A15: AGOS | B15: LUMINASTA CHICA HIELO | C15: AGOSTO | D15: 473 | E15: 40 | F15: 0 | G15: =E15-F15 -> 40
A16: AGOS | B16: PELIROJA EQUUUUX | C16: AGOSTO | D16: 473 | E16: 35 | F16: 0 | G16: =E16-F16 -> 35
A17: AGOS | B17: PELINEGRA EQUUUUUX | C17: AGOSTO | D17: 473 | E17: 30 | F17: 0 | G17: =E17-F17 -> 30
A18: AGOS | B18: MADE IN ABYSS COREFUL | C18: SEPTIEMBRE | D18: 521 | E18: 70 | F18: 0 | G18: =E18-F18 -> 70
A19: AGOS | B19: TSUKI VAQUITA GLITTER | C19: SEPTIEMBRE | D19: 521 | E19: 80 | F19: 0 | G19: =E19-F19 -> 80
A20: AGOS | B20: AZUNA BUNNY | C20: SEPTIEMBRE | D20: 539 | E20: 65 | F20: 0 | G20: =E20-F20 -> 65
A21: ALEXGP | B21: MIKU DISCOS | C21: JULIO | D21: 419 | E21: 200 | F21: 0 | G21: =E21-F21 -> 200
A22: ALEXGP | B22: AI OSHINO | C22: JULIO | D22: 417 | E22: 60 | F22: 0 | G22: =E22-F22 -> 60
A23: ANGELITO | B23: UZAKI CHAN BUNNIE | C23: SEPTIEMBRE | D23: 521 | E23: 95 | F23: 0 | G23: =E23-F23 -> 95
A24: ANGELITO | B24: TSUKI VAQUITA GLITTER | C24: AGOSTO | D24: 494 | E24: 55 | F24: 0 | G24: =E24-F24 -> 55
A25: ANTONELLA | B25: REM VESTIDO ALMOHADA | C25: JULIO | D25: 417 | E25: 55
A26: ANTONIO | B26: RELAX TIME 100 NOVIAS | C26: SEPTIEMBRE | D26: OD3 | E26: 90 | F26: 0 | G26: =E26-F26 -> 90
A27: ANTONIO | B27: HAKARI HANAZONO - The 100 Girlfriends | C27: SEPTIEMBRE | D27: OD3 | E27: 80 | F27: 0 | G27: =E27-F27 -> 80
A28: ANTONIO | B28: RUBIA CAJA ROSADA | C28: AGOSTO | D28: 473 | E28: 45 | F28: 0 | G28: =E28-F28 -> 45
A29: ARANCIEA | B29: MIKU AMARILLA | C29: JULIO | D29: 467 | E29: 80 | F29: 10 | G29: =E29-F29 -> 70
A30: ARANCIEA | B30: MIKU CEREZO | C30: JULIO | D30: 467 | E30: 85 | F30: 10 | G30: =E30-F30 -> 75
A31: ARANCIEA | B31: MIKU VERDE NOODLE | C31: SEPTIEMBRE | D31: 530 | E31: 60 | F31: 0 | G31: =E31-F31 -> 60
A32: ARANCIEA | B32: HATSUNE MIKU OUTDOOR | C32: SEPTIEMBRE | D32: 521 | E32: 80 | F32: 0 | G32: =E32-F32 -> 80
A33: ARANCIEA | B33: PELIROSA CUTE OREJITAS | C33: JULIO | D33: 442 | E33: 65 | F33: 0 | G33: =E33-F33 -> 65
A34: ARMILENK | B34: PELUCHE TOP GUN | C34: JULIO | D34: 450 | E34: 60 | F34: 10 | G34: =E34-F34 -> 50
A35: ARMILENK | B35: SATONO SEGA | C35: JULIO | D35: 442 | E35: 75 | F35: 10 | G35: =E35-F35 -> 65
A36: BRATHLY | B36: KEI KARUIZAWA - Classroom of the Elite. | C36: SEPTIEMBRE | D36: OD3 | E36: 40 | F36: 0 | G36: =E36-F36 -> 40
A37: BRATHLY | B37: Yui Kotegawa - To LOVE-Ru Darkness | C37: SEPTIEMBRE | D37: OD3 | E37: 55 | F37: 0 | G37: =E37-F37 -> 55
A38: DANIEL CH | B38: GUILLOTINA | C38: JULIO | D38: 442 | E38: 45 | F38: 10 | G38: =E38-F38 -> 35
A39: DANNY JOAO | B39: DRAGON ROJO YUGI | C39: JULIO | D39: 417 | E39: 70
A40: IKKI | B40: DEMONIO PELIROSA | C40: AGOSTO | D40: 494 | E40: 50 | F40: 0 | G40: =E40-F40 -> 50
A41: IKKI | B41: MIKU X KUROMI | C41: JULIO | D41: 467 | E41: 190 | F41: 0 | G41: =E41-F41 -> 190
A42: JAROLD005 | B42: REZE POPUP | C42: AGOSTO | D42: PEDIDO | E42: 320 | F42: 200 | G42: =E42-F42 -> 120
A43: JAROLD005 | B43: SHALTEAR GLITTER BLANCA | C43: SEPTIEMBRE | D43: 530 | E43: 60 | F43: 10 | G43: =E43-F43 -> 50
A44: JAROLD005 | B44: RUBIA BIKINI ROJO | C44: SEPTIEMBRE | D44: OD3 | E44: 50 | F44: 10 | G44: =E44-F44 -> 40
A45: JAROLD005 | B45: AZUKA SCHOLAR | C45: AGOSTO | D45: 473 | E45: 45 | F45: 0 | G45: =E45-F45 -> 45
A46: JORGE | B46: OKARUN + MOMO | C46: AGOSTO | D46: 498 | E46: 110 | F46: 110 | G46: =E46-F46 -> 0
A47: JORGE | B47: DUO BLEACH | C47: JULIO | D47: 464 | E47: 200 | F47: 200 | G47: =E47-F47 -> 0
A48: JUMROCK | B48: MADE IN ABYSS DESKTOP | C48: SEPTIEMBRE | D48: 521 | E48: 60 | F48: 0 | G48: =E48-F48 -> 60
A49: KITSUNE | B49: KANA CREMITA | C49: AGOSTO | D49: 494 | E49: 50 | F49: 50 | G49: =E49-F49 -> 0
A50: KITSUNE | B50: ALYA GLITTER | C50: SEPTIEMBRE | D50: 530 | E50: 70 | F50: 0 | G50: =E50-F50 -> 70
A51: KITSUNE | B51: TRIO OSHINOKO | C51: SEPTIEMBRE | D51: 539 | E51: 120 | F51: 0 | G51: =E51-F51 -> 120
A52: LASSZEPHYRUM | B52: ALBEDO CONEJA BLANCA | C52: AGOSTO | D52: 494 | E52: 50 | F52: 0 | G52: =E52-F52 -> 50
A53: LOPEZ_10 | B53: TACHYON RELAX TIME | C53: AGOSTO | D53: 488 | E53: 120 | F53: 10 | G53: =E53-F53 -> 110
A54: POLAR | B54: ALBEDO VACA | C54: AGOSTO | D54: 494 | E54: 55 | F54: 10 | G54: =E54-F54 -> 45
A55: POLAR | B55: TORU GLITTER | C55: SEPTIEMBRE | D55: 521 | E55: 99.99 | F55: 0 | G55: =E55-F55 -> 99.99
A56: SANTA | B56: OGURI BANPRESTO EVOVLE | C56: SEPTIEMBRE | D56: 521 | E56: 120 | F56: 0 | G56: =E56-F56 -> 120
... A63: VANCE | B63: ROBIN LADY DXF | C63: SEPTIEMBRE | D63: 515 | E63: 65 | F63: 0 | G63: =E63-F63 -> 65
A64: VANCE | B64: SHIMAKAZE - Kantai Collection | C64: SEPTIEMBRE | D64: OD3 | E64: 50 | F64: 0 | G64: =E64-F64 -> 50
A65: VANCE | B65: LOTE COMPLETO | C65: SEPTIEMBRE | D65: 540 | E65: 1200 | F65: 0 | G65: =E65-F65 -> 1200
A66: VANCE | B66: LOTE COMPLETO | C66: SEPTIEMBRE | D66: 547 | E66: 240 | F66: 0 | G66: =E66-F66 -> 240
A67: WONEJO | B67: UTA NEW GENESIS | C67: JULIO | D67: 377 | E67: 200 | F67: 200 | G67: =E67-F67 -> 0
A68: XLUTON | B68: NARUTO MASCARA | C68: AGOSTO | D68: 487 | E68: 50 | F68: 10 | G68: =E68-F68 -> 40
A69: XLUTON | B69: MIKU ESPRESTO GOD | C69: SEPTIEMBRE | D69: 535 | E69: 80 | F69: 0 | G69: =E69-F69 -> 80
A70: XLUTON | B70: MAOMAO | C70: JULIO | D70: 426 | E70: 65 | F70: 50 | G70: =E70-F70 -> 15
A71: XLUTON | B71: MADOKA | C71: JULIO | D71: 426 | E71: 80 | F71: 10 | G71: =E71-F71 -> 70
A72: XLUTON | B72: FATE VESTIDO | C72: JULIO | D72: 465 | E72: 130 | F72: 130 | G72: =E72-F72 -> 0
